Workbook

Sheet panics
A1: name | B1: go | C1: curr | D1: fair | E1: RFP | F1: RSP | G1: ratio | H1: fund | I1: techn | J1: i1 | K1: i2 | L1: i3 | M1: score | N1: filter | O1: mena | P1: diff | Q1: gny | R1: r | T1: suppos | U1: abs | V1: mom | W1: diff | X1: gny | Y1: r | AA1: suppos | AB1: abs | AC1: mark | AD1: koko
A2: ISPH | B2: =_xlfn.IFNA(INDEX(bf!B:B,MATCH(A2,bf!A:A,0),1),0) -> 9.44 | C2: =INDEX('اسعار الاسهم'!A:L,MATCH(A2,'اسعار الاسهم'!K:K,0),2) -> 11.27 | E2: 1 | G2: =B2/C2 -> 0.83762201 | H2: =19.1/C2-1 -> 0.69476486 | I2: =13/C2-1 -> 0.15350488 | J2: =1-(_xlfn.RANK.EQ(G2,G:G,)-1)/(COUNTIF(G:G,">0")) -> 0.89583333 | K2: =_xlfn.IFNA(1-(_xlfn.RANK.EQ(H2,H:H,)-1)/(COUNTIF(H:H,">0")),0) -> 0.92857143 | L2: =_xlfn.IFNA(1-(_xlfn.RANK.EQ(I2,I:I,)-1)/(COUNTIF(I:I,">0")),0) -> 0.13333333 | M2: =$AG$2*J2+K2 *$AG$3+L2*$AG$4+$AG$5*E2+$AG$6*F2 -> 2.4252381 | N2: =OR(O2<>"",V2<>"") -> TRUE | O2: 6.45 | P2: =IFERROR(T2-O2,"") -> -0.53 | Q2: =IF(P2<>"",IF(ABS(P2)/T2>0.1,"Gny",""),"") | R2: =IF(P2<>"",ABS(P2)/T2,"") -> 0.089527027 | S2: =_xlfn.NUMBERVALUE(S1)+IF(O2,1,0) -> 1 | T2: {=IF(O2,INDEX($AP$2:$AP$21,S2,1),"")} -> 5.92 | U2: =IF(P2<>"",ABS(P2),"") -> 0.53 | V2: 86 | W2: =IFERROR(AA2-V2,"") -> -0.8 | X2: =IF(W2<>"",IF(ABS(W2)/AA2>0.1,"Gny",""),"") | Y2: =IF(W2<>"",ABS(W2)/AA2,"") -> 0.0093896714 | Z2: =_xlfn.NUMBERVALUE(Z1)+IF(V2,1,0) -> 1 | AA2: {=IF(V2,INDEX($AK$2:$AK$20,Z2,1),"")} -> 85.2 | AB2: =IF(W2<>"",ABS(W2),"") -> 0.8 | AC2: 1 | AD2: 1 | AF2: bf | AG2: 0.8 | AI2: 1 | AJ2: =AM2/AM3+(AM3-1)/2*AM22 -> 85.221053 | AK2: =ROUND(AJ2,1) -> 85.2 | AL2: total | AM2: =1225.5+8.9-20 -> 1214.4 | AN2: 1 | AO2: =AR2/AR3+(AR3-1)/2*AR22 -> 5.9178947 | AP2: =ROUND(AO2,2) -> 5.92 | AQ2: total | AR2: =84.33 -> 84.33
A3: HRHO | B3: =_xlfn.IFNA(INDEX(bf!B:B,MATCH(A3,bf!A:A,0),1),0) -> 21.69 | C3: =INDEX('اسعار الاسهم'!A:L,MATCH(A3,'اسعار الاسهم'!K:K,0),2) -> 26.32 | G3: =B3/C3 -> 0.82408815 | H3: =39.4/C3-1 -> 0.49696049 | I3: =38/C3-1 -> 0.443769 | J3: =1-(_xlfn.RANK.EQ(G3,G:G,)-1)/(COUNTIF(G:G,">0")) -> 0.83333333 | K3: =_xlfn.IFNA(1-(_xlfn.RANK.EQ(H3,H:H,)-1)/(COUNTIF(H:H,">0")),0) -> 0.64285714 | L3: =_xlfn.IFNA(1-(_xlfn.RANK.EQ(I3,I:I,)-1)/(COUNTIF(I:I,">0")),0) -> 0.8 | M3: =$AG$2*J3+K3 *$AG$3+L3*$AG$4+$AG$5*E3+$AG$6*F3 -> 1.7895238 | N3: =OR(O3<>"",V3<>"") -> TRUE | O3: 5.96 | P3: =IFERROR(T3-O3,"") -> -0.21 | Q3: =IF(P3<>"",IF(ABS(P3)/T3>0.1,"Gny",""),"") | R3: =IF(P3<>"",ABS(P3)/T3,"") -> 0.036521739 | S3: =_xlfn.NUMBERVALUE(S2)+IF(O3,1,0) -> 2 | T3: {=IF(O3,INDEX($AP$2:$AP$21,S3,1),"")} -> 5.75 | U3: =IF(P3<>"",ABS(P3),"") -> 0.21 | V3: 88.1 | W3: =IFERROR(AA3-V3,"") -> -5.2 | X3: =IF(W3<>"",IF(ABS(W3)/AA3>0.1,"Gny",""),"") | Y3: =IF(W3<>"",ABS(W3)/AA3,"") -> 0.062726176 | Z3: =_xlfn.NUMBERVALUE(Z2)+IF(V3,1,0) -> 2 | AA3: {=IF(V3,INDEX($AK$2:$AK$20,Z3,1),"")} -> 82.9 | AB3: =IF(W3<>"",ABS(W3),"") -> 5.2 | AC3: 1 | AF3: funda | AG3: 1 | AI3: 2 | AJ3: =AJ2-$AM$22 -> 82.853801 | AK3: =ROUND(AJ3,1) -> 82.9 | AL3: count | AM3: 19 | AN3: 2 | AO3: =AO2-$AR$22 -> 5.7535088 | AP3: =ROUND(AO3,2) -> 5.75 | AQ3: count | AR3: 19
A4: ORHD | B4: =_xlfn.IFNA(INDEX(bf!B:B,MATCH(A4,bf!A:A,0),1),0) -> 29.41 | C4: =INDEX('اسعار الاسهم'!A:L,MATCH(A4,'اسعار الاسهم'!K:K,0),2) -> 34.55 | E4: 1 | G4: =B4/C4 -> 0.8512301 | H4: =43/C4-1 -> 0.24457308 | J4: =1-(_xlfn.RANK.EQ(G4,G:G,)-1)/(COUNTIF(G:G,">0")) -> 0.91666667 | K4: =_xlfn.IFNA(1-(_xlfn.RANK.EQ(H4,H:H,)-1)/(COUNTIF(H:H,">0")),0) -> 0.28571429 | L4: =_xlfn.IFNA(1-(_xlfn.RANK.EQ(I4,I:I,)-1)/(COUNTIF(I:I,">0")),0) -> 0 | M4: =$AG$2*J4+K4 *$AG$3+L4*$AG$4+$AG$5*E4+$AG$6*F4 -> 1.7190476 | N4: =OR(O4<>"",V4<>"") -> TRUE | O4: 5.89 | P4: =IFERROR(T4-O4,"") -> -0.3 | Q4: =IF(P4<>"",IF(ABS(P4)/T4>0.1,"Gny",""),"") | R4: =IF(P4<>"",ABS(P4)/T4,"") -> 0.053667263 | S4: =_xlfn.NUMBERVALUE(S3)+IF(O4,1,0) -> 3 | T4: {=IF(O4,INDEX($AP$2:$AP$21,S4,1),"")} -> 5.59 | U4: =IF(P4<>"",ABS(P4),"") -> 0.3 | V4: 87.2 | W4: =IFERROR(AA4-V4,"") -> -6.7 | X4: =IF(W4<>"",IF(ABS(W4)/AA4>0.1,"Gny",""),"") | Y4: =IF(W4<>"",ABS(W4)/AA4,"") -> 0.083229814 | Z4: =_xlfn.NUMBERVALUE(Z3)+IF(V4,1,0) -> 3 | AA4: {=IF(V4,INDEX($AK$2:$AK$20,Z4,1),"")} -> 80.5 | AB4: =IF(W4<>"",ABS(W4),"") -> 6.7 | AC4: 1 | AD4: 1 | AF4: techn | AG4: 0.6 | AI4: 3 | AJ4: =AJ3-$AM$22 -> 80.48655 | AK4: =ROUND(AJ4,1) -> 80.5 | AL4: factor | AM4: =IF(NOW()>DATE(2026,6,5),0.54, IF(NOW()>DATE(2026,6,3),0.53, IF(NOW()>DATE(2026,5,29),0.52, IF(NOW()>DATE(2026,5,27),0.51, IF(NOW()>DATE(2026,5,22),0.5, 0.49))))) -> 0.5 | AN4: 3 | AO4: =AO3-$AR$22 -> 5.5891228 | AP4: =ROUND(AO4,2) -> 5.59 | AQ4: factor | AR4: 0.5
A5: ORAS | B5: =_xlfn.IFNA(INDEX(bf!B:B,MATCH(A5,bf!A:A,0),1),0) -> 0 | C5: =INDEX('اسعار الاسهم'!A:L,MATCH(A5,'اسعار الاسهم'!K:K,0),2) -> 708.01 | E5: 1 | F5: 0.92 | G5: =B5/C5 -> 0 | H5: =890/C5-1 -> 0.25704439 | J5: =1-(_xlfn.RANK.EQ(G5,G:G,)-1)/(COUNTIF(G:G,">0")) -> 0 | K5: =_xlfn.IFNA(1-(_xlfn.RANK.EQ(H5,H:H,)-1)/(COUNTIF(H:H,">0")),0) -> 0.35714286 | L5: =_xlfn.IFNA(1-(_xlfn.RANK.EQ(I5,I:I,)-1)/(COUNTIF(I:I,">0")),0) -> 0 | M5: =$AG$2*J5+K5 *$AG$3+L5*$AG$4+$AG$5*E5+$AG$6*F5 -> 1.7011429 | N5: =OR(O5<>"",V5<>"") -> TRUE | O5: 5.76 | P5: =IFERROR(T5-O5,"") -> -0.34 | Q5: =IF(P5<>"",IF(ABS(P5)/T5>0.1,"Gny",""),"") | R5: =IF(P5<>"",ABS(P5)/T5,"") -> 0.062730627 | S5: =_xlfn.NUMBERVALUE(S4)+IF(O5,1,0) -> 4 | T5: {=IF(O5,INDEX($AP$2:$AP$21,S5,1),"")} -> 5.42 | U5: =IF(P5<>"",ABS(P5),"") -> 0.34 | V5: 84 | W5: =IFERROR(AA5-V5,"") -> -5.9 | X5: =IF(W5<>"",IF(ABS(W5)/AA5>0.1,"Gny",""),"") | Y5: =IF(W5<>"",ABS(W5)/AA5,"") -> 0.075544174 | Z5: =_xlfn.NUMBERVALUE(Z4)+IF(V5,1,0) -> 4 | AA5: {=IF(V5,INDEX($AK$2:$AK$20,Z5,1),"")} -> 78.1 | AB5: =IF(W5<>"",ABS(W5),"") -> 5.9 | AC5: 1 | AD5: 1 | AF5: RFP | AG5: 0.7 | AI5: 4 | AJ5: =AJ4-$AM$22 -> 78.119298 | AK5: =ROUND(AJ5,1) -> 78.1 | AL5: alpha | AM5: =(AM3-1)/2 -> 9 | AN5: 4 | AO5: =AO4-$AR$22 -> 5.4247368 | AP5: =ROUND(AO5,2) -> 5.42 | AQ5: alpha | AR5: =(AR3-1)/2 -> 9
A6: DSCW | B6: =_xlfn.IFNA(INDEX(bf!B:B,MATCH(A6,bf!A:A,0),1),0) -> 0 | C6: =INDEX('اسعار الاسهم'!A:L,MATCH(A6,'اسعار الاسهم'!K:K,0),2) -> 1.74 | E6: 1 | G6: =B6/C6 -> 0 | H6: =3.2/C6-1 -> 0.83908046 | J6: =1-(_xlfn.RANK.EQ(G6,G:G,)-1)/(COUNTIF(G:G,">0")) -> 0 | K6: =_xlfn.IFNA(1-(_xlfn.RANK.EQ(H6,H:H,)-1)/(COUNTIF(H:H,">0")),0) -> 1 | L6: =_xlfn.IFNA(1-(_xlfn.RANK.EQ(I6,I:I,)-1)/(COUNTIF(I:I,">0")),0) -> 0 | M6: =$AG$2*J6+K6 *$AG$3+L6*$AG$4+$AG$5*E6+$AG$6*F6 -> 1.7 | N6: =OR(O6<>"",V6<>"") -> TRUE | O6: 5.19 | P6: =IFERROR(T6-O6,"") -> 0.07 | Q6: =IF(P6<>"",IF(ABS(P6)/T6>0.1,"Gny",""),"") | R6: =IF(P6<>"",ABS(P6)/T6,"") -> 0.013307985 | S6: =_xlfn.NUMBERVALUE(S5)+IF(O6,1,0) -> 5 | T6: {=IF(O6,INDEX($AP$2:$AP$21,S6,1),"")} -> 5.26 | U6: =IF(P6<>"",ABS(P6),"") -> 0.07 | V6: 83.2 | W6: =IFERROR(AA6-V6,"") -> -7.4 | X6: =IF(W6<>"",IF(ABS(W6)/AA6>0.1,"Gny",""),"") | Y6: =IF(W6<>"",ABS(W6)/AA6,"") -> 0.09762533 | Z6: =_xlfn.NUMBERVALUE(Z5)+IF(V6,1,0) -> 5 | AA6: {=IF(V6,INDEX($AK$2:$AK$20,Z6,1),"")} -> 75.8 | AB6: =IF(W6<>"",ABS(W6),"") -> 7.4 | AC6: 1 | AF6: RSP | AG6: 0.7 | AI6: 5 | AJ6: =AJ5-$AM$22 -> 75.752047 | AK6: =ROUND(AJ6,1) -> 75.8 | AM6: =SUM(AB1:AB13)+SUM(AB15:AB180) -> 94.9 | AN6: 5 | AO6: =AO5-$AR$22 -> 5.2603509 | AP6: =ROUND(AO6,2) -> 5.26
A7: OCDI | B7: =_xlfn.IFNA(INDEX(bf!B:B,MATCH(A7,bf!A:A,0),1),0) -> 21.88 | C7: =INDEX('اسعار الاسهم'!A:L,MATCH(A7,'اسعار الاسهم'!K:K,0),2) -> 20.7 | F7: 0.94 | G7: =B7/C7 -> 1.0570048 | J7: =1-(_xlfn.RANK.EQ(G7,G:G,)-1)/(COUNTIF(G:G,">0")) -> 1 | K7: =_xlfn.IFNA(1-(_xlfn.RANK.EQ(H7,H:H,)-1)/(COUNTIF(H:H,">0")),0) -> 0 | L7: =_xlfn.IFNA(1-(_xlfn.RANK.EQ(I7,I:I,)-1)/(COUNTIF(I:I,">0")),0) -> 0 | M7: =$AG$2*J7+K7 *$AG$3+L7*$AG$4+$AG$5*E7+$AG$6*F7 -> 1.458 | N7: =OR(O7<>"",V7<>"") -> TRUE | O7: 4.97 | P7: =IFERROR(T7-O7,"") -> 0.13 | Q7: =IF(P7<>"",IF(ABS(P7)/T7>0.1,"Gny",""),"") | R7: =IF(P7<>"",ABS(P7)/T7,"") -> 0.025490196 | S7: =_xlfn.NUMBERVALUE(S6)+IF(O7,1,0) -> 6 | T7: {=IF(O7,INDEX($AP$2:$AP$21,S7,1),"")} -> 5.1 | U7: =IF(P7<>"",ABS(P7),"") -> 0.13 | V7: 74.3 | W7: =IFERROR(AA7-V7,"") -> -0.9 | X7: =IF(W7<>"",IF(ABS(W7)/AA7>0.1,"Gny",""),"") | Y7: =IF(W7<>"",ABS(W7)/AA7,"") -> 0.01226158 | Z7: =_xlfn.NUMBERVALUE(Z6)+IF(V7,1,0) -> 6 | AA7: {=IF(V7,INDEX($AK$2:$AK$20,Z7,1),"")} -> 73.4 | AB7: =IF(W7<>"",ABS(W7),"") -> 0.9 | AC7: 1 | AD7: 1 | AI7: 6 | AJ7: =AJ6-$AM$22 -> 73.384795 | AK7: =ROUND(AJ7,1) -> 73.4 | AN7: 6 | AO7: =AO6-$AR$22 -> 5.0959649 | AP7: =ROUND(AO7,2) -> 5.1
A8: RAYA | B8: =_xlfn.IFNA(INDEX(bf!B:B,MATCH(A8,bf!A:A,0),1),0) -> 0 | C8: =INDEX('اسعار الاسهم'!A:L,MATCH(A8,'اسعار الاسهم'!K:K,0),2) -> 7.15 | E8: 1 | G8: =B8/C8 -> 0 | H8: =10.8/C8-1 -> 0.51048951 | J8: =1-(_xlfn.RANK.EQ(G8,G:G,)-1)/(COUNTIF(G:G,">0")) -> 0 | K8: =_xlfn.IFNA(1-(_xlfn.RANK.EQ(H8,H:H,)-1)/(COUNTIF(H:H,">0")),0) -> 0.71428571 | L8: =_xlfn.IFNA(1-(_xlfn.RANK.EQ(I8,I:I,)-1)/(COUNTIF(I:I,">0")),0) -> 0 | M8: =$AG$2*J8+K8 *$AG$3+L8*$AG$4+$AG$5*E8+$AG$6*F8 -> 1.4142857 | N8: =OR(O8<>"",V8<>"") -> TRUE | O8: 4.83 | P8: =IFERROR(T8-O8,"") -> 0.1 | Q8: =IF(P8<>"",IF(ABS(P8)/T8>0.1,"Gny",""),"") | R8: =IF(P8<>"",ABS(P8)/T8,"") -> 0.020283976 | S8: =_xlfn.NUMBERVALUE(S7)+IF(O8,1,0) -> 7 | T8: {=IF(O8,INDEX($AP$2:$AP$21,S8,1),"")} -> 4.93 | U8: =IF(P8<>"",ABS(P8),"") -> 0.1 | V8: 71.9 | W8: =IFERROR(AA8-V8,"") -> -0.9 | X8: =IF(W8<>"",IF(ABS(W8)/AA8>0.1,"Gny",""),"") | Y8: =IF(W8<>"",ABS(W8)/AA8,"") -> 0.012676056 | Z8: =_xlfn.NUMBERVALUE(Z7)+IF(V8,1,0) -> 7 | AA8: {=IF(V8,INDEX($AK$2:$AK$20,Z8,1),"")} -> 71 | AB8: =IF(W8<>"",ABS(W8),"") -> 0.9 | AI8: 7 | AJ8: =AJ7-$AM$22 -> 71.017544 | AK8: =ROUND(AJ8,1) -> 71 | AN8: 7 | AO8: =AO7-$AR$22 -> 4.9315789 | AP8: =ROUND(AO8,2) -> 4.93
A9: MTIE | B9: =_xlfn.IFNA(INDEX(bf!B:B,MATCH(A9,bf!A:A,0),1),0) -> 6.8 | C9: =INDEX('اسعار الاسهم'!A:L,MATCH(A9,'اسعار الاسهم'!K:K,0),2) -> 8.79 | F9: 0.96 | G9: =B9/C9 -> 0.77360637 | J9: =1-(_xlfn.RANK.EQ(G9,G:G,)-1)/(COUNTIF(G:G,">0")) -> 0.77083333 | K9: =_xlfn.IFNA(1-(_xlfn.RANK.EQ(H9,H:H,)-1)/(COUNTIF(H:H,">0")),0) -> 0 | L9: =_xlfn.IFNA(1-(_xlfn.RANK.EQ(I9,I:I,)-1)/(COUNTIF(I:I,">0")),0) -> 0 | M9: =$AG$2*J9+K9 *$AG$3+L9*$AG$4+$AG$5*E9+$AG$6*F9 -> 1.2886667 | N9: =OR(O9<>"",V9<>"") -> FALSE | P9: =IFERROR(T9-O9,"") | Q9: =IF(P9<>"",IF(ABS(P9)/T9>0.1,"Gny",""),"") | R9: =IF(P9<>"",ABS(P9)/T9,"") | S9: =_xlfn.NUMBERVALUE(S8)+IF(O9,1,0) -> 7 | T9: {=IF(O9,INDEX($AP$2:$AP$21,S9,1),"")} | U9: =IF(P9<>"",ABS(P9),"") | W9: =IFERROR(AA9-V9,"") | X9: =IF(W9<>"",IF(ABS(W9)/AA9>0.1,"Gny",""),"") | Y9: =IF(W9<>"",ABS(W9)/AA9,"") | Z9: =_xlfn.NUMBERVALUE(Z8)+IF(V9,1,0) -> 7 | AA9: {=IF(V9,INDEX($AK$2:$AK$20,Z9,1),"")} | AB9: =IF(W9<>"",ABS(W9),"") | AI9: 8 | AJ9: =AJ8-$AM$22 -> 68.650292 | AK9: =ROUND(AJ9,1) -> 68.7 | AN9: 8 | AO9: =AO8-$AR$22 -> 4.767193 | AP9: =ROUND(AO9,2) -> 4.77
A10: TMGH | B10: =_xlfn.IFNA(INDEX(bf!B:B,MATCH(A10,bf!A:A,0),1),0) -> 0 | C10: =INDEX('اسعار الاسهم'!A:L,MATCH(A10,'اسعار الاسهم'!K:K,0),2) -> 99.48 | E10: 1 | F10: 0.84 | G10: =B10/C10 -> 0 | J10: =1-(_xlfn.RANK.EQ(G10,G:G,)-1)/(COUNTIF(G:G,">0")) -> 0 | K10: =_xlfn.IFNA(1-(_xlfn.RANK.EQ(H10,H:H,)-1)/(COUNTIF(H:H,">0")),0) -> 0 | L10: =_xlfn.IFNA(1-(_xlfn.RANK.EQ(I10,I:I,)-1)/(COUNTIF(I:I,">0")),0) -> 0 | M10: =$AG$2*J10+K10 *$AG$3+L10*$AG$4+$AG$5*E10+$AG$6*F10 -> 1.288 | N10: =OR(O10<>"",V10<>"") -> TRUE | O10: 4.75 | P10: =IFERROR(T10-O10,"") -> 0.02 | Q10: =IF(P10<>"",IF(ABS(P10)/T10>0.1,"Gny",""),"") | R10: =IF(P10<>"",ABS(P10)/T10,"") -> 0.0041928721 | S10: =_xlfn.NUMBERVALUE(S9)+IF(O10,1,0) -> 8 | T10: {=IF(O10,INDEX($AP$2:$AP$21,S10,1),"")} -> 4.77 | U10: =IF(P10<>"",ABS(P10),"") -> 0.02 | V10: 75.3 | W10: =IFERROR(AA10-V10,"") -> -6.6 | X10: =IF(W10<>"",IF(ABS(W10)/AA10>0.1,"Gny",""),"") | Y10: =IF(W10<>"",ABS(W10)/AA10,"") -> 0.096069869 | Z10: =_xlfn.NUMBERVALUE(Z9)+IF(V10,1,0) -> 8 | AA10: {=IF(V10,INDEX($AK$2:$AK$20,Z10,1),"")} -> 68.7 | AB10: =IF(W10<>"",ABS(W10),"") -> 6.6 | AC10: 1 | AD10: 1 | AI10: 9 | AJ10: =AJ9-$AM$22 -> 66.283041 | AK10: =ROUND(AJ10,1) -> 66.3 | AN10: 9 | AO10: =AO9-$AR$22 -> 4.602807 | AP10: =ROUND(AO10,2) -> 4.6
A11: ORWE | B11: =_xlfn.IFNA(INDEX(bf!B:B,MATCH(A11,bf!A:A,0),1),0) -> 11.06 | C11: =INDEX('اسعار الاسهم'!A:L,MATCH(A11,'اسعار الاسهم'!K:K,0),2) -> 21.84 | F11: 0.9 | G11: =B11/C11 -> 0.50641026 | I11: =30.5/C11-1 -> 0.39652015 | J11: =1-(_xlfn.RANK.EQ(G11,G:G,)-1)/(COUNTIF(G:G,">0")) -> 0.3125 | K11: =_xlfn.IFNA(1-(_xlfn.RANK.EQ(H11,H:H,)-1)/(COUNTIF(H:H,">0")),0) -> 0 | L11: =_xlfn.IFNA(1-(_xlfn.RANK.EQ(I11,I:I,)-1)/(COUNTIF(I:I,">0")),0) -> 0.66666667 | M11: =$AG$2*J11+K11 *$AG$3+L11*$AG$4+$AG$5*E11+$AG$6*F11 -> 1.28 | N11: =OR(O11<>"",V11<>"") -> FALSE | P11: =IFERROR(T11-O11,"") | Q11: =IF(P11<>"",IF(ABS(P11)/T11>0.1,"Gny",""),"") | R11: =IF(P11<>"",ABS(P11)/T11,"") | S11: =_xlfn.NUMBERVALUE(S10)+IF(O11,1,0) -> 8 | T11: {=IF(O11,INDEX($AP$2:$AP$21,S11,1),"")} | U11: =IF(P11<>"",ABS(P11),"") | W11: =IFERROR(AA11-V11,"") | X11: =IF(W11<>"",IF(ABS(W11)/AA11>0.1,"Gny",""),"") | Y11: =IF(W11<>"",ABS(W11)/AA11,"") | Z11: =_xlfn.NUMBERVALUE(Z10)+IF(V11,1,0) -> 8 | AA11: {=IF(V11,INDEX($AK$2:$AK$20,Z11,1),"")} | AB11: =IF(W11<>"",ABS(W11),"") | AI11: 10 | AJ11: =AJ10-$AM$22 -> 63.915789 | AK11: =ROUND(AJ11,1) -> 63.9 | AN11: 10 | AO11: =AO10-$AR$22 -> 4.4384211 | AP11: =ROUND(AO11,2) -> 4.44
A12: AMER | B12: =_xlfn.IFNA(INDEX(bf!B:B,MATCH(A12,bf!A:A,0),1),0) -> 1.67 | C12: =INDEX('اسعار الاسهم'!A:L,MATCH(A12,'اسعار الاسهم'!K:K,0),2) -> 2.57 | F12: 1 | G12: =B12/C12 -> 0.64980545 | J12: =1-(_xlfn.RANK.EQ(G12,G:G,)-1)/(COUNTIF(G:G,">0")) -> 0.60416667 | K12: =_xlfn.IFNA(1-(_xlfn.RANK.EQ(H12,H:H,)-1)/(COUNTIF(H:H,">0")),0) -> 0 | L12: =_xlfn.IFNA(1-(_xlfn.RANK.EQ(I12,I:I,)-1)/(COUNTIF(I:I,">0")),0) -> 0 | M12: =$AG$2*J12+K12 *$AG$3+L12*$AG$4+$AG$5*E12+$AG$6*F12 -> 1.1833333 | N12: =OR(O12<>"",V12<>"") -> TRUE | P12: =IFERROR(T12-O12,"") | Q12: =IF(P12<>"",IF(ABS(P12)/T12>0.1,"Gny",""),"") | R12: =IF(P12<>"",ABS(P12)/T12,"") | S12: =_xlfn.NUMBERVALUE(S11)+IF(O12,1,0) -> 8 | T12: {=IF(O12,INDEX($AP$2:$AP$21,S12,1),"")} | U12: =IF(P12<>"",ABS(P12),"") | V12: 68.1 | W12: =IFERROR(AA12-V12,"") -> -1.8 | X12: =IF(W12<>"",IF(ABS(W12)/AA12>0.1,"Gny",""),"") | Y12: =IF(W12<>"",ABS(W12)/AA12,"") -> 0.027149321 | Z12: =_xlfn.NUMBERVALUE(Z11)+IF(V12,1,0) -> 9 | AA12: {=IF(V12,INDEX($AK$2:$AK$20,Z12,1),"")} -> 66.3 | AB12: =IF(W12<>"",ABS(W12),"") -> 1.8 | AC12: 1 | AI12: 11 | AJ12: =AJ11-$AM$22 -> 61.548538 | AK12: =ROUND(AJ12,1) -> 61.5 | AN12: 11 | AO12: =AO11-$AR$22 -> 4.2740351 | AP12: =ROUND(AO12,2) -> 4.27
A13: SAUD | B13: =_xlfn.IFNA(INDEX(bf!B:B,MATCH(A13,bf!A:A,0),1),0) -> 14.09 | C13: =INDEX('اسعار الاسهم'!A:L,MATCH(A13,'اسعار الاسهم'!K:K,0),2) -> 22.19 | E13: 1 | G13: =B13/C13 -> 0.63497071 | J13: =1-(_xlfn.RANK.EQ(G13,G:G,)-1)/(COUNTIF(G:G,">0")) -> 0.54166667 | K13: =_xlfn.IFNA(1-(_xlfn.RANK.EQ(H13,H:H,)-1)/(COUNTIF(H:H,">0")),0) -> 0 | L13: =_xlfn.IFNA(1-(_xlfn.RANK.EQ(I13,I:I,)-1)/(COUNTIF(I:I,">0")),0) -> 0 | M13: =$AG$2*J13+K13 *$AG$3+L13*$AG$4+$AG$5*E13+$AG$6*F13 -> 1.1333333 | N13: =OR(O13<>"",V13<>"") -> TRUE | O13: 4.62 | P13: =IFERROR(T13-O13,"") -> -0.02 | Q13: =IF(P13<>"",IF(ABS(P13)/T13>0.1,"Gny",""),"") | R13: =IF(P13<>"",ABS(P13)/T13,"") -> 0.0043478261 | S13: =_xlfn.NUMBERVALUE(S12)+IF(O13,1,0) -> 9 | T13: {=IF(O13,INDEX($AP$2:$AP$21,S13,1),"")} -> 4.6 | U13: =IF(P13<>"",ABS(P13),"") -> 0.02 | V13: 70.3 | W13: =IFERROR(AA13-V13,"") -> -6.4 | X13: =IF(W13<>"",IF(ABS(W13)/AA13>0.1,"Gny",""),"") -> Gny | Y13: =IF(W13<>"",ABS(W13)/AA13,"") -> 0.10015649 | Z13: =_xlfn.NUMBERVALUE(Z12)+IF(V13,1,0) -> 10 | AA13: {=IF(V13,INDEX($AK$2:$AK$20,Z13,1),"")} -> 63.9 | AB13: =IF(W13<>"",ABS(W13),"") -> 6.4 | AI13: 12 | AJ13: =AJ12-$AM$22 -> 59.181287 | AK13: =ROUND(AJ13,1) -> 59.2 | AN13: 12 | AO13: =AO12-$AR$22 -> 4.1096491 | AP13: =ROUND(AO13,2) -> 4.11
A14: TAQA | B14: =_xlfn.IFNA(INDEX(bf!B:B,MATCH(A14,bf!A:A,0),1),0) -> 0 | C14: =INDEX('اسعار الاسهم'!A:L,MATCH(A14,'اسعار الاسهم'!K:K,0),2) -> 13.19 | G14: =B14/C14 -> 0 | H14: =20.2/C14-1 -> 0.53146323 | I14: =17.5/C14-1 -> 0.3267627 | J14: =1-(_xlfn.RANK.EQ(G14,G:G,)-1)/(COUNTIF(G:G,">0")) -> 0 | K14: =_xlfn.IFNA(1-(_xlfn.RANK.EQ(H14,H:H,)-1)/(COUNTIF(H:H,">0")),0) -> 0.78571429 | L14: =_xlfn.IFNA(1-(_xlfn.RANK.EQ(I14,I:I,)-1)/(COUNTIF(I:I,">0")),0) -> 0.53333333 | M14: =$AG$2*J14+K14 *$AG$3+L14*$AG$4+$AG$5*E14+$AG$6*F14 -> 1.1057143 | N14: =OR(O14<>"",V14<>"") -> FALSE | P14: =IFERROR(T14-O14,"") | Q14: =IF(P14<>"",IF(ABS(P14)/T14>0.1,"Gny",""),"") | R14: =IF(P14<>"",ABS(P14)/T14,"") | S14: =_xlfn.NUMBERVALUE(S13)+IF(O14,1,0) -> 9 | T14: {=IF(O14,INDEX($AP$2:$AP$21,S14,1),"")} | U14: =IF(P14<>"",ABS(P14),"") | W14: =IFERROR(AA14-V14,"") | X14: =IF(W14<>"",IF(ABS(W14)/AA14>0.1,"Gny",""),"") | Y14: =IF(W14<>"",ABS(W14)/AA14,"") | Z14: =_xlfn.NUMBERVALUE(Z13)+IF(V14,1,0) -> 10 | AA14: {=IF(V14,INDEX($AK$2:$AK$20,Z14,1),"")} | AB14: =IF(W14<>"",ABS(W14),"") | AI14: 13 | AJ14: =AJ13-$AM$22 -> 56.814035 | AK14: =ROUND(AJ14,1) -> 56.8 | AN14: 13 | AO14: =AO13-$AR$22 -> 3.9452632 | AP14: =ROUND(AO14,2) -> 3.95
A15: EFIH | B15: =_xlfn.IFNA(INDEX(bf!B:B,MATCH(A15,bf!A:A,0),1),0) -> 16.07 | C15: =INDEX('اسعار الاسهم'!A:L,MATCH(A15,'اسعار الاسهم'!K:K,0),2) -> 21.76 | G15: =B15/C15 -> 0.73851103 | H15: =30.1/C15-1 -> 0.38327206 | J15: =1-(_xlfn.RANK.EQ(G15,G:G,)-1)/(COUNTIF(G:G,">0")) -> 0.72916667 | K15: =_xlfn.IFNA(1-(_xlfn.RANK.EQ(H15,H:H,)-1)/(COUNTIF(H:H,">0")),0) -> 0.5 | L15: =_xlfn.IFNA(1-(_xlfn.RANK.EQ(I15,I:I,)-1)/(COUNTIF(I:I,">0")),0) -> 0 | M15: =$AG$2*J15+K15 *$AG$3+L15*$AG$4+$AG$5*E15+$AG$6*F15 -> 1.0833333 | N15: =OR(O15<>"",V15<>"") -> TRUE | O15: 2.55 | P15: =IFERROR(T15-O15,"") -> 1.89 | Q15: =IF(P15<>"",IF(ABS(P15)/T15>0.1,"Gny",""),"") -> Gny | R15: =IF(P15<>"",ABS(P15)/T15,"") -> 0.42567568 | S15: =_xlfn.NUMBERVALUE(S14)+IF(O15,1,0) -> 10 | T15: {=IF(O15,INDEX($AP$2:$AP$21,S15,1),"")} -> 4.44 | U15: =IF(P15<>"",ABS(P15),"") -> 1.89 | V15: 23.2 | W15: =IFERROR(AA15-V15,"") -> 38.3 | X15: =IF(W15<>"",IF(ABS(W15)/AA15>0.1,"Gny",""),"") -> Gny | Y15: =IF(W15<>"",ABS(W15)/AA15,"") -> 0.62276423 | Z15: =_xlfn.NUMBERVALUE(Z14)+IF(V15,1,0) -> 11 | AA15: {=IF(V15,INDEX($AK$2:$AK$20,Z15,1),"")} -> 61.5 | AB15: =IF(W15<>"",ABS(W15),"") -> 38.3 | AI15: 14 | AJ15: =AJ14-$AM$22 -> 54.446784 | AK15: =ROUND(AJ15,1) -> 54.4 | AN15: 14 | AO15: =AO14-$AR$22 -> 3.7808772 | AP15: =ROUND(AO15,2) -> 3.78
A16: EHDR | B16: =_xlfn.IFNA(INDEX(bf!B:B,MATCH(A16,bf!A:A,0),1),0) -> 1.71 | C16: =INDEX('اسعار الاسهم'!A:L,MATCH(A16,'اسعار الاسهم'!K:K,0),2) -> 2.26 | G16: =B16/C16 -> 0.75663717 | I16: =3.2/C16-1 -> 0.4159292 | J16: =1-(_xlfn.RANK.EQ(G16,G:G,)-1)/(COUNTIF(G:G,">0")) -> 0.75 | K16: =_xlfn.IFNA(1-(_xlfn.RANK.EQ(H16,H:H,)-1)/(COUNTIF(H:H,">0")),0) -> 0 | L16: =_xlfn.IFNA(1-(_xlfn.RANK.EQ(I16,I:I,)-1)/(COUNTIF(I:I,">0")),0) -> 0.76666667 | M16: =$AG$2*J16+K16 *$AG$3+L16*$AG$4+$AG$5*E16+$AG$6*F16 -> 1.06 | N16: =OR(O16<>"",V16<>"") -> FALSE | P16: =IFERROR(T16-O16,"") | Q16: =IF(P16<>"",IF(ABS(P16)/T16>0.1,"Gny",""),"") | R16: =IF(P16<>"",ABS(P16)/T16,"") | S16: =_xlfn.NUMBERVALUE(S15)+IF(O16,1,0) -> 10 | T16: {=IF(O16,INDEX($AP$2:$AP$21,S16,1),"")} | U16: =IF(P16<>"",ABS(P16),"") | W16: =IFERROR(AA16-V16,"") | X16: =IF(W16<>"",IF(ABS(W16)/AA16>0.1,"Gny",""),"") | Y16: =IF(W16<>"",ABS(W16)/AA16,"") | Z16: =_xlfn.NUMBERVALUE(Z15)+IF(V16,1,0) -> 11 | AA16: {=IF(V16,INDEX($AK$2:$AK$20,Z16,1),"")} | AB16: =IF(W16<>"",ABS(W16),"") | AI16: 15 | AJ16: =AJ15-$AM$22 -> 52.079532 | AK16: =ROUND(AJ16,1) -> 52.1 | AN16: 15 | AO16: =AO15-$AR$22 -> 3.6164912 | AP16: =ROUND(AO16,2) -> 3.62
A17: CLHO | B17: =_xlfn.IFNA(INDEX(bf!B:B,MATCH(A17,bf!A:A,0),1),0) -> 5.96 | C17: =INDEX('اسعار الاسهم'!A:L,MATCH(A17,'اسعار الاسهم'!K:K,0),2) -> 15.19 | E17: 1 | G17: =B17/C17 -> 0.3923634 | H17: =18.9/C17-1 -> 0.24423963 | J17: =1-(_xlfn.RANK.EQ(G17,G:G,)-1)/(COUNTIF(G:G,">0")) -> 0.125 | K17: =_xlfn.IFNA(1-(_xlfn.RANK.EQ(H17,H:H,)-1)/(COUNTIF(H:H,">0")),0) -> 0.21428571 | L17: =_xlfn.IFNA(1-(_xlfn.RANK.EQ(I17,I:I,)-1)/(COUNTIF(I:I,">0")),0) -> 0 | M17: =$AG$2*J17+K17 *$AG$3+L17*$AG$4+$AG$5*E17+$AG$6*F17 -> 1.0142857 | N17: =OR(O17<>"",V17<>"") -> TRUE | O17: 3.92 | P17: =IFERROR(T17-O17,"") -> 0.35 | Q17: =IF(P17<>"",IF(ABS(P17)/T17>0.1,"Gny",""),"") | R17: =IF(P17<>"",ABS(P17)/T17,"") -> 0.081967213 | S17: =_xlfn.NUMBERVALUE(S16)+IF(O17,1,0) -> 11 | T17: {=IF(O17,INDEX($AP$2:$AP$21,S17,1),"")} -> 4.27 | U17: =IF(P17<>"",ABS(P17),"") -> 0.35 | V17: 55.6 | W17: =IFERROR(AA17-V17,"") -> 3.6 | X17: =IF(W17<>"",IF(ABS(W17)/AA17>0.1,"Gny",""),"") | Y17: =IF(W17<>"",ABS(W17)/AA17,"") -> 0.060810811 | Z17: =_xlfn.NUMBERVALUE(Z16)+IF(V17,1,0) -> 12 | AA17: {=IF(V17,INDEX($AK$2:$AK$20,Z17,1),"")} -> 59.2 | AB17: =IF(W17<>"",ABS(W17),"") -> 3.6 | AC17: 1 | AI17: 16 | AJ17: =AJ16-$AM$22 -> 49.712281 | AK17: =ROUND(AJ17,1) -> 49.7 | AN17: 16 | AO17: =AO16-$AR$22 -> 3.4521053 | AP17: =ROUND(AO17,2) -> 3.45
A18: ZMID | B18: =_xlfn.IFNA(INDEX(bf!B:B,MATCH(A18,bf!A:A,0),1),0) -> 3.8 | C18: =INDEX('اسعار الاسهم'!A:L,MATCH(A18,'اسعار الاسهم'!K:K,0),2) -> 5.86 | G18: =B18/C18 -> 0.64846416 | I18: =9/C18-1 -> 0.53583618 | J18: =1-(_xlfn.RANK.EQ(G18,G:G,)-1)/(COUNTIF(G:G,">0")) -> 0.58333333 | K18: =_xlfn.IFNA(1-(_xlfn.RANK.EQ(H18,H:H,)-1)/(COUNTIF(H:H,">0")),0) -> 0 | L18: =_xlfn.IFNA(1-(_xlfn.RANK.EQ(I18,I:I,)-1)/(COUNTIF(I:I,">0")),0) -> 0.86666667 | M18: =$AG$2*J18+K18 *$AG$3+L18*$AG$4+$AG$5*E18+$AG$6*F18 -> 0.98666667 | N18: =OR(O18<>"",V18<>"") -> FALSE | P18: =IFERROR(T18-O18,"") | Q18: =IF(P18<>"",IF(ABS(P18)/T18>0.1,"Gny",""),"") | R18: =IF(P18<>"",ABS(P18)/T18,"") | S18: =_xlfn.NUMBERVALUE(S17)+IF(O18,1,0) -> 11 | T18: {=IF(O18,INDEX($AP$2:$AP$21,S18,1),"")} | U18: =IF(P18<>"",ABS(P18),"") | W18: =IFERROR(AA18-V18,"") | X18: =IF(W18<>"",IF(ABS(W18)/AA18>0.1,"Gny",""),"") | Y18: =IF(W18<>"",ABS(W18)/AA18,"") | Z18: =_xlfn.NUMBERVALUE(Z17)+IF(V18,1,0) -> 12 | AA18: {=IF(V18,INDEX($AK$2:$AK$20,Z18,1),"")} | AB18: =IF(W18<>"",ABS(W18),"") | AI18: 17 | AJ18: =AJ17-$AM$22 -> 47.345029 | AK18: =ROUND(AJ18,1) -> 47.3 | AN18: 17 | AO18: =AO17-$AR$22 -> 3.2877193 | AP18: =ROUND(AO18,2) -> 3.29
A19: SWDY | B19: =_xlfn.IFNA(INDEX(bf!B:B,MATCH(A19,bf!A:A,0),1),0) -> 49.17 | C19: =INDEX('اسعار الاسهم'!A:L,MATCH(A19,'اسعار الاسهم'!K:K,0),2) -> 87.9 | F19: 0.86 | G19: =B19/C19 -> 0.55938567 | J19: =1-(_xlfn.RANK.EQ(G19,G:G,)-1)/(COUNTIF(G:G,">0")) -> 0.4375 | K19: =_xlfn.IFNA(1-(_xlfn.RANK.EQ(H19,H:H,)-1)/(COUNTIF(H:H,">0")),0) -> 0 | L19: =_xlfn.IFNA(1-(_xlfn.RANK.EQ(I19,I:I,)-1)/(COUNTIF(I:I,">0")),0) -> 0 | M19: =$AG$2*J19+K19 *$AG$3+L19*$AG$4+$AG$5*E19+$AG$6*F19 -> 0.952 | N19: =OR(O19<>"",V19<>"") -> FALSE | P19: =IFERROR(T19-O19,"") | Q19: =IF(P19<>"",IF(ABS(P19)/T19>0.1,"Gny",""),"") | R19: =IF(P19<>"",ABS(P19)/T19,"") | S19: =_xlfn.NUMBERVALUE(S18)+IF(O19,1,0) -> 11 | T19: {=IF(O19,INDEX($AP$2:$AP$21,S19,1),"")} | U19: =IF(P19<>"",ABS(P19),"") | W19: =IFERROR(AA19-V19,"") | X19: =IF(W19<>"",IF(ABS(W19)/AA19>0.1,"Gny",""),"") | Y19: =IF(W19<>"",ABS(W19)/AA19,"") | Z19: =_xlfn.NUMBERVALUE(Z18)+IF(V19,1,0) -> 12 | AA19: {=IF(V19,INDEX($AK$2:$AK$20,Z19,1),"")} | AB19: =IF(W19<>"",ABS(W19),"") | AI19: 18 | AJ19: =AJ18-$AM$22 -> 44.977778 | AK19: =ROUND(AJ19,1) -> 45 | AN19: 18 | AO19: =AO18-$AR$22 -> 3.1233333 | AP19: =ROUND(AO19,2) -> 3.12
A20: QNBE | B20: =_xlfn.IFNA(INDEX(bf!B:B,MATCH(A20,bf!A:A,0),1),0) -> 50.91 | C20: =INDEX('اسعار الاسهم'!A:L,MATCH(A20,'اسعار الاسهم'!K:K,0),2) -> 53.39 | G20: =B20/C20 -> 0.95354935 | H20: =64/C20-1 -> 0.19872635 | J20: =1-(_xlfn.RANK.EQ(G20,G:G,)-1)/(COUNTIF(G:G,">0")) -> 0.95833333 | K20: =_xlfn.IFNA(1-(_xlfn.RANK.EQ(H20,H:H,)-1)/(COUNTIF(H:H,">0")),0) -> 0.14285714 | L20: =_xlfn.IFNA(1-(_xlfn.RANK.EQ(I20,I:I,)-1)/(COUNTIF(I:I,">0")),0) -> 0 | M20: =$AG$2*J20+K20 *$AG$3+L20*$AG$4+$AG$5*E20+$AG$6*F20 -> 0.90952381 | N20: =OR(O20<>"",V20<>"") -> TRUE | O20: 4.25 | P20: =IFERROR(T20-O20,"") -> -0.14 | Q20: =IF(P20<>"",IF(ABS(P20)/T20>0.1,"Gny",""),"") | R20: =IF(P20<>"",ABS(P20)/T20,"") -> 0.03406326 | S20: =_xlfn.NUMBERVALUE(S19)+IF(O20,1,0) -> 12 | T20: {=IF(O20,INDEX($AP$2:$AP$21,S20,1),"")} -> 4.11 | U20: =IF(P20<>"",ABS(P20),"") -> 0.14 | V20: 57.4 | W20: =IFERROR(AA20-V20,"") -> -0.6 | X20: =IF(W20<>"",IF(ABS(W20)/AA20>0.1,"Gny",""),"") | Y20: =IF(W20<>"",ABS(W20)/AA20,"") -> 0.01056338 | Z20: =_xlfn.NUMBERVALUE(Z19)+IF(V20,1,0) -> 13 | AA20: {=IF(V20,INDEX($AK$2:$AK$20,Z20,1),"")} -> 56.8 | AB20: =IF(W20<>"",ABS(W20),"") -> 0.6 | AC20: 1 | AD20: 1 | AI20: 19 | AJ20: =AJ19-$AM$22 -> 42.610526 | AK20: =ROUND(AJ20,1) -> 42.6 | AN20: 19 | AO20: =AO19-$AR$22 -> 2.9589474 | AP20: =ROUND(AO20,2) -> 2.96
A21: PHDC | B21: =_xlfn.IFNA(INDEX(bf!B:B,MATCH(A21,bf!A:A,0),1),0) -> 7.5 | C21: =INDEX('اسعار الاسهم'!A:L,MATCH(A21,'اسعار الاسهم'!K:K,0),2) -> 13.61 | F21: 0.88 | G21: =B21/C21 -> 0.55106539 | J21: =1-(_xlfn.RANK.EQ(G21,G:G,)-1)/(COUNTIF(G:G,">0")) -> 0.35416667 | K21: =_xlfn.IFNA(1-(_xlfn.RANK.EQ(H21,H:H,)-1)/(COUNTIF(H:H,">0")),0) -> 0 | L21: =_xlfn.IFNA(1-(_xlfn.RANK.EQ(I21,I:I,)-1)/(COUNTIF(I:I,">0")),0) -> 0 | M21: =$AG$2*J21+K21 *$AG$3+L21*$AG$4+$AG$5*E21+$AG$6*F21 -> 0.89933333 | N21: =OR(O21<>"",V21<>"") -> FALSE | P21: =IFERROR(T21-O21,"") | Q21: =IF(P21<>"",IF(ABS(P21)/T21>0.1,"Gny",""),"") | R21: =IF(P21<>"",ABS(P21)/T21,"") | S21: =_xlfn.NUMBERVALUE(S20)+IF(O21,1,0) -> 12 | T21: {=IF(O21,INDEX($AP$2:$AP$21,S21,1),"")} | U21: =IF(P21<>"",ABS(P21),"") | W21: =IFERROR(AA21-V21,"") | X21: =IF(W21<>"",IF(ABS(W21)/AA21>0.1,"Gny",""),"") | Y21: =IF(W21<>"",ABS(W21)/AA21,"") | Z21: =_xlfn.NUMBERVALUE(Z20)+IF(V21,1,0) -> 13 | AA21: {=IF(V21,INDEX($AK$2:$AK$20,Z21,1),"")} | AB21: =IF(W21<>"",ABS(W21),"")
A22: FWRY | B22: =_xlfn.IFNA(INDEX(bf!B:B,MATCH(A22,bf!A:A,0),1),0) -> 16 | C22: =INDEX('اسعار الاسهم'!A:L,MATCH(A22,'اسعار الاسهم'!K:K,0),2) -> 19.32 | G22: =B22/C22 -> 0.82815735 | I22: =23.5/C22-1 -> 0.21635611 | J22: =1-(_xlfn.RANK.EQ(G22,G:G,)-1)/(COUNTIF(G:G,">0")) -> 0.875 | K22: =_xlfn.IFNA(1-(_xlfn.RANK.EQ(H22,H:H,)-1)/(COUNTIF(H:H,">0")),0) -> 0 | L22: =_xlfn.IFNA(1-(_xlfn.RANK.EQ(I22,I:I,)-1)/(COUNTIF(I:I,">0")),0) -> 0.3 | M22: =$AG$2*J22+K22 *$AG$3+L22*$AG$4+$AG$5*E22+$AG$6*F22 -> 0.88 | N22: =OR(O22<>"",V22<>"") -> FALSE | P22: =IFERROR(T22-O22,"") | Q22: =IF(P22<>"",IF(ABS(P22)/T22>0.1,"Gny",""),"") | R22: =IF(P22<>"",ABS(P22)/T22,"") | S22: =_xlfn.NUMBERVALUE(S21)+IF(O22,1,0) -> 12 | T22: {=IF(O22,INDEX($AP$2:$AP$21,S22,1),"")} | U22: =IF(P22<>"",ABS(P22),"") | W22: =IFERROR(AA22-V22,"") | X22: =IF(W22<>"",IF(ABS(W22)/AA22>0.1,"Gny",""),"") | Y22: =IF(W22<>"",ABS(W22)/AA22,"") | Z22: =_xlfn.NUMBERVALUE(Z21)+IF(V22,1,0) -> 13 | AA22: {=IF(V22,INDEX($AK$2:$AK$20,Z22,1),"")} | AB22: =IF(W22<>"",ABS(W22),"") | AM22: =AM2*(1-AM4)/AM3/(AM5+AM4*AM5) -> 2.3672515 | AR22: =AR2*(1-AR4)/AR3/(AR5+AR4*AR5) -> 0.16438596
A23: MPRC | B23: =_xlfn.IFNA(INDEX(bf!B:B,MATCH(A23,bf!A:A,0),1),0) -> 24.88 | C23: =INDEX('اسعار الاسهم'!A:L,MATCH(A23,'اسعار الاسهم'!K:K,0),2) -> 31.55 | G23: =B23/C23 -> 0.78858954 | I23: =40/C23-1 -> 0.26782884 | J23: =1-(_xlfn.RANK.EQ(G23,G:G,)-1)/(COUNTIF(G:G,">0")) -> 0.8125 | K23: =_xlfn.IFNA(1-(_xlfn.RANK.EQ(H23,H:H,)-1)/(COUNTIF(H:H,">0")),0) -> 0 | L23: =_xlfn.IFNA(1-(_xlfn.RANK.EQ(I23,I:I,)-1)/(COUNTIF(I:I,">0")),0) -> 0.36666667 | M23: =$AG$2*J23+K23 *$AG$3+L23*$AG$4+$AG$5*E23+$AG$6*F23 -> 0.87 | N23: =OR(O23<>"",V23<>"") -> FALSE | Q23: =IF(P23<>"",IF(ABS(P23)/T23>0.1,"Gny",""),"") | R23: =IF(P23<>"",ABS(P23)/T23,"") | S23: =_xlfn.NUMBERVALUE(S22)+IF(O23,1,0) -> 12 | U23: =IF(P23<>"",ABS(P23),"") | W23: =IFERROR(AA23-V23,"") | X23: =IF(W23<>"",IF(ABS(W23)/AA23>0.1,"Gny",""),"") | Y23: =IF(W23<>"",ABS(W23)/AA23,"") | Z23: =_xlfn.NUMBERVALUE(Z22)+IF(V23,1,0) -> 13 | AA23: {=IF(V23,INDEX($AK$2:$AK$20,Z23,1),"")} | AB23: =IF(W23<>"",ABS(W23),"") | AD23: 1
A24: BONY | B24: =_xlfn.IFNA(INDEX(bf!B:B,MATCH(A24,bf!A:A,0),1),0) -> 0 | C24: =INDEX('اسعار الاسهم'!A:L,MATCH(A24,'اسعار الاسهم'!K:K,0),2) -> 4.88 | G24: =B24/C24 -> 0 | H24: =7.6/C24-1 -> 0.55737705 | J24: =1-(_xlfn.RANK.EQ(G24,G:G,)-1)/(COUNTIF(G:G,">0")) -> 0 | K24: =_xlfn.IFNA(1-(_xlfn.RANK.EQ(H24,H:H,)-1)/(COUNTIF(H:H,">0")),0) -> 0.85714286 | L24: =_xlfn.IFNA(1-(_xlfn.RANK.EQ(I24,I:I,)-1)/(COUNTIF(I:I,">0")),0) -> 0 | M24: =$AG$2*J24+K24 *$AG$3+L24*$AG$4+$AG$5*E24+$AG$6*F24 -> 0.85714286 | N24: =OR(O24<>"",V24<>"") -> TRUE | O24: 3.82 | P24: =IFERROR(T24-O24,"") -> 0.13 | Q24: =IF(P24<>"",IF(ABS(P24)/T24>0.1,"Gny",""),"") | R24: =IF(P24<>"",ABS(P24)/T24,"") -> 0.032911392 | S24: =_xlfn.NUMBERVALUE(S23)+IF(O24,1,0) -> 13 | T24: {=IF(O24,INDEX($AP$2:$AP$21,S24,1),"")} -> 3.95 | U24: =IF(P24<>"",ABS(P24),"") -> 0.13 | V24: 55.5 | W24: =IFERROR(AA24-V24,"") -> -1.1 | X24: =IF(W24<>"",IF(ABS(W24)/AA24>0.1,"Gny",""),"") | Y24: =IF(W24<>"",ABS(W24)/AA24,"") -> 0.020220588 | Z24: =_xlfn.NUMBERVALUE(Z23)+IF(V24,1,0) -> 14 | AA24: {=IF(V24,INDEX($AK$2:$AK$20,Z24,1),"")} -> 54.4 | AB24: =IF(W24<>"",ABS(W24),"") -> 1.1 | AC24: 1 | AD24: 1
A25: ENGC | B25: =_xlfn.IFNA(INDEX(bf!B:B,MATCH(A25,bf!A:A,0),1),0) -> 20.74 | C25: =INDEX('اسعار الاسهم'!A:L,MATCH(A25,'اسعار الاسهم'!K:K,0),2) -> 32.76 | G25: =B25/C25 -> 0.63308913 | H25: =44/C25-1 -> 0.34310134 | J25: =1-(_xlfn.RANK.EQ(G25,G:G,)-1)/(COUNTIF(G:G,">0")) -> 0.52083333 | K25: =_xlfn.IFNA(1-(_xlfn.RANK.EQ(H25,H:H,)-1)/(COUNTIF(H:H,">0")),0) -> 0.42857143 | L25: =_xlfn.IFNA(1-(_xlfn.RANK.EQ(I25,I:I,)-1)/(COUNTIF(I:I,">0")),0) -> 0 | M25: =$AG$2*J25+K25 *$AG$3+L25*$AG$4+$AG$5*E25+$AG$6*F25 -> 0.8452381 | N25: =OR(O25<>"",V25<>"") -> TRUE | O25: 3.87 | P25: =IFERROR(T25-O25,"") -> -0.09 | Q25: =IF(P25<>"",IF(ABS(P25)/T25>0.1,"Gny",""),"") | R25: =IF(P25<>"",ABS(P25)/T25,"") -> 0.023809524 | S25: =_xlfn.NUMBERVALUE(S24)+IF(O25,1,0) -> 14 | T25: {=IF(O25,INDEX($AP$2:$AP$21,S25,1),"")} -> 3.78 | U25: =IF(P25<>"",ABS(P25),"") -> 0.09 | W25: =IFERROR(AA25-V25,"") | X25: =IF(W25<>"",IF(ABS(W25)/AA25>0.1,"Gny",""),"") | Y25: =IF(W25<>"",ABS(W25)/AA25,"") | Z25: =_xlfn.NUMBERVALUE(Z24)+IF(V25,1,0) -> 14 | AA25: {=IF(V25,INDEX($AK$2:$AK$20,Z25,1),"")} | AB25: =IF(W25<>"",ABS(W25),"")
A26: CIEB | B26: =_xlfn.IFNA(INDEX(bf!B:B,MATCH(A26,bf!A:A,0),1),0) -> 22.46 | C26: =INDEX('اسعار الاسهم'!A:L,MATCH(A26,'اسعار الاسهم'!K:K,0),2) -> 23.41 | G26: =B26/C26 -> 0.95941905 | J26: =1-(_xlfn.RANK.EQ(G26,G:G,)-1)/(COUNTIF(G:G,">0")) -> 0.97916667 | K26: =_xlfn.IFNA(1-(_xlfn.RANK.EQ(H26,H:H,)-1)/(COUNTIF(H:H,">0")),0) -> 0 | L26: =_xlfn.IFNA(1-(_xlfn.RANK.EQ(I26,I:I,)-1)/(COUNTIF(I:I,">0")),0) -> 0 | M26: =$AG$2*J26+K26 *$AG$3+L26*$AG$4+$AG$5*E26+$AG$6*F26 -> 0.78333333 | N26: =OR(O26<>"",V26<>"") -> FALSE | P26: =IFERROR(T26-O26,"") | Q26: =IF(P26<>"",IF(ABS(P26)/T26>0.1,"Gny",""),"") | R26: =IF(P26<>"",ABS(P26)/T26,"") | S26: =_xlfn.NUMBERVALUE(S25)+IF(O26,1,0) -> 14 | T26: {=IF(O26,INDEX($AP$2:$AP$21,S26,1),"")} | U26: =IF(P26<>"",ABS(P26),"") | W26: =IFERROR(AA26-V26,"") | X26: =IF(W26<>"",IF(ABS(W26)/AA26>0.1,"Gny",""),"") | Y26: =IF(W26<>"",ABS(W26)/AA26,"") | Z26: =_xlfn.NUMBERVALUE(Z25)+IF(V26,1,0) -> 14 | AA26: {=IF(V26,INDEX($AK$2:$AK$20,Z26,1),"")} | AB26: =IF(W26<>"",ABS(W26),"")
A27: COMI | B27: =_xlfn.IFNA(INDEX(bf!B:B,MATCH(A27,bf!A:A,0),1),0) -> 115.7 | C27: =INDEX('اسعار الاسهم'!A:L,MATCH(A27,'اسعار الاسهم'!K:K,0),2) -> 132.35 | G27: =B27/C27 -> 0.8741972 | J27: =1-(_xlfn.RANK.EQ(G27,G:G,)-1)/(COUNTIF(G:G,">0")) -> 0.9375 | K27: =_xlfn.IFNA(1-(_xlfn.RANK.EQ(H27,H:H,)-1)/(COUNTIF(H:H,">0")),0) -> 0 | L27: =_xlfn.IFNA(1-(_xlfn.RANK.EQ(I27,I:I,)-1)/(COUNTIF(I:I,">0")),0) -> 0 | M27: =$AG$2*J27+K27 *$AG$3+L27*$AG$4+$AG$5*E27+$AG$6*F27 -> 0.75 | N27: =OR(O27<>"",V27<>"") -> FALSE | P27: =IFERROR(T27-O27,"") | Q27: =IF(P27<>"",IF(ABS(P27)/T27>0.1,"Gny",""),"") | R27: =IF(P27<>"",ABS(P27)/T27,"") | S27: =_xlfn.NUMBERVALUE(S26)+IF(O27,1,0) -> 14 | T27: {=IF(O27,INDEX($AP$2:$AP$21,S27,1),"")} | U27: =IF(P27<>"",ABS(P27),"") | W27: =IFERROR(AA27-V27,"") | X27: =IF(W27<>"",IF(ABS(W27)/AA27>0.1,"Gny",""),"") | Y27: =IF(W27<>"",ABS(W27)/AA27,"") | Z27: =_xlfn.NUMBERVALUE(Z26)+IF(V27,1,0) -> 14 | AA27: {=IF(V27,INDEX($AK$2:$AK$20,Z27,1),"")} | AB27: =IF(W27<>"",ABS(W27),"") | AM27: =SUM(AB:AB)/SUM(V:V)*100 -> 7.743778 | AR27: =SUM(U:U)/SUM(O:O)*100 -> 6.3461768
A28: JUFO | B28: =_xlfn.IFNA(INDEX(bf!B:B,MATCH(A28,bf!A:A,0),1),0) -> 13.06 | C28: =INDEX('اسعار الاسهم'!A:L,MATCH(A28,'اسعار الاسهم'!K:K,0),2) -> 27 | G28: =B28/C28 -> 0.4837037 | I28: =40/C28-1 -> 0.48148148 | J28: =1-(_xlfn.RANK.EQ(G28,G:G,)-1)/(COUNTIF(G:G,">0")) -> 0.27083333 | K28: =_xlfn.IFNA(1-(_xlfn.RANK.EQ(H28,H:H,)-1)/(COUNTIF(H:H,">0")),0) -> 0 | L28: =_xlfn.IFNA(1-(_xlfn.RANK.EQ(I28,I:I,)-1)/(COUNTIF(I:I,">0")),0) -> 0.83333333 | M28: =$AG$2*J28+K28 *$AG$3+L28*$AG$4+$AG$5*E28+$AG$6*F28 -> 0.71666667 | N28: =OR(O28<>"",V28<>"") -> FALSE | P28: =IFERROR(T28-O28,"") | Q28: =IF(P28<>"",IF(ABS(P28)/T28>0.1,"Gny",""),"") | R28: =IF(P28<>"",ABS(P28)/T28,"") | S28: =_xlfn.NUMBERVALUE(S27)+IF(O28,1,0) -> 14 | T28: {=IF(O28,INDEX($AP$2:$AP$21,S28,1),"")} | U28: =IF(P28<>"",ABS(P28),"") | W28: =IFERROR(AA28-V28,"") | X28: =IF(W28<>"",IF(ABS(W28)/AA28>0.1,"Gny",""),"") | Y28: =IF(W28<>"",ABS(W28)/AA28,"") | Z28: =_xlfn.NUMBERVALUE(Z27)+IF(V28,1,0) -> 14 | AA28: {=IF(V28,INDEX($AK$2:$AK$20,Z28,1),"")} | AB28: =IF(W28<>"",ABS(W28),"")
A29: ARCC | B29: =_xlfn.IFNA(INDEX(bf!B:B,MATCH(A29,bf!A:A,0),1),0) -> 0 | C29: =INDEX('اسعار الاسهم'!A:L,MATCH(A29,'اسعار الاسهم'!K:K,0),2) -> 54.2 | E29: 1 | G29: =B29/C29 -> 0 | J29: =1-(_xlfn.RANK.EQ(G29,G:G,)-1)/(COUNTIF(G:G,">0")) -> 0 | K29: =_xlfn.IFNA(1-(_xlfn.RANK.EQ(H29,H:H,)-1)/(COUNTIF(H:H,">0")),0) -> 0 | L29: =_xlfn.IFNA(1-(_xlfn.RANK.EQ(I29,I:I,)-1)/(COUNTIF(I:I,">0")),0) -> 0 | M29: =$AG$2*J29+K29 *$AG$3+L29*$AG$4+$AG$5*E29+$AG$6*F29 -> 0.7 | N29: =OR(O29<>"",V29<>"") -> TRUE | O29: 3.57 | P29: =IFERROR(T29-O29,"") -> 0.05 | Q29: =IF(P29<>"",IF(ABS(P29)/T29>0.1,"Gny",""),"") | R29: =IF(P29<>"",ABS(P29)/T29,"") -> 0.013812155 | S29: =_xlfn.NUMBERVALUE(S28)+IF(O29,1,0) -> 15 | T29: {=IF(O29,INDEX($AP$2:$AP$21,S29,1),"")} -> 3.62 | U29: =IF(P29<>"",ABS(P29),"") -> 0.05 | V29: 53.2 | W29: =IFERROR(AA29-V29,"") -> -1.1 | X29: =IF(W29<>"",IF(ABS(W29)/AA29>0.1,"Gny",""),"") | Y29: =IF(W29<>"",ABS(W29)/AA29,"") -> 0.021113244 | Z29: =_xlfn.NUMBERVALUE(Z28)+IF(V29,1,0) -> 15 | AA29: {=IF(V29,INDEX($AK$2:$AK$20,Z29,1),"")} -> 52.1 | AB29: =IF(W29<>"",ABS(W29),"") -> 1.1 | AC29: 1 | AD29: 1
A30: CCAP | B30: =_xlfn.IFNA(INDEX(bf!B:B,MATCH(A30,bf!A:A,0),1),0) -> 0 | C30: =INDEX('اسعار الاسهم'!A:L,MATCH(A30,'اسعار الاسهم'!K:K,0),2) -> 5.2 | E30: 1 | G30: =B30/C30 -> 0 | J30: =1-(_xlfn.RANK.EQ(G30,G:G,)-1)/(COUNTIF(G:G,">0")) -> 0 | K30: =_xlfn.IFNA(1-(_xlfn.RANK.EQ(H30,H:H,)-1)/(COUNTIF(H:H,">0")),0) -> 0 | L30: =_xlfn.IFNA(1-(_xlfn.RANK.EQ(I30,I:I,)-1)/(COUNTIF(I:I,">0")),0) -> 0 | M30: =$AG$2*J30+K30 *$AG$3+L30*$AG$4+$AG$5*E30+$AG$6*F30 -> 0.7 | N30: =OR(O30<>"",V30<>"") -> FALSE | P30: =IFERROR(T30-O30,"") | Q30: =IF(P30<>"",IF(ABS(P30)/T30>0.1,"Gny",""),"") | R30: =IF(P30<>"",ABS(P30)/T30,"") | S30: =_xlfn.NUMBERVALUE(S29)+IF(O30,1,0) -> 15 | T30: {=IF(O30,INDEX($AP$2:$AP$21,S30,1),"")} | U30: =IF(P30<>"",ABS(P30),"") | W30: =IFERROR(AA30-V30,"") | X30: =IF(W30<>"",IF(ABS(W30)/AA30>0.1,"Gny",""),"") | Y30: =IF(W30<>"",ABS(W30)/AA30,"") | Z30: =_xlfn.NUMBERVALUE(Z29)+IF(V30,1,0) -> 15 | AA30: {=IF(V30,INDEX($AK$2:$AK$20,Z30,1),"")} | AB30: =IF(W30<>"",ABS(W30),"")
A31: LCSW | B31: =_xlfn.IFNA(INDEX(bf!B:B,MATCH(A31,bf!A:A,0),1),0) -> 0 | C31: =INDEX('اسعار الاسهم'!A:L,MATCH(A31,'اسعار الاسهم'!K:K,0),2) -> 26.64 | F31: 0.98 | G31: =B31/C31 -> 0 | J31: =1-(_xlfn.RANK.EQ(G31,G:G,)-1)/(COUNTIF(G:G,">0")) -> 0 | K31: =_xlfn.IFNA(1-(_xlfn.RANK.EQ(H31,H:H,)-1)/(COUNTIF(H:H,">0")),0) -> 0 | L31: =_xlfn.IFNA(1-(_xlfn.RANK.EQ(I31,I:I,)-1)/(COUNTIF(I:I,">0")),0) -> 0 | M31: =$AG$2*J31+K31 *$AG$3+L31*$AG$4+$AG$5*E31+$AG$6*F31 -> 0.686 | N31: =OR(O31<>"",V31<>"") -> FALSE | P31: =IFERROR(T31-O31,"") | Q31: =IF(P31<>"",IF(ABS(P31)/T31>0.1,"Gny",""),"") | R31: =IF(P31<>"",ABS(P31)/T31,"") | S31: =_xlfn.NUMBERVALUE(S30)+IF(O31,1,0) -> 15 | T31: {=IF(O31,INDEX($AP$2:$AP$21,S31,1),"")} | U31: =IF(P31<>"",ABS(P31),"") | W31: =IFERROR(AA31-V31,"") | X31: =IF(W31<>"",IF(ABS(W31)/AA31>0.1,"Gny",""),"") | Y31: =IF(W31<>"",ABS(W31)/AA31,"") | Z31: =_xlfn.NUMBERVALUE(Z30)+IF(V31,1,0) -> 15 | AA31: {=IF(V31,INDEX($AK$2:$AK$20,Z31,1),"")} | AB31: =IF(W31<>"",ABS(W31),"")
A32: CICH | B32: =_xlfn.IFNA(INDEX(bf!B:B,MATCH(A32,bf!A:A,0),1),0) -> 10.48 | C32: =INDEX('اسعار الاسهم'!A:L,MATCH(A32,'اسعار الاسهم'!K:K,0),2) -> 12.71 | G32: =B32/C32 -> 0.8245476 | J32: =1-(_xlfn.RANK.EQ(G32,G:G,)-1)/(COUNTIF(G:G,">0")) -> 0.85416667 | K32: =_xlfn.IFNA(1-(_xlfn.RANK.EQ(H32,H:H,)-1)/(COUNTIF(H:H,">0")),0) -> 0 | L32: =_xlfn.IFNA(1-(_xlfn.RANK.EQ(I32,I:I,)-1)/(COUNTIF(I:I,">0")),0) -> 0 | M32: =$AG$2*J32+K32 *$AG$3+L32*$AG$4+$AG$5*E32+$AG$6*F32 -> 0.68333333 | N32: =OR(O32<>"",V32<>"") -> FALSE | P32: =IFERROR(T32-O32,"") | Q32: =IF(P32<>"",IF(ABS(P32)/T32>0.1,"Gny",""),"") | R32: =IF(P32<>"",ABS(P32)/T32,"") | S32: =_xlfn.NUMBERVALUE(S31)+IF(O32,1,0) -> 15 | T32: {=IF(O32,INDEX($AP$2:$AP$21,S32,1),"")} | U32: =IF(P32<>"",ABS(P32),"") | W32: =IFERROR(AA32-V32,"") | X32: =IF(W32<>"",IF(ABS(W32)/AA32>0.1,"Gny",""),"") | Y32: =IF(W32<>"",ABS(W32)/AA32,"") | Z32: =_xlfn.NUMBERVALUE(Z31)+IF(V32,1,0) -> 15 | AA32: {=IF(V32,INDEX($AK$2:$AK$20,Z32,1),"")} | AB32: =IF(W32<>"",ABS(W32),"") | AD32: 1
A33: RACC | B33: =_xlfn.IFNA(INDEX(bf!B:B,MATCH(A33,bf!A:A,0),1),0) -> 3.68 | C33: =INDEX('اسعار الاسهم'!A:L,MATCH(A33,'اسعار الاسهم'!K:K,0),2) -> 9.7 | F33: 0.82 | G33: =B33/C33 -> 0.37938144 | J33: =1-(_xlfn.RANK.EQ(G33,G:G,)-1)/(COUNTIF(G:G,">0")) -> 0.10416667 | K33: =_xlfn.IFNA(1-(_xlfn.RANK.EQ(H33,H:H,)-1)/(COUNTIF(H:H,">0")),0) -> 0 | L33: =_xlfn.IFNA(1-(_xlfn.RANK.EQ(I33,I:I,)-1)/(COUNTIF(I:I,">0")),0) -> 0 | M33: =$AG$2*J33+K33 *$AG$3+L33*$AG$4+$AG$5*E33+$AG$6*F33 -> 0.65733333 | N33: =OR(O33<>"",V33<>"") -> FALSE | P33: =IFERROR(T33-O33,"") | Q33: =IF(P33<>"",IF(ABS(P33)/T33>0.1,"Gny",""),"") | R33: =IF(P33<>"",ABS(P33)/T33,"") | S33: =_xlfn.NUMBERVALUE(S32)+IF(O33,1,0) -> 15 | T33: {=IF(O33,INDEX($AP$2:$AP$21,S33,1),"")} | U33: =IF(P33<>"",ABS(P33),"") | W33: =IFERROR(AA33-V33,"") | X33: =IF(W33<>"",IF(ABS(W33)/AA33>0.1,"Gny",""),"") | Y33: =IF(W33<>"",ABS(W33)/AA33,"") | Z33: =_xlfn.NUMBERVALUE(Z32)+IF(V33,1,0) -> 15 | AA33: {=IF(V33,INDEX($AK$2:$AK$20,Z33,1),"")} | AB33: =IF(W33<>"",ABS(W33),"")
A34: TALM | B34: =_xlfn.IFNA(INDEX(bf!B:B,MATCH(A34,bf!A:A,0),1),0) -> 12.19 | C34: =INDEX('اسعار الاسهم'!A:L,MATCH(A34,'اسعار الاسهم'!K:K,0),2) -> 15.64 | G34: =B34/C34 -> 0.77941176 | J34: =1-(_xlfn.RANK.EQ(G34,G:G,)-1)/(COUNTIF(G:G,">0")) -> 0.79166667 | K34: =_xlfn.IFNA(1-(_xlfn.RANK.EQ(H34,H:H,)-1)/(COUNTIF(H:H,">0")),0) -> 0 | L34: =_xlfn.IFNA(1-(_xlfn.RANK.EQ(I34,I:I,)-1)/(COUNTIF(I:I,">0")),0) -> 0 | M34: =$AG$2*J34+K34 *$AG$3+L34*$AG$4+$AG$5*E34+$AG$6*F34 -> 0.63333333 | N34: =OR(O34<>"",V34<>"") -> FALSE | P34: =IFERROR(T34-O34,"") | Q34: =IF(P34<>"",IF(ABS(P34)/T34>0.1,"Gny",""),"") | R34: =IF(P34<>"",ABS(P34)/T34,"") | S34: =_xlfn.NUMBERVALUE(S33)+IF(O34,1,0) -> 15 | T34: {=IF(O34,INDEX($AP$2:$AP$21,S34,1),"")} | U34: =IF(P34<>"",ABS(P34),"") | W34: =IFERROR(AA34-V34,"") | X34: =IF(W34<>"",IF(ABS(W34)/AA34>0.1,"Gny",""),"") | Y34: =IF(W34<>"",ABS(W34)/AA34,"") | Z34: =_xlfn.NUMBERVALUE(Z33)+IF(V34,1,0) -> 15 | AA34: {=IF(V34,INDEX($AK$2:$AK$20,Z34,1),"")} | AB34: =IF(W34<>"",ABS(W34),"")
A35: ELEC | B35: =_xlfn.IFNA(INDEX(bf!B:B,MATCH(A35,bf!A:A,0),1),0) -> 0 | C35: =INDEX('اسعار الاسهم'!A:L,MATCH(A35,'اسعار الاسهم'!K:K,0),2) -> 2.1 | G35: =B35/C35 -> 0 | I35: =3.8/C35-1 -> 0.80952381 | J35: =1-(_xlfn.RANK.EQ(G35,G:G,)-1)/(COUNTIF(G:G,">0")) -> 0 | K35: =_xlfn.IFNA(1-(_xlfn.RANK.EQ(H35,H:H,)-1)/(COUNTIF(H:H,">0")),0) -> 0 | L35: =_xlfn.IFNA(1-(_xlfn.RANK.EQ(I35,I:I,)-1)/(COUNTIF(I:I,">0")),0) -> 1 | M35: =$AG$2*J35+K35 *$AG$3+L35*$AG$4+$AG$5*E35+$AG$6*F35 -> 0.6 | N35: =OR(O35<>"",V35<>"") -> FALSE | P35: =IFERROR(T35-O35,"") | Q35: =IF(P35<>"",IF(ABS(P35)/T35>0.1,"Gny",""),"") | R35: =IF(P35<>"",ABS(P35)/T35,"") | S35: =_xlfn.NUMBERVALUE(S34)+IF(O35,1,0) -> 15 | T35: {=IF(O35,INDEX($AP$2:$AP$21,S35,1),"")} | U35: =IF(P35<>"",ABS(P35),"") | W35: =IFERROR(AA35-V35,"") | X35: =IF(W35<>"",IF(ABS(W35)/AA35>0.1,"Gny",""),"") | Y35: =IF(W35<>"",ABS(W35)/AA35,"") | Z35: =_xlfn.NUMBERVALUE(Z34)+IF(V35,1,0) -> 15 | AA35: {=IF(V35,INDEX($AK$2:$AK$20,Z35,1),"")} | AB35: =IF(W35<>"",ABS(W35),"")
A36: MPCO | B36: =_xlfn.IFNA(INDEX(bf!B:B,MATCH(A36,bf!A:A,0),1),0) -> 0 | C36: =INDEX('اسعار الاسهم'!A:L,MATCH(A36,'اسعار الاسهم'!K:K,0),2) -> 1.57 | G36: =B36/C36 -> 0 | I36: =2.8/C36-1 -> 0.78343949 | J36: =1-(_xlfn.RANK.EQ(G36,G:G,)-1)/(COUNTIF(G:G,">0")) -> 0 | K36: =_xlfn.IFNA(1-(_xlfn.RANK.EQ(H36,H:H,)-1)/(COUNTIF(H:H,">0")),0) -> 0 | L36: =_xlfn.IFNA(1-(_xlfn.RANK.EQ(I36,I:I,)-1)/(COUNTIF(I:I,">0")),0) -> 0.96666667 | M36: =$AG$2*J36+K36 *$AG$3+L36*$AG$4+$AG$5*E36+$AG$6*F36 -> 0.58 | N36: =OR(O36<>"",V36<>"") -> FALSE | P36: =IFERROR(T36-O36,"") | Q36: =IF(P36<>"",IF(ABS(P36)/T36>0.1,"Gny",""),"") | R36: =IF(P36<>"",ABS(P36)/T36,"") | S36: =_xlfn.NUMBERVALUE(S35)+IF(O36,1,0) -> 15 | T36: {=IF(O36,INDEX($AP$2:$AP$21,S36,1),"")} | U36: =IF(P36<>"",ABS(P36),"") | W36: =IFERROR(AA36-V36,"") | X36: =IF(W36<>"",IF(ABS(W36)/AA36>0.1,"Gny",""),"") | Y36: =IF(W36<>"",ABS(W36)/AA36,"") | Z36: =_xlfn.NUMBERVALUE(Z35)+IF(V36,1,0) -> 15 | AA36: {=IF(V36,INDEX($AK$2:$AK$20,Z36,1),"")} | AB36: =IF(W36<>"",ABS(W36),"")
A37: VLMRA | B37: =_xlfn.IFNA(INDEX(bf!B:B,MATCH(A37,bf!A:A,0),1),0) -> 0 | C37: =INDEX('اسعار الاسهم'!A:L,MATCH(A37,'اسعار الاسهم'!K:K,0),2) -> 30.4 | G37: =B37/C37 -> 0 | H37: =42.7/C37-1 -> 0.40460526 | J37: =1-(_xlfn.RANK.EQ(G37,G:G,)-1)/(COUNTIF(G:G,">0")) -> 0 | K37: =_xlfn.IFNA(1-(_xlfn.RANK.EQ(H37,H:H,)-1)/(COUNTIF(H:H,">0")),0) -> 0.57142857 | L37: =_xlfn.IFNA(1-(_xlfn.RANK.EQ(I37,I:I,)-1)/(COUNTIF(I:I,">0")),0) -> 0 | M37: =$AG$2*J37+K37 *$AG$3+L37*$AG$4+$AG$5*E37+$AG$6*F37 -> 0.57142857 | N37: =OR(O37<>"",V37<>"") -> TRUE | O37: 3.67 | P37: =IFERROR(T37-O37,"") -> -0.22 | Q37: =IF(P37<>"",IF(ABS(P37)/T37>0.1,"Gny",""),"") | R37: =IF(P37<>"",ABS(P37)/T37,"") -> 0.063768116 | S37: =_xlfn.NUMBERVALUE(S36)+IF(O37,1,0) -> 16 | T37: {=IF(O37,INDEX($AP$2:$AP$21,S37,1),"")} -> 3.45 | U37: =IF(P37<>"",ABS(P37),"") -> 0.22 | V37: 52 | W37: =IFERROR(AA37-V37,"") -> -2.3 | X37: =IF(W37<>"",IF(ABS(W37)/AA37>0.1,"Gny",""),"") | Y37: =IF(W37<>"",ABS(W37)/AA37,"") -> 0.046277666 | Z37: =_xlfn.NUMBERVALUE(Z36)+IF(V37,1,0) -> 16 | AA37: {=IF(V37,INDEX($AK$2:$AK$20,Z37,1),"")} -> 49.7 | AB37: =IF(W37<>"",ABS(W37),"") -> 2.3 | AC37: 1
A38: ELSH | B38: =_xlfn.IFNA(INDEX(bf!B:B,MATCH(A38,bf!A:A,0),1),0) -> 5.94 | C38: =INDEX('اسعار الاسهم'!A:L,MATCH(A38,'اسعار الاسهم'!K:K,0),2) -> 8.38 | G38: =B38/C38 -> 0.70883055 | J38: =1-(_xlfn.RANK.EQ(G38,G:G,)-1)/(COUNTIF(G:G,">0")) -> 0.70833333 | K38: =_xlfn.IFNA(1-(_xlfn.RANK.EQ(H38,H:H,)-1)/(COUNTIF(H:H,">0")),0) -> 0 | L38: =_xlfn.IFNA(1-(_xlfn.RANK.EQ(I38,I:I,)-1)/(COUNTIF(I:I,">0")),0) -> 0 | M38: =$AG$2*J38+K38 *$AG$3+L38*$AG$4+$AG$5*E38+$AG$6*F38 -> 0.56666667 | N38: =OR(O38<>"",V38<>"") -> FALSE | P38: =IFERROR(T38-O38,"") | Q38: =IF(P38<>"",IF(ABS(P38)/T38>0.1,"Gny",""),"") | R38: =IF(P38<>"",ABS(P38)/T38,"") | S38: =_xlfn.NUMBERVALUE(S37)+IF(O38,1,0) -> 16 | T38: {=IF(O38,INDEX($AP$2:$AP$21,S38,1),"")} | U38: =IF(P38<>"",ABS(P38),"") | W38: =IFERROR(AA38-V38,"") | X38: =IF(W38<>"",IF(ABS(W38)/AA38>0.1,"Gny",""),"") | Y38: =IF(W38<>"",ABS(W38)/AA38,"") | Z38: =_xlfn.NUMBERVALUE(Z37)+IF(V38,1,0) -> 16 | AA38: {=IF(V38,INDEX($AK$2:$AK$20,Z38,1),"")} | AB38: =IF(W38<>"",ABS(W38),"")
A39: MEPA | B39: =_xlfn.IFNA(INDEX(bf!B:B,MATCH(A39,bf!A:A,0),1),0) -> 0.77 | C39: =INDEX('اسعار الاسهم'!A:L,MATCH(A39,'اسعار الاسهم'!K:K,0),2) -> 1.66 | G39: =B39/C39 -> 0.46385542 | I39: =2.3/C39-1 -> 0.38554217 | J39: =1-(_xlfn.RANK.EQ(G39,G:G,)-1)/(COUNTIF(G:G,">0")) -> 0.22916667 | K39: =_xlfn.IFNA(1-(_xlfn.RANK.EQ(H39,H:H,)-1)/(COUNTIF(H:H,">0")),0) -> 0 | L39: =_xlfn.IFNA(1-(_xlfn.RANK.EQ(I39,I:I,)-1)/(COUNTIF(I:I,">0")),0) -> 0.63333333 | M39: =$AG$2*J39+K39 *$AG$3+L39*$AG$4+$AG$5*E39+$AG$6*F39 -> 0.56333333 | N39: =OR(O39<>"",V39<>"") -> FALSE | P39: =IFERROR(T39-O39,"") | Q39: =IF(P39<>"",IF(ABS(P39)/T39>0.1,"Gny",""),"") | R39: =IF(P39<>"",ABS(P39)/T39,"") | S39: =_xlfn.NUMBERVALUE(S38)+IF(O39,1,0) -> 16 | T39: {=IF(O39,INDEX($AP$2:$AP$21,S39,1),"")} | U39: =IF(P39<>"",ABS(P39),"") | W39: =IFERROR(AA39-V39,"") | X39: =IF(W39<>"",IF(ABS(W39)/AA39>0.1,"Gny",""),"") | Y39: =IF(W39<>"",ABS(W39)/AA39,"") | Z39: =_xlfn.NUMBERVALUE(Z38)+IF(V39,1,0) -> 16 | AA39: {=IF(V39,INDEX($AK$2:$AK$20,Z39,1),"")} | AB39: =IF(W39<>"",ABS(W39),"")
A40: ARAB | B40: =_xlfn.IFNA(INDEX(bf!B:B,MATCH(A40,bf!A:A,0),1),0) -> 0 | C40: =INDEX('اسعار الاسهم'!A:L,MATCH(A40,'اسعار الاسهم'!K:K,0),2) -> 0.2 | G40: =B40/C40 -> 0 | I40: =0.318/C40-1 -> 0.59 | J40: =1-(_xlfn.RANK.EQ(G40,G:G,)-1)/(COUNTIF(G:G,">0")) -> 0 | K40: =_xlfn.IFNA(1-(_xlfn.RANK.EQ(H40,H:H,)-1)/(COUNTIF(H:H,">0")),0) -> 0 | L40: =_xlfn.IFNA(1-(_xlfn.RANK.EQ(I40,I:I,)-1)/(COUNTIF(I:I,">0")),0) -> 0.93333333 | M40: =$AG$2*J40+K40 *$AG$3+L40*$AG$4+$AG$5*E40+$AG$6*F40 -> 0.56 | N40: =OR(O40<>"",V40<>"") -> FALSE | P40: =IFERROR(T40-O40,"") | Q40: =IF(P40<>"",IF(ABS(P40)/T40>0.1,"Gny",""),"") | R40: =IF(P40<>"",ABS(P40)/T40,"") | S40: =_xlfn.NUMBERVALUE(S39)+IF(O40,1,0) -> 16 | T40: {=IF(O40,INDEX($AP$2:$AP$21,S40,1),"")} | U40: =IF(P40<>"",ABS(P40),"") | W40: =IFERROR(AA40-V40,"") | X40: =IF(W40<>"",IF(ABS(W40)/AA40>0.1,"Gny",""),"") | Y40: =IF(W40<>"",ABS(W40)/AA40,"") | Z40: =_xlfn.NUMBERVALUE(Z39)+IF(V40,1,0) -> 16 | AA40: {=IF(V40,INDEX($AK$2:$AK$20,Z40,1),"")} | AB40: =IF(W40<>"",ABS(W40),"")
A41: UNIT | B41: =_xlfn.IFNA(INDEX(bf!B:B,MATCH(A41,bf!A:A,0),1),0) -> 9.27 | C41: =INDEX('اسعار الاسهم'!A:L,MATCH(A41,'اسعار الاسهم'!K:K,0),2) -> 13.14 | G41: =B41/C41 -> 0.70547945 | J41: =1-(_xlfn.RANK.EQ(G41,G:G,)-1)/(COUNTIF(G:G,">0")) -> 0.6875 | K41: =_xlfn.IFNA(1-(_xlfn.RANK.EQ(H41,H:H,)-1)/(COUNTIF(H:H,">0")),0) -> 0 | L41: =_xlfn.IFNA(1-(_xlfn.RANK.EQ(I41,I:I,)-1)/(COUNTIF(I:I,">0")),0) -> 0 | M41: =$AG$2*J41+K41 *$AG$3+L41*$AG$4+$AG$5*E41+$AG$6*F41 -> 0.55 | N41: =OR(O41<>"",V41<>"") -> FALSE | P41: =IFERROR(T41-O41,"") | Q41: =IF(P41<>"",IF(ABS(P41)/T41>0.1,"Gny",""),"") | R41: =IF(P41<>"",ABS(P41)/T41,"") | S41: =_xlfn.NUMBERVALUE(S40)+IF(O41,1,0) -> 16 | T41: {=IF(O41,INDEX($AP$2:$AP$21,S41,1),"")} | U41: =IF(P41<>"",ABS(P41),"") | W41: =IFERROR(AA41-V41,"") | X41: =IF(W41<>"",IF(ABS(W41)/AA41>0.1,"Gny",""),"") | Y41: =IF(W41<>"",ABS(W41)/AA41,"") | Z41: =_xlfn.NUMBERVALUE(Z40)+IF(V41,1,0) -> 16 | AA41: {=IF(V41,INDEX($AK$2:$AK$20,Z41,1),"")} | AB41: =IF(W41<>"",ABS(W41),"")
A42: KZPC | B42: =_xlfn.IFNA(INDEX(bf!B:B,MATCH(A42,bf!A:A,0),1),0) -> 0 | C42: =INDEX('اسعار الاسهم'!A:L,MATCH(A42,'اسعار الاسهم'!K:K,0),2) -> 10.33 | G42: =B42/C42 -> 0 | I42: =16/C42-1 -> 0.54888674 | J42: =1-(_xlfn.RANK.EQ(G42,G:G,)-1)/(COUNTIF(G:G,">0")) -> 0 | K42: =_xlfn.IFNA(1-(_xlfn.RANK.EQ(H42,H:H,)-1)/(COUNTIF(H:H,">0")),0) -> 0 | L42: =_xlfn.IFNA(1-(_xlfn.RANK.EQ(I42,I:I,)-1)/(COUNTIF(I:I,">0")),0) -> 0.9 | M42: =$AG$2*J42+K42 *$AG$3+L42*$AG$4+$AG$5*E42+$AG$6*F42 -> 0.54 | N42: =OR(O42<>"",V42<>"") -> FALSE | P42: =IFERROR(T42-O42,"") | Q42: =IF(P42<>"",IF(ABS(P42)/T42>0.1,"Gny",""),"") | R42: =IF(P42<>"",ABS(P42)/T42,"") | S42: =_xlfn.NUMBERVALUE(S41)+IF(O42,1,0) -> 16 | T42: {=IF(O42,INDEX($AP$2:$AP$21,S42,1),"")} | U42: =IF(P42<>"",ABS(P42),"") | W42: =IFERROR(AA42-V42,"") | X42: =IF(W42<>"",IF(ABS(W42)/AA42>0.1,"Gny",""),"") | Y42: =IF(W42<>"",ABS(W42)/AA42,"") | Z42: =_xlfn.NUMBERVALUE(Z41)+IF(V42,1,0) -> 16 | AA42: {=IF(V42,INDEX($AK$2:$AK$20,Z42,1),"")} | AB42: =IF(W42<>"",ABS(W42),"")
A43: EXPA | B43: =_xlfn.IFNA(INDEX(bf!B:B,MATCH(A43,bf!A:A,0),1),0) -> 12.89 | C43: =INDEX('اسعار الاسهم'!A:L,MATCH(A43,'اسعار الاسهم'!K:K,0),2) -> 18.73 | G43: =B43/C43 -> 0.68820075 | J43: =1-(_xlfn.RANK.EQ(G43,G:G,)-1)/(COUNTIF(G:G,">0")) -> 0.66666667 | K43: =_xlfn.IFNA(1-(_xlfn.RANK.EQ(H43,H:H,)-1)/(COUNTIF(H:H,">0")),0) -> 0 | L43: =_xlfn.IFNA(1-(_xlfn.RANK.EQ(I43,I:I,)-1)/(COUNTIF(I:I,">0")),0) -> 0 | M43: =$AG$2*J43+K43 *$AG$3+L43*$AG$4+$AG$5*E43+$AG$6*F43 -> 0.53333333 | N43: =OR(O43<>"",V43<>"") -> FALSE | P43: =IFERROR(T43-O43,"") | Q43: =IF(P43<>"",IF(ABS(P43)/T43>0.1,"Gny",""),"") | R43: =IF(P43<>"",ABS(P43)/T43,"") | S43: =_xlfn.NUMBERVALUE(S42)+IF(O43,1,0) -> 16 | T43: {=IF(O43,INDEX($AP$2:$AP$21,S43,1),"")} | U43: =IF(P43<>"",ABS(P43),"") | W43: =IFERROR(AA43-V43,"") | X43: =IF(W43<>"",IF(ABS(W43)/AA43>0.1,"Gny",""),"") | Y43: =IF(W43<>"",ABS(W43)/AA43,"") | Z43: =_xlfn.NUMBERVALUE(Z42)+IF(V43,1,0) -> 16 | AA43: {=IF(V43,INDEX($AK$2:$AK$20,Z43,1),"")} | AB43: =IF(W43<>"",ABS(W43),"")
A44: MICH | B44: =_xlfn.IFNA(INDEX(bf!B:B,MATCH(A44,bf!A:A,0),1),0) -> 23.93 | C44: =INDEX('اسعار الاسهم'!A:L,MATCH(A44,'اسعار الاسهم'!K:K,0),2) -> 35.5 | G44: =B44/C44 -> 0.67408451 | J44: =1-(_xlfn.RANK.EQ(G44,G:G,)-1)/(COUNTIF(G:G,">0")) -> 0.64583333 | K44: =_xlfn.IFNA(1-(_xlfn.RANK.EQ(H44,H:H,)-1)/(COUNTIF(H:H,">0")),0) -> 0 | L44: =_xlfn.IFNA(1-(_xlfn.RANK.EQ(I44,I:I,)-1)/(COUNTIF(I:I,">0")),0) -> 0 | M44: =$AG$2*J44+K44 *$AG$3+L44*$AG$4+$AG$5*E44+$AG$6*F44 -> 0.51666667 | N44: =OR(O44<>"",V44<>"") -> FALSE | P44: =IFERROR(T44-O44,"") | Q44: =IF(P44<>"",IF(ABS(P44)/T44>0.1,"Gny",""),"") | R44: =IF(P44<>"",ABS(P44)/T44,"") | S44: =_xlfn.NUMBERVALUE(S43)+IF(O44,1,0) -> 16 | T44: {=IF(O44,INDEX($AP$2:$AP$21,S44,1),"")} | U44: =IF(P44<>"",ABS(P44),"") | W44: =IFERROR(AA44-V44,"") | X44: =IF(W44<>"",IF(ABS(W44)/AA44>0.1,"Gny",""),"") | Y44: =IF(W44<>"",ABS(W44)/AA44,"") | Z44: =_xlfn.NUMBERVALUE(Z43)+IF(V44,1,0) -> 16 | AA44: {=IF(V44,INDEX($AK$2:$AK$20,Z44,1),"")} | AB44: =IF(W44<>"",ABS(W44),"")
A45: EFID | B45: =_xlfn.IFNA(INDEX(bf!B:B,MATCH(A45,bf!A:A,0),1),0) -> 18.16 | C45: =INDEX('اسعار الاسهم'!A:L,MATCH(A45,'اسعار الاسهم'!K:K,0),2) -> 27.92 | G45: =B45/C45 -> 0.6504298 | J45: =1-(_xlfn.RANK.EQ(G45,G:G,)-1)/(COUNTIF(G:G,">0")) -> 0.625 | K45: =_xlfn.IFNA(1-(_xlfn.RANK.EQ(H45,H:H,)-1)/(COUNTIF(H:H,">0")),0) -> 0 | L45: =_xlfn.IFNA(1-(_xlfn.RANK.EQ(I45,I:I,)-1)/(COUNTIF(I:I,">0")),0) -> 0 | M45: =$AG$2*J45+K45 *$AG$3+L45*$AG$4+$AG$5*E45+$AG$6*F45 -> 0.5 | N45: =OR(O45<>"",V45<>"") -> FALSE | P45: =IFERROR(T45-O45,"") | Q45: =IF(P45<>"",IF(ABS(P45)/T45>0.1,"Gny",""),"") | R45: =IF(P45<>"",ABS(P45)/T45,"") | S45: =_xlfn.NUMBERVALUE(S44)+IF(O45,1,0) -> 16 | T45: {=IF(O45,INDEX($AP$2:$AP$21,S45,1),"")} | U45: =IF(P45<>"",ABS(P45),"") | W45: =IFERROR(AA45-V45,"") | X45: =IF(W45<>"",IF(ABS(W45)/AA45>0.1,"Gny",""),"") | Y45: =IF(W45<>"",ABS(W45)/AA45,"") | Z45: =_xlfn.NUMBERVALUE(Z44)+IF(V45,1,0) -> 16 | AA45: {=IF(V45,INDEX($AK$2:$AK$20,Z45,1),"")} | AB45: =IF(W45<>"",ABS(W45),"")
A46: KRDI | B46: =_xlfn.IFNA(INDEX(bf!B:B,MATCH(A46,bf!A:A,0),1),0) -> 0.22 | C46: =INDEX('اسعار الاسهم'!A:L,MATCH(A46,'اسعار الاسهم'!K:K,0),2) -> 0.34 | G46: =B46/C46 -> 0.64705882 | J46: =1-(_xlfn.RANK.EQ(G46,G:G,)-1)/(COUNTIF(G:G,">0")) -> 0.5625 | K46: =_xlfn.IFNA(1-(_xlfn.RANK.EQ(H46,H:H,)-1)/(COUNTIF(H:H,">0")),0) -> 0 | L46: =_xlfn.IFNA(1-(_xlfn.RANK.EQ(I46,I:I,)-1)/(COUNTIF(I:I,">0")),0) -> 0 | M46: =$AG$2*J46+K46 *$AG$3+L46*$AG$4+$AG$5*E46+$AG$6*F46 -> 0.45 | N46: =OR(O46<>"",V46<>"") -> TRUE | P46: =IFERROR(T46-O46,"") | Q46: =IF(P46<>"",IF(ABS(P46)/T46>0.1,"Gny",""),"") | R46: =IF(P46<>"",ABS(P46)/T46,"") | S46: =_xlfn.NUMBERVALUE(S45)+IF(O46,1,0) -> 16 | T46: {=IF(O46,INDEX($AP$2:$AP$21,S46,1),"")} | U46: =IF(P46<>"",ABS(P46),"") | V46: 51.3 | W46: =IFERROR(AA46-V46,"") -> -4 | X46: =IF(W46<>"",IF(ABS(W46)/AA46>0.1,"Gny",""),"") | Y46: =IF(W46<>"",ABS(W46)/AA46,"") -> 0.084566596 | Z46: =_xlfn.NUMBERVALUE(Z45)+IF(V46,1,0) -> 17 | AA46: {=IF(V46,INDEX($AK$2:$AK$20,Z46,1),"")} -> 47.3 | AB46: =IF(W46<>"",ABS(W46),"") -> 4
A47: MBEG | B47: =_xlfn.IFNA(INDEX(bf!B:B,MATCH(A47,bf!A:A,0),1),0) -> 0 | C47: =INDEX('اسعار الاسهم'!A:L,MATCH(A47,'اسعار الاسهم'!K:K,0),2) -> 3.9 | G47: =B47/C47 -> 0 | I47: =5.5/C47-1 -> 0.41025641 | J47: =1-(_xlfn.RANK.EQ(G47,G:G,)-1)/(COUNTIF(G:G,">0")) -> 0 | K47: =_xlfn.IFNA(1-(_xlfn.RANK.EQ(H47,H:H,)-1)/(COUNTIF(H:H,">0")),0) -> 0 | L47: =_xlfn.IFNA(1-(_xlfn.RANK.EQ(I47,I:I,)-1)/(COUNTIF(I:I,">0")),0) -> 0.73333333 | M47: =$AG$2*J47+K47 *$AG$3+L47*$AG$4+$AG$5*E47+$AG$6*F47 -> 0.44 | N47: =OR(O47<>"",V47<>"") -> FALSE | P47: =IFERROR(T47-O47,"") | Q47: =IF(P47<>"",IF(ABS(P47)/T47>0.1,"Gny",""),"") | R47: =IF(P47<>"",ABS(P47)/T47,"") | S47: =_xlfn.NUMBERVALUE(S46)+IF(O47,1,0) -> 16 | T47: {=IF(O47,INDEX($AP$2:$AP$21,S47,1),"")} | U47: =IF(P47<>"",ABS(P47),"") | W47: =IFERROR(AA47-V47,"") | X47: =IF(W47<>"",IF(ABS(W47)/AA47>0.1,"Gny",""),"") | Y47: =IF(W47<>"",ABS(W47)/AA47,"") | Z47: =_xlfn.NUMBERVALUE(Z46)+IF(V47,1,0) -> 17 | AA47: {=IF(V47,INDEX($AK$2:$AK$20,Z47,1),"")} | AB47: =IF(W47<>"",ABS(W47),"")
A48: AIFI | B48: =_xlfn.IFNA(INDEX(bf!B:B,MATCH(A48,bf!A:A,0),1),0) -> 0 | C48: =INDEX('اسعار الاسهم'!A:L,MATCH(A48,'اسعار الاسهم'!K:K,0),2) -> 1.74 | G48: =B48/C48 -> 0 | I48: =2.45/C48-1 -> 0.40804598 | J48: =1-(_xlfn.RANK.EQ(G48,G:G,)-1)/(COUNTIF(G:G,">0")) -> 0 | K48: =_xlfn.IFNA(1-(_xlfn.RANK.EQ(H48,H:H,)-1)/(COUNTIF(H:H,">0")),0) -> 0 | L48: =_xlfn.IFNA(1-(_xlfn.RANK.EQ(I48,I:I,)-1)/(COUNTIF(I:I,">0")),0) -> 0.7 | M48: =$AG$2*J48+K48 *$AG$3+L48*$AG$4+$AG$5*E48+$AG$6*F48 -> 0.42 | N48: =OR(O48<>"",V48<>"") -> FALSE | P48: =IFERROR(T48-O48,"") | Q48: =IF(P48<>"",IF(ABS(P48)/T48>0.1,"Gny",""),"") | R48: =IF(P48<>"",ABS(P48)/T48,"") | S48: =_xlfn.NUMBERVALUE(S47)+IF(O48,1,0) -> 16 | T48: {=IF(O48,INDEX($AP$2:$AP$21,S48,1),"")} | U48: =IF(P48<>"",ABS(P48),"") | W48: =IFERROR(AA48-V48,"") | X48: =IF(W48<>"",IF(ABS(W48)/AA48>0.1,"Gny",""),"") | Y48: =IF(W48<>"",ABS(W48)/AA48,"") | Z48: =_xlfn.NUMBERVALUE(Z47)+IF(V48,1,0) -> 17 | AA48: {=IF(V48,INDEX($AK$2:$AK$20,Z48,1),"")} | AB48: =IF(W48<>"",ABS(W48),"")
A49: POUL | B49: =_xlfn.IFNA(INDEX(bf!B:B,MATCH(A49,bf!A:A,0),1),0) -> 22.06 | C49: =INDEX('اسعار الاسهم'!A:L,MATCH(A49,'اسعار الاسهم'!K:K,0),2) -> 35.6 | G49: =B49/C49 -> 0.61966292 | J49: =1-(_xlfn.RANK.EQ(G49,G:G,)-1)/(COUNTIF(G:G,">0")) -> 0.5 | K49: =_xlfn.IFNA(1-(_xlfn.RANK.EQ(H49,H:H,)-1)/(COUNTIF(H:H,">0")),0) -> 0 | L49: =_xlfn.IFNA(1-(_xlfn.RANK.EQ(I49,I:I,)-1)/(COUNTIF(I:I,">0")),0) -> 0 | M49: =$AG$2*J49+K49 *$AG$3+L49*$AG$4+$AG$5*E49+$AG$6*F49 -> 0.4 | N49: =OR(O49<>"",V49<>"") -> TRUE | O49: 3.57 | P49: =IFERROR(T49-O49,"") -> -0.28 | Q49: =IF(P49<>"",IF(ABS(P49)/T49>0.1,"Gny",""),"") | R49: =IF(P49<>"",ABS(P49)/T49,"") -> 0.085106383 | S49: =_xlfn.NUMBERVALUE(S48)+IF(O49,1,0) -> 17 | T49: {=IF(O49,INDEX($AP$2:$AP$21,S49,1),"")} -> 3.29 | U49: =IF(P49<>"",ABS(P49),"") -> 0.28 | W49: =IFERROR(AA49-V49,"") | X49: =IF(W49<>"",IF(ABS(W49)/AA49>0.1,"Gny",""),"") | Y49: =IF(W49<>"",ABS(W49)/AA49,"") | Z49: =_xlfn.NUMBERVALUE(Z48)+IF(V49,1,0) -> 17 | AA49: {=IF(V49,INDEX($AK$2:$AK$20,Z49,1),"")} | AB49: =IF(W49<>"",ABS(W49),"") | AD49: 1
A50: MASR | B50: =_xlfn.IFNA(INDEX(bf!B:B,MATCH(A50,bf!A:A,0),1),0) -> 3.85 | C50: =INDEX('اسعار الاسهم'!A:L,MATCH(A50,'اسعار الاسهم'!K:K,0),2) -> 6.79 | G50: =B50/C50 -> 0.56701031 | J50: =1-(_xlfn.RANK.EQ(G50,G:G,)-1)/(COUNTIF(G:G,">0")) -> 0.47916667 | K50: =_xlfn.IFNA(1-(_xlfn.RANK.EQ(H50,H:H,)-1)/(COUNTIF(H:H,">0")),0) -> 0 | L50: =_xlfn.IFNA(1-(_xlfn.RANK.EQ(I50,I:I,)-1)/(COUNTIF(I:I,">0")),0) -> 0 | M50: =$AG$2*J50+K50 *$AG$3+L50*$AG$4+$AG$5*E50+$AG$6*F50 -> 0.38333333 | N50: =OR(O50<>"",V50<>"") -> FALSE | P50: =IFERROR(T50-O50,"") | Q50: =IF(P50<>"",IF(ABS(P50)/T50>0.1,"Gny",""),"") | R50: =IF(P50<>"",ABS(P50)/T50,"") | S50: =_xlfn.NUMBERVALUE(S49)+IF(O50,1,0) -> 17 | T50: {=IF(O50,INDEX($AP$2:$AP$21,S50,1),"")} | U50: =IF(P50<>"",ABS(P50),"") | W50: =IFERROR(AA50-V50,"") | X50: =IF(W50<>"",IF(ABS(W50)/AA50>0.1,"Gny",""),"") | Y50: =IF(W50<>"",ABS(W50)/AA50,"") | Z50: =_xlfn.NUMBERVALUE(Z49)+IF(V50,1,0) -> 17 | AA50: {=IF(V50,INDEX($AK$2:$AK$20,Z50,1),"")} | AB50: =IF(W50<>"",ABS(W50),"") | AD50: 1
A51: HDBK | B51: =_xlfn.IFNA(INDEX(bf!B:B,MATCH(A51,bf!A:A,0),1),0) -> 81.26 | C51: =INDEX('اسعار الاسهم'!A:L,MATCH(A51,'اسعار الاسهم'!K:K,0),2) -> 143.45 | G51: =B51/C51 -> 0.56646915 | J51: =1-(_xlfn.RANK.EQ(G51,G:G,)-1)/(COUNTIF(G:G,">0")) -> 0.45833333 | K51: =_xlfn.IFNA(1-(_xlfn.RANK.EQ(H51,H:H,)-1)/(COUNTIF(H:H,">0")),0) -> 0 | L51: =_xlfn.IFNA(1-(_xlfn.RANK.EQ(I51,I:I,)-1)/(COUNTIF(I:I,">0")),0) -> 0 | M51: =$AG$2*J51+K51 *$AG$3+L51*$AG$4+$AG$5*E51+$AG$6*F51 -> 0.36666667 | N51: =OR(O51<>"",V51<>"") -> FALSE | P51: =IFERROR(T51-O51,"") | Q51: =IF(P51<>"",IF(ABS(P51)/T51>0.1,"Gny",""),"") | R51: =IF(P51<>"",ABS(P51)/T51,"") | S51: =_xlfn.NUMBERVALUE(S50)+IF(O51,1,0) -> 17 | T51: {=IF(O51,INDEX($AP$2:$AP$21,S51,1),"")} | U51: =IF(P51<>"",ABS(P51),"") | W51: =IFERROR(AA51-V51,"") | X51: =IF(W51<>"",IF(ABS(W51)/AA51>0.1,"Gny",""),"") | Y51: =IF(W51<>"",ABS(W51)/AA51,"") | Z51: =_xlfn.NUMBERVALUE(Z50)+IF(V51,1,0) -> 17 | AA51: {=IF(V51,INDEX($AK$2:$AK$20,Z51,1),"")} | AB51: =IF(W51<>"",ABS(W51),"")
A52: SKPC | B52: =_xlfn.IFNA(INDEX(bf!B:B,MATCH(A52,bf!A:A,0),1),0) -> 0 | C52: =INDEX('اسعار الاسهم'!A:L,MATCH(A52,'اسعار الاسهم'!K:K,0),2) -> 17.01 | G52: =B52/C52 -> 0 | I52: =23.5/C52-1 -> 0.38154027 | J52: =1-(_xlfn.RANK.EQ(G52,G:G,)-1)/(COUNTIF(G:G,">0")) -> 0 | K52: =_xlfn.IFNA(1-(_xlfn.RANK.EQ(H52,H:H,)-1)/(COUNTIF(H:H,">0")),0) -> 0 | L52: =_xlfn.IFNA(1-(_xlfn.RANK.EQ(I52,I:I,)-1)/(COUNTIF(I:I,">0")),0) -> 0.6 | M52: =$AG$2*J52+K52 *$AG$3+L52*$AG$4+$AG$5*E52+$AG$6*F52 -> 0.36 | N52: =OR(O52<>"",V52<>"") -> FALSE | P52: =IFERROR(T52-O52,"") | Q52: =IF(P52<>"",IF(ABS(P52)/T52>0.1,"Gny",""),"") | R52: =IF(P52<>"",ABS(P52)/T52,"") | S52: =_xlfn.NUMBERVALUE(S51)+IF(O52,1,0) -> 17 | T52: {=IF(O52,INDEX($AP$2:$AP$21,S52,1),"")} | U52: =IF(P52<>"",ABS(P52),"") | W52: =IFERROR(AA52-V52,"") | X52: =IF(W52<>"",IF(ABS(W52)/AA52>0.1,"Gny",""),"") | Y52: =IF(W52<>"",ABS(W52)/AA52,"") | Z52: =_xlfn.NUMBERVALUE(Z51)+IF(V52,1,0) -> 17 | AA52: {=IF(V52,INDEX($AK$2:$AK$20,Z52,1),"")} | AB52: =IF(W52<>"",ABS(W52),"")
A53: KABO | B53: =_xlfn.IFNA(INDEX(bf!B:B,MATCH(A53,bf!A:A,0),1),0) -> 0 | C53: =INDEX('اسعار الاسهم'!A:L,MATCH(A53,'اسعار الاسهم'!K:K,0),2) -> 6.11 | G53: =B53/C53 -> 0 | I53: =8.2/C53-1 -> 0.34206219 | J53: =1-(_xlfn.RANK.EQ(G53,G:G,)-1)/(COUNTIF(G:G,">0")) -> 0 | K53: =_xlfn.IFNA(1-(_xlfn.RANK.EQ(H53,H:H,)-1)/(COUNTIF(H:H,">0")),0) -> 0 | L53: =_xlfn.IFNA(1-(_xlfn.RANK.EQ(I53,I:I,)-1)/(COUNTIF(I:I,">0")),0) -> 0.56666667 | M53: =$AG$2*J53+K53 *$AG$3+L53*$AG$4+$AG$5*E53+$AG$6*F53 -> 0.34 | N53: =OR(O53<>"",V53<>"") -> FALSE | P53: =IFERROR(T53-O53,"") | Q53: =IF(P53<>"",IF(ABS(P53)/T53>0.1,"Gny",""),"") | R53: =IF(P53<>"",ABS(P53)/T53,"") | S53: =_xlfn.NUMBERVALUE(S52)+IF(O53,1,0) -> 17 | T53: {=IF(O53,INDEX($AP$2:$AP$21,S53,1),"")} | U53: =IF(P53<>"",ABS(P53),"") | W53: =IFERROR(AA53-V53,"") | X53: =IF(W53<>"",IF(ABS(W53)/AA53>0.1,"Gny",""),"") | Y53: =IF(W53<>"",ABS(W53)/AA53,"") | Z53: =_xlfn.NUMBERVALUE(Z52)+IF(V53,1,0) -> 17 | AA53: {=IF(V53,INDEX($AK$2:$AK$20,Z53,1),"")} | AB53: =IF(W53<>"",ABS(W53),"")
A54: OLFI | B54: =_xlfn.IFNA(INDEX(bf!B:B,MATCH(A54,bf!A:A,0),1),0) -> 11.77 | C54: =INDEX('اسعار الاسهم'!A:L,MATCH(A54,'اسعار الاسهم'!K:K,0),2) -> 21.15 | G54: =B54/C54 -> 0.55650118 | J54: =1-(_xlfn.RANK.EQ(G54,G:G,)-1)/(COUNTIF(G:G,">0")) -> 0.41666667 | K54: =_xlfn.IFNA(1-(_xlfn.RANK.EQ(H54,H:H,)-1)/(COUNTIF(H:H,">0")),0) -> 0 | L54: =_xlfn.IFNA(1-(_xlfn.RANK.EQ(I54,I:I,)-1)/(COUNTIF(I:I,">0")),0) -> 0 | M54: =$AG$2*J54+K54 *$AG$3+L54*$AG$4+$AG$5*E54+$AG$6*F54 -> 0.33333333 | N54: =OR(O54<>"",V54<>"") -> FALSE | P54: =IFERROR(T54-O54,"") | Q54: =IF(P54<>"",IF(ABS(P54)/T54>0.1,"Gny",""),"") | R54: =IF(P54<>"",ABS(P54)/T54,"") | S54: =_xlfn.NUMBERVALUE(S53)+IF(O54,1,0) -> 17 | T54: {=IF(O54,INDEX($AP$2:$AP$21,S54,1),"")} | U54: =IF(P54<>"",ABS(P54),"") | W54: =IFERROR(AA54-V54,"") | X54: =IF(W54<>"",IF(ABS(W54)/AA54>0.1,"Gny",""),"") | Y54: =IF(W54<>"",ABS(W54)/AA54,"") | Z54: =_xlfn.NUMBERVALUE(Z53)+IF(V54,1,0) -> 17 | AA54: {=IF(V54,INDEX($AK$2:$AK$20,Z54,1),"")} | AB54: =IF(W54<>"",ABS(W54),"")
A55: ALCN | B55: =_xlfn.IFNA(INDEX(bf!B:B,MATCH(A55,bf!A:A,0),1),0) -> 15.95 | C55: =INDEX('اسعار الاسهم'!A:L,MATCH(A55,'اسعار الاسهم'!K:K,0),2) -> 28.85 | G55: =B55/C55 -> 0.55285962 | J55: =1-(_xlfn.RANK.EQ(G55,G:G,)-1)/(COUNTIF(G:G,">0")) -> 0.39583333 | K55: =_xlfn.IFNA(1-(_xlfn.RANK.EQ(H55,H:H,)-1)/(COUNTIF(H:H,">0")),0) -> 0 | L55: =_xlfn.IFNA(1-(_xlfn.RANK.EQ(I55,I:I,)-1)/(COUNTIF(I:I,">0")),0) -> 0 | M55: =$AG$2*J55+K55 *$AG$3+L55*$AG$4+$AG$5*E55+$AG$6*F55 -> 0.31666667 | N55: =OR(O55<>"",V55<>"") -> FALSE | P55: =IFERROR(T55-O55,"") | Q55: =IF(P55<>"",IF(ABS(P55)/T55>0.1,"Gny",""),"") | R55: =IF(P55<>"",ABS(P55)/T55,"") | S55: =_xlfn.NUMBERVALUE(S54)+IF(O55,1,0) -> 17 | T55: {=IF(O55,INDEX($AP$2:$AP$21,S55,1),"")} | U55: =IF(P55<>"",ABS(P55),"") | W55: =IFERROR(AA55-V55,"") | X55: =IF(W55<>"",IF(ABS(W55)/AA55>0.1,"Gny",""),"") | Y55: =IF(W55<>"",ABS(W55)/AA55,"") | Z55: =_xlfn.NUMBERVALUE(Z54)+IF(V55,1,0) -> 17 | AA55: {=IF(V55,INDEX($AK$2:$AK$20,Z55,1),"")} | AB55: =IF(W55<>"",ABS(W55),"")
A56: MFPC | B56: =_xlfn.IFNA(INDEX(bf!B:B,MATCH(A56,bf!A:A,0),1),0) -> 24 | C56: =INDEX('اسعار الاسهم'!A:L,MATCH(A56,'اسعار الاسهم'!K:K,0),2) -> 43.48 | G56: =B56/C56 -> 0.55197792 | J56: =1-(_xlfn.RANK.EQ(G56,G:G,)-1)/(COUNTIF(G:G,">0")) -> 0.375 | K56: =_xlfn.IFNA(1-(_xlfn.RANK.EQ(H56,H:H,)-1)/(COUNTIF(H:H,">0")),0) -> 0 | L56: =_xlfn.IFNA(1-(_xlfn.RANK.EQ(I56,I:I,)-1)/(COUNTIF(I:I,">0")),0) -> 0 | M56: =$AG$2*J56+K56 *$AG$3+L56*$AG$4+$AG$5*E56+$AG$6*F56 -> 0.3 | N56: =OR(O56<>"",V56<>"") -> FALSE | P56: =IFERROR(T56-O56,"") | Q56: =IF(P56<>"",IF(ABS(P56)/T56>0.1,"Gny",""),"") | R56: =IF(P56<>"",ABS(P56)/T56,"") | S56: =_xlfn.NUMBERVALUE(S55)+IF(O56,1,0) -> 17 | T56: {=IF(O56,INDEX($AP$2:$AP$21,S56,1),"")} | U56: =IF(P56<>"",ABS(P56),"") | W56: =IFERROR(AA56-V56,"") | X56: =IF(W56<>"",IF(ABS(W56)/AA56>0.1,"Gny",""),"") | Y56: =IF(W56<>"",ABS(W56)/AA56,"") | Z56: =_xlfn.NUMBERVALUE(Z55)+IF(V56,1,0) -> 17 | AA56: {=IF(V56,INDEX($AK$2:$AK$20,Z56,1),"")} | AB56: =IF(W56<>"",ABS(W56),"")
A57: IFAP | B57: =_xlfn.IFNA(INDEX(bf!B:B,MATCH(A57,bf!A:A,0),1),0) -> 0 | C57: =INDEX('اسعار الاسهم'!A:L,MATCH(A57,'اسعار الاسهم'!K:K,0),2) -> 19.68 | G57: =B57/C57 -> 0 | I57: =26/C57-1 -> 0.32113821 | J57: =1-(_xlfn.RANK.EQ(G57,G:G,)-1)/(COUNTIF(G:G,">0")) -> 0 | K57: =_xlfn.IFNA(1-(_xlfn.RANK.EQ(H57,H:H,)-1)/(COUNTIF(H:H,">0")),0) -> 0 | L57: =_xlfn.IFNA(1-(_xlfn.RANK.EQ(I57,I:I,)-1)/(COUNTIF(I:I,">0")),0) -> 0.5 | M57: =$AG$2*J57+K57 *$AG$3+L57*$AG$4+$AG$5*E57+$AG$6*F57 -> 0.3 | N57: =OR(O57<>"",V57<>"") -> FALSE | P57: =IFERROR(T57-O57,"") | Q57: =IF(P57<>"",IF(ABS(P57)/T57>0.1,"Gny",""),"") | R57: =IF(P57<>"",ABS(P57)/T57,"") | S57: =_xlfn.NUMBERVALUE(S56)+IF(O57,1,0) -> 17 | T57: {=IF(O57,INDEX($AP$2:$AP$21,S57,1),"")} | U57: =IF(P57<>"",ABS(P57),"") | W57: =IFERROR(AA57-V57,"") | X57: =IF(W57<>"",IF(ABS(W57)/AA57>0.1,"Gny",""),"") | Y57: =IF(W57<>"",ABS(W57)/AA57,"") | Z57: =_xlfn.NUMBERVALUE(Z56)+IF(V57,1,0) -> 17 | AA57: {=IF(V57,INDEX($AK$2:$AK$20,Z57,1),"")} | AB57: =IF(W57<>"",ABS(W57),"")
A58: UBEE | B58: =_xlfn.IFNA(INDEX(bf!B:B,MATCH(A58,bf!A:A,0),1),0) -> 0 | C58: =INDEX('اسعار الاسهم'!A:L,MATCH(A58,'اسعار الاسهم'!K:K,0),2) -> 13.63 | G58: =B58/C58 -> 0 | I58: =18/C58-1 -> 0.32061629 | J58: =1-(_xlfn.RANK.EQ(G58,G:G,)-1)/(COUNTIF(G:G,">0")) -> 0 | K58: =_xlfn.IFNA(1-(_xlfn.RANK.EQ(H58,H:H,)-1)/(COUNTIF(H:H,">0")),0) -> 0 | L58: =_xlfn.IFNA(1-(_xlfn.RANK.EQ(I58,I:I,)-1)/(COUNTIF(I:I,">0")),0) -> 0.46666667 | M58: =$AG$2*J58+K58 *$AG$3+L58*$AG$4+$AG$5*E58+$AG$6*F58 -> 0.28 | N58: =OR(O58<>"",V58<>"") -> FALSE | P58: =IFERROR(T58-O58,"") | Q58: =IF(P58<>"",IF(ABS(P58)/T58>0.1,"Gny",""),"") | R58: =IF(P58<>"",ABS(P58)/T58,"") | S58: =_xlfn.NUMBERVALUE(S57)+IF(O58,1,0) -> 17 | T58: {=IF(O58,INDEX($AP$2:$AP$21,S58,1),"")} | U58: =IF(P58<>"",ABS(P58),"") | W58: =IFERROR(AA58-V58,"") | X58: =IF(W58<>"",IF(ABS(W58)/AA58>0.1,"Gny",""),"") | Y58: =IF(W58<>"",ABS(W58)/AA58,"") | Z58: =_xlfn.NUMBERVALUE(Z57)+IF(V58,1,0) -> 17 | AA58: {=IF(V58,INDEX($AK$2:$AK$20,Z58,1),"")} | AB58: =IF(W58<>"",ABS(W58),"")
A59: RMDA | B59: =_xlfn.IFNA(INDEX(bf!B:B,MATCH(A59,bf!A:A,0),1),0) -> 2.64 | C59: =INDEX('اسعار الاسهم'!A:L,MATCH(A59,'اسعار الاسهم'!K:K,0),2) -> 5.06 | G59: =B59/C59 -> 0.52173913 | J59: =1-(_xlfn.RANK.EQ(G59,G:G,)-1)/(COUNTIF(G:G,">0")) -> 0.33333333 | K59: =_xlfn.IFNA(1-(_xlfn.RANK.EQ(H59,H:H,)-1)/(COUNTIF(H:H,">0")),0) -> 0 | L59: =_xlfn.IFNA(1-(_xlfn.RANK.EQ(I59,I:I,)-1)/(COUNTIF(I:I,">0")),0) -> 0 | M59: =$AG$2*J59+K59 *$AG$3+L59*$AG$4+$AG$5*E59+$AG$6*F59 -> 0.26666667 | N59: =OR(O59<>"",V59<>"") -> FALSE | P59: =IFERROR(T59-O59,"") | Q59: =IF(P59<>"",IF(ABS(P59)/T59>0.1,"Gny",""),"") | R59: =IF(P59<>"",ABS(P59)/T59,"") | S59: =_xlfn.NUMBERVALUE(S58)+IF(O59,1,0) -> 17 | T59: {=IF(O59,INDEX($AP$2:$AP$21,S59,1),"")} | U59: =IF(P59<>"",ABS(P59),"") | W59: =IFERROR(AA59-V59,"") | X59: =IF(W59<>"",IF(ABS(W59)/AA59>0.1,"Gny",""),"") | Y59: =IF(W59<>"",ABS(W59)/AA59,"") | Z59: =_xlfn.NUMBERVALUE(Z58)+IF(V59,1,0) -> 17 | AA59: {=IF(V59,INDEX($AK$2:$AK$20,Z59,1),"")} | AB59: =IF(W59<>"",ABS(W59),"")
A60: ATQA | B60: =_xlfn.IFNA(INDEX(bf!B:B,MATCH(A60,bf!A:A,0),1),0) -> 0 | C60: =INDEX('اسعار الاسهم'!A:L,MATCH(A60,'اسعار الاسهم'!K:K,0),2) -> 9.46 | G60: =B60/C60 -> 0 | I60: =12.3/C60-1 -> 0.30021142 | J60: =1-(_xlfn.RANK.EQ(G60,G:G,)-1)/(COUNTIF(G:G,">0")) -> 0 | K60: =_xlfn.IFNA(1-(_xlfn.RANK.EQ(H60,H:H,)-1)/(COUNTIF(H:H,">0")),0) -> 0 | L60: =_xlfn.IFNA(1-(_xlfn.RANK.EQ(I60,I:I,)-1)/(COUNTIF(I:I,">0")),0) -> 0.43333333 | M60: =$AG$2*J60+K60 *$AG$3+L60*$AG$4+$AG$5*E60+$AG$6*F60 -> 0.26 | N60: =OR(O60<>"",V60<>"") -> FALSE | P60: =IFERROR(T60-O60,"") | Q60: =IF(P60<>"",IF(ABS(P60)/T60>0.1,"Gny",""),"") | R60: =IF(P60<>"",ABS(P60)/T60,"") | S60: =_xlfn.NUMBERVALUE(S59)+IF(O60,1,0) -> 17 | T60: {=IF(O60,INDEX($AP$2:$AP$21,S60,1),"")} | U60: =IF(P60<>"",ABS(P60),"") | W60: =IFERROR(AA60-V60,"") | X60: =IF(W60<>"",IF(ABS(W60)/AA60>0.1,"Gny",""),"") | Y60: =IF(W60<>"",ABS(W60)/AA60,"") | Z60: =_xlfn.NUMBERVALUE(Z59)+IF(V60,1,0) -> 17 | AA60: {=IF(V60,INDEX($AK$2:$AK$20,Z60,1),"")} | AB60: =IF(W60<>"",ABS(W60),"")
A61: IEEC | B61: =_xlfn.IFNA(INDEX(bf!B:B,MATCH(A61,bf!A:A,0),1),0) -> 0 | C61: =INDEX('اسعار الاسهم'!A:L,MATCH(A61,'اسعار الاسهم'!K:K,0),2) -> 0.43 | G61: =B61/C61 -> 0 | I61: =0.55/C61-1 -> 0.27906977 | J61: =1-(_xlfn.RANK.EQ(G61,G:G,)-1)/(COUNTIF(G:G,">0")) -> 0 | K61: =_xlfn.IFNA(1-(_xlfn.RANK.EQ(H61,H:H,)-1)/(COUNTIF(H:H,">0")),0) -> 0 | L61: =_xlfn.IFNA(1-(_xlfn.RANK.EQ(I61,I:I,)-1)/(COUNTIF(I:I,">0")),0) -> 0.4 | M61: =$AG$2*J61+K61 *$AG$3+L61*$AG$4+$AG$5*E61+$AG$6*F61 -> 0.24 | N61: =OR(O61<>"",V61<>"") -> FALSE | P61: =IFERROR(T61-O61,"") | Q61: =IF(P61<>"",IF(ABS(P61)/T61>0.1,"Gny",""),"") | R61: =IF(P61<>"",ABS(P61)/T61,"") | S61: =_xlfn.NUMBERVALUE(S60)+IF(O61,1,0) -> 17 | T61: {=IF(O61,INDEX($AP$2:$AP$21,S61,1),"")} | U61: =IF(P61<>"",ABS(P61),"") | W61: =IFERROR(AA61-V61,"") | X61: =IF(W61<>"",IF(ABS(W61)/AA61>0.1,"Gny",""),"") | Y61: =IF(W61<>"",ABS(W61)/AA61,"") | Z61: =_xlfn.NUMBERVALUE(Z60)+IF(V61,1,0) -> 17 | AA61: {=IF(V61,INDEX($AK$2:$AK$20,Z61,1),"")} | AB61: =IF(W61<>"",ABS(W61),"")
A62: GBCO | B62: =_xlfn.IFNA(INDEX(bf!B:B,MATCH(A62,bf!A:A,0),1),0) -> 12.7 | C62: =INDEX('اسعار الاسهم'!A:L,MATCH(A62,'اسعار الاسهم'!K:K,0),2) -> 25.67 | G62: =B62/C62 -> 0.49474094 | J62: =1-(_xlfn.RANK.EQ(G62,G:G,)-1)/(COUNTIF(G:G,">0")) -> 0.29166667 | K62: =_xlfn.IFNA(1-(_xlfn.RANK.EQ(H62,H:H,)-1)/(COUNTIF(H:H,">0")),0) -> 0 | L62: =_xlfn.IFNA(1-(_xlfn.RANK.EQ(I62,I:I,)-1)/(COUNTIF(I:I,">0")),0) -> 0 | M62: =$AG$2*J62+K62 *$AG$3+L62*$AG$4+$AG$5*E62+$AG$6*F62 -> 0.23333333 | N62: =OR(O62<>"",V62<>"") -> FALSE | P62: =IFERROR(T62-O62,"") | Q62: =IF(P62<>"",IF(ABS(P62)/T62>0.1,"Gny",""),"") | R62: =IF(P62<>"",ABS(P62)/T62,"") | S62: =_xlfn.NUMBERVALUE(S61)+IF(O62,1,0) -> 17 | T62: {=IF(O62,INDEX($AP$2:$AP$21,S62,1),"")} | U62: =IF(P62<>"",ABS(P62),"") | W62: =IFERROR(AA62-V62,"") | X62: =IF(W62<>"",IF(ABS(W62)/AA62>0.1,"Gny",""),"") | Y62: =IF(W62<>"",ABS(W62)/AA62,"") | Z62: =_xlfn.NUMBERVALUE(Z61)+IF(V62,1,0) -> 17 | AA62: {=IF(V62,INDEX($AK$2:$AK$20,Z62,1),"")} | AB62: =IF(W62<>"",ABS(W62),"")
A63: PHAR | B63: =_xlfn.IFNA(INDEX(bf!B:B,MATCH(A63,bf!A:A,0),1),0) -> 35.86 | C63: =INDEX('اسعار الاسهم'!A:L,MATCH(A63,'اسعار الاسهم'!K:K,0),2) -> 84.5 | G63: =B63/C63 -> 0.4243787 | H63: =96/C63-1 -> 0.13609467 | J63: =1-(_xlfn.RANK.EQ(G63,G:G,)-1)/(COUNTIF(G:G,">0")) -> 0.16666667 | K63: =_xlfn.IFNA(1-(_xlfn.RANK.EQ(H63,H:H,)-1)/(COUNTIF(H:H,">0")),0) -> 0.071428571 | L63: =_xlfn.IFNA(1-(_xlfn.RANK.EQ(I63,I:I,)-1)/(COUNTIF(I:I,">0")),0) -> 0 | M63: =$AG$2*J63+K63 *$AG$3+L63*$AG$4+$AG$5*E63+$AG$6*F63 -> 0.2047619 | N63: =OR(O63<>"",V63<>"") -> FALSE | P63: =IFERROR(T63-O63,"") | Q63: =IF(P63<>"",IF(ABS(P63)/T63>0.1,"Gny",""),"") | R63: =IF(P63<>"",ABS(P63)/T63,"") | S63: =_xlfn.NUMBERVALUE(S62)+IF(O63,1,0) -> 17 | T63: {=IF(O63,INDEX($AP$2:$AP$21,S63,1),"")} | U63: =IF(P63<>"",ABS(P63),"") | W63: =IFERROR(AA63-V63,"") | X63: =IF(W63<>"",IF(ABS(W63)/AA63>0.1,"Gny",""),"") | Y63: =IF(W63<>"",ABS(W63)/AA63,"") | Z63: =_xlfn.NUMBERVALUE(Z62)+IF(V63,1,0) -> 17 | AA63: {=IF(V63,INDEX($AK$2:$AK$20,Z63,1),"")} | AB63: =IF(W63<>"",ABS(W63),"")
A64: ATLC | B64: =_xlfn.IFNA(INDEX(bf!B:B,MATCH(A64,bf!A:A,0),1),0) -> 2.3 | C64: =INDEX('اسعار الاسهم'!A:L,MATCH(A64,'اسعار الاسهم'!K:K,0),2) -> 4.8 | G64: =B64/C64 -> 0.47916667 | J64: =1-(_xlfn.RANK.EQ(G64,G:G,)-1)/(COUNTIF(G:G,">0")) -> 0.25 | K64: =_xlfn.IFNA(1-(_xlfn.RANK.EQ(H64,H:H,)-1)/(COUNTIF(H:H,">0")),0) -> 0 | L64: =_xlfn.IFNA(1-(_xlfn.RANK.EQ(I64,I:I,)-1)/(COUNTIF(I:I,">0")),0) -> 0 | M64: =$AG$2*J64+K64 *$AG$3+L64*$AG$4+$AG$5*E64+$AG$6*F64 -> 0.2 | N64: =OR(O64<>"",V64<>"") -> FALSE | P64: =IFERROR(T64-O64,"") | Q64: =IF(P64<>"",IF(ABS(P64)/T64>0.1,"Gny",""),"") | R64: =IF(P64<>"",ABS(P64)/T64,"") | S64: =_xlfn.NUMBERVALUE(S63)+IF(O64,1,0) -> 17 | T64: {=IF(O64,INDEX($AP$2:$AP$21,S64,1),"")} | U64: =IF(P64<>"",ABS(P64),"") | W64: =IFERROR(AA64-V64,"") | X64: =IF(W64<>"",IF(ABS(W64)/AA64>0.1,"Gny",""),"") | Y64: =IF(W64<>"",ABS(W64)/AA64,"") | Z64: =_xlfn.NUMBERVALUE(Z63)+IF(V64,1,0) -> 17 | AA64: {=IF(V64,INDEX($AK$2:$AK$20,Z64,1),"")} | AB64: =IF(W64<>"",ABS(W64),"")
A65: GSSC | B65: =_xlfn.IFNA(INDEX(bf!B:B,MATCH(A65,bf!A:A,0),1),0) -> 0 | C65: =INDEX('اسعار الاسهم'!A:L,MATCH(A65,'اسعار الاسهم'!K:K,0),2) -> 260 | G65: =B65/C65 -> 0 | I65: =323/C65-1 -> 0.24230769 | J65: =1-(_xlfn.RANK.EQ(G65,G:G,)-1)/(COUNTIF(G:G,">0")) -> 0 | K65: =_xlfn.IFNA(1-(_xlfn.RANK.EQ(H65,H:H,)-1)/(COUNTIF(H:H,">0")),0) -> 0 | L65: =_xlfn.IFNA(1-(_xlfn.RANK.EQ(I65,I:I,)-1)/(COUNTIF(I:I,">0")),0) -> 0.33333333 | M65: =$AG$2*J65+K65 *$AG$3+L65*$AG$4+$AG$5*E65+$AG$6*F65 -> 0.2 | N65: =OR(O65<>"",V65<>"") -> FALSE | P65: =IFERROR(T65-O65,"") | Q65: =IF(P65<>"",IF(ABS(P65)/T65>0.1,"Gny",""),"") | R65: =IF(P65<>"",ABS(P65)/T65,"") | S65: =_xlfn.NUMBERVALUE(S64)+IF(O65,1,0) -> 17 | T65: {=IF(O65,INDEX($AP$2:$AP$21,S65,1),"")} | U65: =IF(P65<>"",ABS(P65),"") | W65: =IFERROR(AA65-V65,"") | X65: =IF(W65<>"",IF(ABS(W65)/AA65>0.1,"Gny",""),"") | Y65: =IF(W65<>"",ABS(W65)/AA65,"") | Z65: =_xlfn.NUMBERVALUE(Z64)+IF(V65,1,0) -> 17 | AA65: {=IF(V65,INDEX($AK$2:$AK$20,Z65,1),"")} | AB65: =IF(W65<>"",ABS(W65),"")
A66: ETEL | B66: =_xlfn.IFNA(INDEX(bf!B:B,MATCH(A66,bf!A:A,0),1),0) -> 35.87 | C66: =INDEX('اسعار الاسهم'!A:L,MATCH(A66,'اسعار الاسهم'!K:K,0),2) -> 95.5 | G66: =B66/C66 -> 0.37560209 | I66: =112/C66-1 -> 0.17277487 | J66: =1-(_xlfn.RANK.EQ(G66,G:G,)-1)/(COUNTIF(G:G,">0")) -> 0.083333333 | K66: =_xlfn.IFNA(1-(_xlfn.RANK.EQ(H66,H:H,)-1)/(COUNTIF(H:H,">0")),0) -> 0 | L66: =_xlfn.IFNA(1-(_xlfn.RANK.EQ(I66,I:I,)-1)/(COUNTIF(I:I,">0")),0) -> 0.2 | M66: =$AG$2*J66+K66 *$AG$3+L66*$AG$4+$AG$5*E66+$AG$6*F66 -> 0.18666667 | N66: =OR(O66<>"",V66<>"") -> FALSE | P66: =IFERROR(T66-O66,"") | Q66: =IF(P66<>"",IF(ABS(P66)/T66>0.1,"Gny",""),"") | R66: =IF(P66<>"",ABS(P66)/T66,"") | S66: =_xlfn.NUMBERVALUE(S65)+IF(O66,1,0) -> 17 | T66: {=IF(O66,INDEX($AP$2:$AP$21,S66,1),"")} | U66: =IF(P66<>"",ABS(P66),"") | W66: =IFERROR(AA66-V66,"") | X66: =IF(W66<>"",IF(ABS(W66)/AA66>0.1,"Gny",""),"") | Y66: =IF(W66<>"",ABS(W66)/AA66,"") | Z66: =_xlfn.NUMBERVALUE(Z65)+IF(V66,1,0) -> 17 | AA66: {=IF(V66,INDEX($AK$2:$AK$20,Z66,1),"")} | AB66: =IF(W66<>"",ABS(W66),"")
A67: EAST | B67: =_xlfn.IFNA(INDEX(bf!B:B,MATCH(A67,bf!A:A,0),1),0) -> 17.02 | C67: =INDEX('اسعار الاسهم'!A:L,MATCH(A67,'اسعار الاسهم'!K:K,0),2) -> 37.59 | G67: =B67/C67 -> 0.45277999 | J67: =1-(_xlfn.RANK.EQ(G67,G:G,)-1)/(COUNTIF(G:G,">0")) -> 0.20833333 | K67: =_xlfn.IFNA(1-(_xlfn.RANK.EQ(H67,H:H,)-1)/(COUNTIF(H:H,">0")),0) -> 0 | L67: =_xlfn.IFNA(1-(_xlfn.RANK.EQ(I67,I:I,)-1)/(COUNTIF(I:I,">0")),0) -> 0 | M67: =$AG$2*J67+K67 *$AG$3+L67*$AG$4+$AG$5*E67+$AG$6*F67 -> 0.16666667 | N67: =OR(O67<>"",V67<>"") -> FALSE | P67: =IFERROR(T67-O67,"") | Q67: =IF(P67<>"",IF(ABS(P67)/T67>0.1,"Gny",""),"") | R67: =IF(P67<>"",ABS(P67)/T67,"") | S67: =_xlfn.NUMBERVALUE(S66)+IF(O67,1,0) -> 17 | T67: {=IF(O67,INDEX($AP$2:$AP$21,S67,1),"")} | U67: =IF(P67<>"",ABS(P67),"") | W67: =IFERROR(AA67-V67,"") | X67: =IF(W67<>"",IF(ABS(W67)/AA67>0.1,"Gny",""),"") | Y67: =IF(W67<>"",ABS(W67)/AA67,"") | Z67: =_xlfn.NUMBERVALUE(Z66)+IF(V67,1,0) -> 17 | AA67: {=IF(V67,INDEX($AK$2:$AK$20,Z67,1),"")} | AB67: =IF(W67<>"",ABS(W67),"")
A68: BINV | B68: =_xlfn.IFNA(INDEX(bf!B:B,MATCH(A68,bf!A:A,0),1),0) -> 0 | C68: =INDEX('اسعار الاسهم'!A:L,MATCH(A68,'اسعار الاسهم'!K:K,0),2) -> 41.43 | G68: =B68/C68 -> 0 | I68: =50/C68-1 -> 0.20685494 | J68: =1-(_xlfn.RANK.EQ(G68,G:G,)-1)/(COUNTIF(G:G,">0")) -> 0 | K68: =_xlfn.IFNA(1-(_xlfn.RANK.EQ(H68,H:H,)-1)/(COUNTIF(H:H,">0")),0) -> 0 | L68: =_xlfn.IFNA(1-(_xlfn.RANK.EQ(I68,I:I,)-1)/(COUNTIF(I:I,">0")),0) -> 0.26666667 | M68: =$AG$2*J68+K68 *$AG$3+L68*$AG$4+$AG$5*E68+$AG$6*F68 -> 0.16 | N68: =OR(O68<>"",V68<>"") -> FALSE | P68: =IFERROR(T68-O68,"") | Q68: =IF(P68<>"",IF(ABS(P68)/T68>0.1,"Gny",""),"") | R68: =IF(P68<>"",ABS(P68)/T68,"") | S68: =_xlfn.NUMBERVALUE(S67)+IF(O68,1,0) -> 17 | T68: {=IF(O68,INDEX($AP$2:$AP$21,S68,1),"")} | U68: =IF(P68<>"",ABS(P68),"") | W68: =IFERROR(AA68-V68,"") | X68: =IF(W68<>"",IF(ABS(W68)/AA68>0.1,"Gny",""),"") | Y68: =IF(W68<>"",ABS(W68)/AA68,"") | Z68: =_xlfn.NUMBERVALUE(Z67)+IF(V68,1,0) -> 17 | AA68: {=IF(V68,INDEX($AK$2:$AK$20,Z68,1),"")} | AB68: =IF(W68<>"",ABS(W68),"")
A69: EMFD | B69: =_xlfn.IFNA(INDEX(bf!B:B,MATCH(A69,bf!A:A,0),1),0) -> 4.155 | C69: =INDEX('اسعار الاسهم'!A:L,MATCH(A69,'اسعار الاسهم'!K:K,0),2) -> 10.11 | G69: =B69/C69 -> 0.41097923 | I69: =11.5/C69-1 -> 0.13748764 | J69: =1-(_xlfn.RANK.EQ(G69,G:G,)-1)/(COUNTIF(G:G,">0")) -> 0.14583333 | K69: =_xlfn.IFNA(1-(_xlfn.RANK.EQ(H69,H:H,)-1)/(COUNTIF(H:H,">0")),0) -> 0 | L69: =_xlfn.IFNA(1-(_xlfn.RANK.EQ(I69,I:I,)-1)/(COUNTIF(I:I,">0")),0) -> 0.066666667 | M69: =$AG$2*J69+K69 *$AG$3+L69*$AG$4+$AG$5*E69+$AG$6*F69 -> 0.15666667 | N69: =OR(O69<>"",V69<>"") -> FALSE | P69: =IFERROR(T69-O69,"") | Q69: =IF(P69<>"",IF(ABS(P69)/T69>0.1,"Gny",""),"") | R69: =IF(P69<>"",ABS(P69)/T69,"") | S69: =_xlfn.NUMBERVALUE(S68)+IF(O69,1,0) -> 17 | T69: {=IF(O69,INDEX($AP$2:$AP$21,S69,1),"")} | U69: =IF(P69<>"",ABS(P69),"") | W69: =IFERROR(AA69-V69,"") | X69: =IF(W69<>"",IF(ABS(W69)/AA69>0.1,"Gny",""),"") | Y69: =IF(W69<>"",ABS(W69)/AA69,"") | Z69: =_xlfn.NUMBERVALUE(Z68)+IF(V69,1,0) -> 17 | AA69: {=IF(V69,INDEX($AK$2:$AK$20,Z69,1),"")} | AB69: =IF(W69<>"",ABS(W69),"")
A70: ADIB | B70: =_xlfn.IFNA(INDEX(bf!B:B,MATCH(A70,bf!A:A,0),1),0) -> 19.9 | C70: =INDEX('اسعار الاسهم'!A:L,MATCH(A70,'اسعار الاسهم'!K:K,0),2) -> 46.1 | G70: =B70/C70 -> 0.43167028 | J70: =1-(_xlfn.RANK.EQ(G70,G:G,)-1)/(COUNTIF(G:G,">0")) -> 0.1875 | K70: =_xlfn.IFNA(1-(_xlfn.RANK.EQ(H70,H:H,)-1)/(COUNTIF(H:H,">0")),0) -> 0 | L70: =_xlfn.IFNA(1-(_xlfn.RANK.EQ(I70,I:I,)-1)/(COUNTIF(I:I,">0")),0) -> 0 | M70: =$AG$2*J70+K70 *$AG$3+L70*$AG$4+$AG$5*E70+$AG$6*F70 -> 0.15 | N70: =OR(O70<>"",V70<>"") -> FALSE | P70: =IFERROR(T70-O70,"") | Q70: =IF(P70<>"",IF(ABS(P70)/T70>0.1,"Gny",""),"") | R70: =IF(P70<>"",ABS(P70)/T70,"") | S70: =_xlfn.NUMBERVALUE(S69)+IF(O70,1,0) -> 17 | T70: {=IF(O70,INDEX($AP$2:$AP$21,S70,1),"")} | U70: =IF(P70<>"",ABS(P70),"") | W70: =IFERROR(AA70-V70,"") | X70: =IF(W70<>"",IF(ABS(W70)/AA70>0.1,"Gny",""),"") | Y70: =IF(W70<>"",ABS(W70)/AA70,"") | Z70: =_xlfn.NUMBERVALUE(Z69)+IF(V70,1,0) -> 17 | AA70: {=IF(V70,INDEX($AK$2:$AK$20,Z70,1),"")} | AB70: =IF(W70<>"",ABS(W70),"") | AD70: 1
A71: ETRS | B71: =_xlfn.IFNA(INDEX(bf!B:B,MATCH(A71,bf!A:A,0),1),0) -> 0 | C71: =INDEX('اسعار الاسهم'!A:L,MATCH(A71,'اسعار الاسهم'!K:K,0),2) -> 7.59 | G71: =B71/C71 -> 0 | I71: =9.1/C71-1 -> 0.19894598 | J71: =1-(_xlfn.RANK.EQ(G71,G:G,)-1)/(COUNTIF(G:G,">0")) -> 0 | K71: =_xlfn.IFNA(1-(_xlfn.RANK.EQ(H71,H:H,)-1)/(COUNTIF(H:H,">0")),0) -> 0 | L71: =_xlfn.IFNA(1-(_xlfn.RANK.EQ(I71,I:I,)-1)/(COUNTIF(I:I,">0")),0) -> 0.23333333 | M71: =$AG$2*J71+K71 *$AG$3+L71*$AG$4+$AG$5*E71+$AG$6*F71 -> 0.14 | N71: =OR(O71<>"",V71<>"") -> FALSE | P71: =IFERROR(T71-O71,"") | Q71: =IF(P71<>"",IF(ABS(P71)/T71>0.1,"Gny",""),"") | R71: =IF(P71<>"",ABS(P71)/T71,"") | S71: =_xlfn.NUMBERVALUE(S70)+IF(O71,1,0) -> 17 | T71: {=IF(O71,INDEX($AP$2:$AP$21,S71,1),"")} | U71: =IF(P71<>"",ABS(P71),"") | W71: =IFERROR(AA71-V71,"") | X71: =IF(W71<>"",IF(ABS(W71)/AA71>0.1,"Gny",""),"") | Y71: =IF(W71<>"",ABS(W71)/AA71,"") | Z71: =_xlfn.NUMBERVALUE(Z70)+IF(V71,1,0) -> 17 | AA71: {=IF(V71,INDEX($AK$2:$AK$20,Z71,1),"")} | AB71: =IF(W71<>"",ABS(W71),"")
A72: ICID | B72: =_xlfn.IFNA(INDEX(bf!B:B,MATCH(A72,bf!A:A,0),1),0) -> 0 | C72: =INDEX('اسعار الاسهم'!A:L,MATCH(A72,'اسعار الاسهم'!K:K,0),2) -> 4.54 | G72: =B72/C72 -> 0 | I72: =5.3/C72-1 -> 0.16740088 | J72: =1-(_xlfn.RANK.EQ(G72,G:G,)-1)/(COUNTIF(G:G,">0")) -> 0 | K72: =_xlfn.IFNA(1-(_xlfn.RANK.EQ(H72,H:H,)-1)/(COUNTIF(H:H,">0")),0) -> 0 | L72: =_xlfn.IFNA(1-(_xlfn.RANK.EQ(I72,I:I,)-1)/(COUNTIF(I:I,">0")),0) -> 0.16666667 | M72: =$AG$2*J72+K72 *$AG$3+L72*$AG$4+$AG$5*E72+$AG$6*F72 -> 0.1 | N72: =OR(O72<>"",V72<>"") -> FALSE | P72: =IFERROR(T72-O72,"") | Q72: =IF(P72<>"",IF(ABS(P72)/T72>0.1,"Gny",""),"") | R72: =IF(P72<>"",ABS(P72)/T72,"") | S72: =_xlfn.NUMBERVALUE(S71)+IF(O72,1,0) -> 17 | T72: {=IF(O72,INDEX($AP$2:$AP$21,S72,1),"")} | U72: =IF(P72<>"",ABS(P72),"") | W72: =IFERROR(AA72-V72,"") | X72: =IF(W72<>"",IF(ABS(W72)/AA72>0.1,"Gny",""),"") | Y72: =IF(W72<>"",ABS(W72)/AA72,"") | Z72: =_xlfn.NUMBERVALUE(Z71)+IF(V72,1,0) -> 17 | AA72: {=IF(V72,INDEX($AK$2:$AK$20,Z72,1),"")} | AB72: =IF(W72<>"",ABS(W72),"")
A73: OFH | B73: =_xlfn.IFNA(INDEX(bf!B:B,MATCH(A73,bf!A:A,0),1),0) -> 0 | C73: =INDEX('اسعار الاسهم'!A:L,MATCH(A73,'اسعار الاسهم'!K:K,0),2) -> 0.61 | G73: =B73/C73 -> 0 | I73: =0.7/C73-1 -> 0.14754098 | J73: =1-(_xlfn.RANK.EQ(G73,G:G,)-1)/(COUNTIF(G:G,">0")) -> 0 | K73: =_xlfn.IFNA(1-(_xlfn.RANK.EQ(H73,H:H,)-1)/(COUNTIF(H:H,">0")),0) -> 0 | L73: =_xlfn.IFNA(1-(_xlfn.RANK.EQ(I73,I:I,)-1)/(COUNTIF(I:I,">0")),0) -> 0.1 | M73: =$AG$2*J73+K73 *$AG$3+L73*$AG$4+$AG$5*E73+$AG$6*F73 -> 0.06 | N73: =OR(O73<>"",V73<>"") -> FALSE | P73: =IFERROR(T73-O73,"") | Q73: =IF(P73<>"",IF(ABS(P73)/T73>0.1,"Gny",""),"") | R73: =IF(P73<>"",ABS(P73)/T73,"") | S73: =_xlfn.NUMBERVALUE(S72)+IF(O73,1,0) -> 17 | T73: {=IF(O73,INDEX($AP$2:$AP$21,S73,1),"")} | U73: =IF(P73<>"",ABS(P73),"") | W73: =IFERROR(AA73-V73,"") | X73: =IF(W73<>"",IF(ABS(W73)/AA73>0.1,"Gny",""),"") | Y73: =IF(W73<>"",ABS(W73)/AA73,"") | Z73: =_xlfn.NUMBERVALUE(Z72)+IF(V73,1,0) -> 17 | AA73: {=IF(V73,INDEX($AK$2:$AK$20,Z73,1),"")} | AB73: =IF(W73<>"",ABS(W73),"")
A74: CIRA | B74: =_xlfn.IFNA(INDEX(bf!B:B,MATCH(A74,bf!A:A,0),1),0) -> 9.96 | C74: =INDEX('اسعار الاسهم'!A:L,MATCH(A74,'اسعار الاسهم'!K:K,0),2) -> 27.63 | G74: =B74/C74 -> 0.36047774 | J74: =1-(_xlfn.RANK.EQ(G74,G:G,)-1)/(COUNTIF(G:G,">0")) -> 0.0625 | K74: =_xlfn.IFNA(1-(_xlfn.RANK.EQ(H74,H:H,)-1)/(COUNTIF(H:H,">0")),0) -> 0 | L74: =_xlfn.IFNA(1-(_xlfn.RANK.EQ(I74,I:I,)-1)/(COUNTIF(I:I,">0")),0) -> 0 | M74: =$AG$2*J74+K74 *$AG$3+L74*$AG$4+$AG$5*E74+$AG$6*F74 -> 0.05 | N74: =OR(O74<>"",V74<>"") -> FALSE | P74: =IFERROR(T74-O74,"") | Q74: =IF(P74<>"",IF(ABS(P74)/T74>0.1,"Gny",""),"") | R74: =IF(P74<>"",ABS(P74)/T74,"") | S74: =_xlfn.NUMBERVALUE(S73)+IF(O74,1,0) -> 17 | T74: {=IF(O74,INDEX($AP$2:$AP$21,S74,1),"")} | U74: =IF(P74<>"",ABS(P74),"") | W74: =IFERROR(AA74-V74,"") | X74: =IF(W74<>"",IF(ABS(W74)/AA74>0.1,"Gny",""),"") | Y74: =IF(W74<>"",ABS(W74)/AA74,"") | Z74: =_xlfn.NUMBERVALUE(Z73)+IF(V74,1,0) -> 17 | AA74: {=IF(V74,INDEX($AK$2:$AK$20,Z74,1),"")} | AB74: =IF(W74<>"",ABS(W74),"")
A75: ABUK | B75: =_xlfn.IFNA(INDEX(bf!B:B,MATCH(A75,bf!A:A,0),1),0) -> 30 | C75: =INDEX('اسعار الاسهم'!A:L,MATCH(A75,'اسعار الاسهم'!K:K,0),2) -> 86.56 | G75: =B75/C75 -> 0.34658041 | J75: =1-(_xlfn.RANK.EQ(G75,G:G,)-1)/(COUNTIF(G:G,">0")) -> 0.041666667 | K75: =_xlfn.IFNA(1-(_xlfn.RANK.EQ(H75,H:H,)-1)/(COUNTIF(H:H,">0")),0) -> 0 | L75: =_xlfn.IFNA(1-(_xlfn.RANK.EQ(I75,I:I,)-1)/(COUNTIF(I:I,">0")),0) -> 0 | M75: =$AG$2*J75+K75 *$AG$3+L75*$AG$4+$AG$5*E75+$AG$6*F75 -> 0.033333333 | N75: =OR(O75<>"",V75<>"") -> FALSE | P75: =IFERROR(T75-O75,"") | Q75: =IF(P75<>"",IF(ABS(P75)/T75>0.1,"Gny",""),"") | R75: =IF(P75<>"",ABS(P75)/T75,"") | S75: =_xlfn.NUMBERVALUE(S74)+IF(O75,1,0) -> 17 | T75: {=IF(O75,INDEX($AP$2:$AP$21,S75,1),"")} | U75: =IF(P75<>"",ABS(P75),"") | W75: =IFERROR(AA75-V75,"") | X75: =IF(W75<>"",IF(ABS(W75)/AA75>0.1,"Gny",""),"") | Y75: =IF(W75<>"",ABS(W75)/AA75,"") | Z75: =_xlfn.NUMBERVALUE(Z74)+IF(V75,1,0) -> 17 | AA75: {=IF(V75,INDEX($AK$2:$AK$20,Z75,1),"")} | AB75: =IF(W75<>"",ABS(W75),"")
A76: EGCH | B76: =_xlfn.IFNA(INDEX(bf!B:B,MATCH(A76,bf!A:A,0),1),0) -> 0 | C76: =INDEX('اسعار الاسهم'!A:L,MATCH(A76,'اسعار الاسهم'!K:K,0),2) -> 14.13 | G76: =B76/C76 -> 0 | I76: =16/C76-1 -> 0.13234253 | J76: =1-(_xlfn.RANK.EQ(G76,G:G,)-1)/(COUNTIF(G:G,">0")) -> 0 | K76: =_xlfn.IFNA(1-(_xlfn.RANK.EQ(H76,H:H,)-1)/(COUNTIF(H:H,">0")),0) -> 0 | L76: =_xlfn.IFNA(1-(_xlfn.RANK.EQ(I76,I:I,)-1)/(COUNTIF(I:I,">0")),0) -> 0.033333333 | M76: =$AG$2*J76+K76 *$AG$3+L76*$AG$4+$AG$5*E76+$AG$6*F76 -> 0.02 | N76: =OR(O76<>"",V76<>"") -> FALSE | P76: =IFERROR(T76-O76,"") | Q76: =IF(P76<>"",IF(ABS(P76)/T76>0.1,"Gny",""),"") | R76: =IF(P76<>"",ABS(P76)/T76,"") | S76: =_xlfn.NUMBERVALUE(S75)+IF(O76,1,0) -> 17 | T76: {=IF(O76,INDEX($AP$2:$AP$21,S76,1),"")} | U76: =IF(P76<>"",ABS(P76),"") | W76: =IFERROR(AA76-V76,"") | X76: =IF(W76<>"",IF(ABS(W76)/AA76>0.1,"Gny",""),"") | Y76: =IF(W76<>"",ABS(W76)/AA76,"") | Z76: =_xlfn.NUMBERVALUE(Z75)+IF(V76,1,0) -> 17 | AA76: {=IF(V76,INDEX($AK$2:$AK$20,Z76,1),"")} | AB76: =IF(W76<>"",ABS(W76),"")
A77: BIOC | B77: =_xlfn.IFNA(INDEX(bf!B:B,MATCH(A77,bf!A:A,0),1),0) -> 11.17 | C77: =INDEX('اسعار الاسهم'!A:L,MATCH(A77,'اسعار الاسهم'!K:K,0),2) -> 70.46 | G77: =B77/C77 -> 0.15852966 | J77: =1-(_xlfn.RANK.EQ(G77,G:G,)-1)/(COUNTIF(G:G,">0")) -> 0.020833333 | K77: =_xlfn.IFNA(1-(_xlfn.RANK.EQ(H77,H:H,)-1)/(COUNTIF(H:H,">0")),0) -> 0 | L77: =_xlfn.IFNA(1-(_xlfn.RANK.EQ(I77,I:I,)-1)/(COUNTIF(I:I,">0")),0) -> 0 | M77: =$AG$2*J77+K77 *$AG$3+L77*$AG$4+$AG$5*E77+$AG$6*F77 -> 0.016666667 | N77: =OR(O77<>"",V77<>"") -> FALSE | P77: =IFERROR(T77-O77,"") | Q77: =IF(P77<>"",IF(ABS(P77)/T77>0.1,"Gny",""),"") | R77: =IF(P77<>"",ABS(P77)/T77,"") | S77: =_xlfn.NUMBERVALUE(S76)+IF(O77,1,0) -> 17 | T77: {=IF(O77,INDEX($AP$2:$AP$21,S77,1),"")} | U77: =IF(P77<>"",ABS(P77),"") | W77: =IFERROR(AA77-V77,"") | X77: =IF(W77<>"",IF(ABS(W77)/AA77>0.1,"Gny",""),"") | Y77: =IF(W77<>"",ABS(W77)/AA77,"") | Z77: =_xlfn.NUMBERVALUE(Z76)+IF(V77,1,0) -> 17 | AA77: {=IF(V77,INDEX($AK$2:$AK$20,Z77,1),"")} | AB77: =IF(W77<>"",ABS(W77),"")
A78: ACAMD | B78: =_xlfn.IFNA(INDEX(bf!B:B,MATCH(A78,bf!A:A,0),1),0) -> 0 | C78: =INDEX('اسعار الاسهم'!A:L,MATCH(A78,'اسعار الاسهم'!K:K,0),2) -> 2.17 | G78: =B78/C78 -> 0 | J78: =1-(_xlfn.RANK.EQ(G78,G:G,)-1)/(COUNTIF(G:G,">0")) -> 0 | K78: =_xlfn.IFNA(1-(_xlfn.RANK.EQ(H78,H:H,)-1)/(COUNTIF(H:H,">0")),0) -> 0 | L78: =_xlfn.IFNA(1-(_xlfn.RANK.EQ(I78,I:I,)-1)/(COUNTIF(I:I,">0")),0) -> 0 | M78: =$AG$2*J78+K78 *$AG$3+L78*$AG$4+$AG$5*E78+$AG$6*F78 -> 0 | N78: =OR(O78<>"",V78<>"") -> FALSE | P78: =IFERROR(T78-O78,"") | Q78: =IF(P78<>"",IF(ABS(P78)/T78>0.1,"Gny",""),"") | R78: =IF(P78<>"",ABS(P78)/T78,"") | S78: =_xlfn.NUMBERVALUE(S77)+IF(O78,1,0) -> 17 | T78: {=IF(O78,INDEX($AP$2:$AP$21,S78,1),"")} | U78: =IF(P78<>"",ABS(P78),"") | W78: =IFERROR(AA78-V78,"") | X78: =IF(W78<>"",IF(ABS(W78)/AA78>0.1,"Gny",""),"") | Y78: =IF(W78<>"",ABS(W78)/AA78,"") | Z78: =_xlfn.NUMBERVALUE(Z77)+IF(V78,1,0) -> 17 | AA78: {=IF(V78,INDEX($AK$2:$AK$20,Z78,1),"")} | AB78: =IF(W78<>"",ABS(W78),"")
A79: ACAP | B79: =_xlfn.IFNA(INDEX(bf!B:B,MATCH(A79,bf!A:A,0),1),0) -> 0 | C79: =INDEX('اسعار الاسهم'!A:L,MATCH(A79,'اسعار الاسهم'!K:K,0),2) -> 8.3 | G79: =B79/C79 -> 0 | J79: =1-(_xlfn.RANK.EQ(G79,G:G,)-1)/(COUNTIF(G:G,">0")) -> 0 | K79: =_xlfn.IFNA(1-(_xlfn.RANK.EQ(H79,H:H,)-1)/(COUNTIF(H:H,">0")),0) -> 0 | L79: =_xlfn.IFNA(1-(_xlfn.RANK.EQ(I79,I:I,)-1)/(COUNTIF(I:I,">0")),0) -> 0 | M79: =$AG$2*J79+K79 *$AG$3+L79*$AG$4+$AG$5*E79+$AG$6*F79 -> 0 | N79: =OR(O79<>"",V79<>"") -> FALSE | P79: =IFERROR(T79-O79,"") | Q79: =IF(P79<>"",IF(ABS(P79)/T79>0.1,"Gny",""),"") | R79: =IF(P79<>"",ABS(P79)/T79,"") | S79: =_xlfn.NUMBERVALUE(S78)+IF(O79,1,0) -> 17 | T79: {=IF(O79,INDEX($AP$2:$AP$21,S79,1),"")} | U79: =IF(P79<>"",ABS(P79),"") | W79: =IFERROR(AA79-V79,"") | X79: =IF(W79<>"",IF(ABS(W79)/AA79>0.1,"Gny",""),"") | Y79: =IF(W79<>"",ABS(W79)/AA79,"") | Z79: =_xlfn.NUMBERVALUE(Z78)+IF(V79,1,0) -> 17 | AA79: {=IF(V79,INDEX($AK$2:$AK$20,Z79,1),"")} | AB79: =IF(W79<>"",ABS(W79),"")
A80: ACGC | B80: =_xlfn.IFNA(INDEX(bf!B:B,MATCH(A80,bf!A:A,0),1),0) -> 0 | C80: =INDEX('اسعار الاسهم'!A:L,MATCH(A80,'اسعار الاسهم'!K:K,0),2) -> 10.1 | G80: =B80/C80 -> 0 | J80: =1-(_xlfn.RANK.EQ(G80,G:G,)-1)/(COUNTIF(G:G,">0")) -> 0 | K80: =_xlfn.IFNA(1-(_xlfn.RANK.EQ(H80,H:H,)-1)/(COUNTIF(H:H,">0")),0) -> 0 | L80: =_xlfn.IFNA(1-(_xlfn.RANK.EQ(I80,I:I,)-1)/(COUNTIF(I:I,">0")),0) -> 0 | M80: =$AG$2*J80+K80 *$AG$3+L80*$AG$4+$AG$5*E80+$AG$6*F80 -> 0 | N80: =OR(O80<>"",V80<>"") -> FALSE | P80: =IFERROR(T80-O80,"") | Q80: =IF(P80<>"",IF(ABS(P80)/T80>0.1,"Gny",""),"") | R80: =IF(P80<>"",ABS(P80)/T80,"") | S80: =_xlfn.NUMBERVALUE(S79)+IF(O80,1,0) -> 17 | T80: {=IF(O80,INDEX($AP$2:$AP$21,S80,1),"")} | U80: =IF(P80<>"",ABS(P80),"") | W80: =IFERROR(AA80-V80,"") | X80: =IF(W80<>"",IF(ABS(W80)/AA80>0.1,"Gny",""),"") | Y80: =IF(W80<>"",ABS(W80)/AA80,"") | Z80: =_xlfn.NUMBERVALUE(Z79)+IF(V80,1,0) -> 17 | AA80: {=IF(V80,INDEX($AK$2:$AK$20,Z80,1),"")} | AB80: =IF(W80<>"",ABS(W80),"")
A81: ACTF | B81: =_xlfn.IFNA(INDEX(bf!B:B,MATCH(A81,bf!A:A,0),1),0) -> 0 | C81: =INDEX('اسعار الاسهم'!A:L,MATCH(A81,'اسعار الاسهم'!K:K,0),2) -> 2.74 | G81: =B81/C81 -> 0 | J81: =1-(_xlfn.RANK.EQ(G81,G:G,)-1)/(COUNTIF(G:G,">0")) -> 0 | K81: =_xlfn.IFNA(1-(_xlfn.RANK.EQ(H81,H:H,)-1)/(COUNTIF(H:H,">0")),0) -> 0 | L81: =_xlfn.IFNA(1-(_xlfn.RANK.EQ(I81,I:I,)-1)/(COUNTIF(I:I,">0")),0) -> 0 | M81: =$AG$2*J81+K81 *$AG$3+L81*$AG$4+$AG$5*E81+$AG$6*F81 -> 0 | N81: =OR(O81<>"",V81<>"") -> TRUE | O81: 2.95 | P81: =IFERROR(T81-O81,"") -> 0.17 | Q81: =IF(P81<>"",IF(ABS(P81)/T81>0.1,"Gny",""),"") | R81: =IF(P81<>"",ABS(P81)/T81,"") -> 0.054487179 | S81: =_xlfn.NUMBERVALUE(S80)+IF(O81,1,0) -> 18 | T81: {=IF(O81,INDEX($AP$2:$AP$21,S81,1),"")} -> 3.12 | U81: =IF(P81<>"",ABS(P81),"") -> 0.17 | W81: =IFERROR(AA81-V81,"") | X81: =IF(W81<>"",IF(ABS(W81)/AA81>0.1,"Gny",""),"") | Y81: =IF(W81<>"",ABS(W81)/AA81,"") | Z81: =_xlfn.NUMBERVALUE(Z80)+IF(V81,1,0) -> 17 | AA81: {=IF(V81,INDEX($AK$2:$AK$20,Z81,1),"")} | AB81: =IF(W81<>"",ABS(W81),"")
A82: AFDI | B82: =_xlfn.IFNA(INDEX(bf!B:B,MATCH(A82,bf!A:A,0),1),0) -> 0 | C82: =INDEX('اسعار الاسهم'!A:L,MATCH(A82,'اسعار الاسهم'!K:K,0),2) -> 41.67 | G82: =B82/C82 -> 0 | J82: =1-(_xlfn.RANK.EQ(G82,G:G,)-1)/(COUNTIF(G:G,">0")) -> 0 | K82: =_xlfn.IFNA(1-(_xlfn.RANK.EQ(H82,H:H,)-1)/(COUNTIF(H:H,">0")),0) -> 0 | L82: =_xlfn.IFNA(1-(_xlfn.RANK.EQ(I82,I:I,)-1)/(COUNTIF(I:I,">0")),0) -> 0 | M82: =$AG$2*J82+K82 *$AG$3+L82*$AG$4+$AG$5*E82+$AG$6*F82 -> 0 | N82: =OR(O82<>"",V82<>"") -> FALSE | P82: =IFERROR(T82-O82,"") | Q82: =IF(P82<>"",IF(ABS(P82)/T82>0.1,"Gny",""),"") | R82: =IF(P82<>"",ABS(P82)/T82,"") | S82: =_xlfn.NUMBERVALUE(S81)+IF(O82,1,0) -> 18 | T82: {=IF(O82,INDEX($AP$2:$AP$21,S82,1),"")} | U82: =IF(P82<>"",ABS(P82),"") | W82: =IFERROR(AA82-V82,"") | X82: =IF(W82<>"",IF(ABS(W82)/AA82>0.1,"Gny",""),"") | Y82: =IF(W82<>"",ABS(W82)/AA82,"") | Z82: =_xlfn.NUMBERVALUE(Z81)+IF(V82,1,0) -> 17 | AA82: {=IF(V82,INDEX($AK$2:$AK$20,Z82,1),"")} | AB82: =IF(W82<>"",ABS(W82),"")
A83: AFMC | B83: =_xlfn.IFNA(INDEX(bf!B:B,MATCH(A83,bf!A:A,0),1),0) -> 0 | C83: =INDEX('اسعار الاسهم'!A:L,MATCH(A83,'اسعار الاسهم'!K:K,0),2) -> 70.95 | G83: =B83/C83 -> 0 | J83: =1-(_xlfn.RANK.EQ(G83,G:G,)-1)/(COUNTIF(G:G,">0")) -> 0 | K83: =_xlfn.IFNA(1-(_xlfn.RANK.EQ(H83,H:H,)-1)/(COUNTIF(H:H,">0")),0) -> 0 | L83: =_xlfn.IFNA(1-(_xlfn.RANK.EQ(I83,I:I,)-1)/(COUNTIF(I:I,">0")),0) -> 0 | M83: =$AG$2*J83+K83 *$AG$3+L83*$AG$4+$AG$5*E83+$AG$6*F83 -> 0 | N83: =OR(O83<>"",V83<>"") -> FALSE | P83: =IFERROR(T83-O83,"") | Q83: =IF(P83<>"",IF(ABS(P83)/T83>0.1,"Gny",""),"") | R83: =IF(P83<>"",ABS(P83)/T83,"") | S83: =_xlfn.NUMBERVALUE(S82)+IF(O83,1,0) -> 18 | T83: {=IF(O83,INDEX($AP$2:$AP$21,S83,1),"")} | U83: =IF(P83<>"",ABS(P83),"") | W83: =IFERROR(AA83-V83,"") | X83: =IF(W83<>"",IF(ABS(W83)/AA83>0.1,"Gny",""),"") | Y83: =IF(W83<>"",ABS(W83)/AA83,"") | Z83: =_xlfn.NUMBERVALUE(Z82)+IF(V83,1,0) -> 17 | AA83: {=IF(V83,INDEX($AK$2:$AK$20,Z83,1),"")} | AB83: =IF(W83<>"",ABS(W83),"")
A84: AIH | B84: =_xlfn.IFNA(INDEX(bf!B:B,MATCH(A84,bf!A:A,0),1),0) -> 0 | C84: =INDEX('اسعار الاسهم'!A:L,MATCH(A84,'اسعار الاسهم'!K:K,0),2) -> 0.34 | G84: =B84/C84 -> 0 | J84: =1-(_xlfn.RANK.EQ(G84,G:G,)-1)/(COUNTIF(G:G,">0")) -> 0 | K84: =_xlfn.IFNA(1-(_xlfn.RANK.EQ(H84,H:H,)-1)/(COUNTIF(H:H,">0")),0) -> 0 | L84: =_xlfn.IFNA(1-(_xlfn.RANK.EQ(I84,I:I,)-1)/(COUNTIF(I:I,">0")),0) -> 0 | M84: =$AG$2*J84+K84 *$AG$3+L84*$AG$4+$AG$5*E84+$AG$6*F84 -> 0 | N84: =OR(O84<>"",V84<>"") -> FALSE | P84: =IFERROR(T84-O84,"") | Q84: =IF(P84<>"",IF(ABS(P84)/T84>0.1,"Gny",""),"") | R84: =IF(P84<>"",ABS(P84)/T84,"") | S84: =_xlfn.NUMBERVALUE(S83)+IF(O84,1,0) -> 18 | T84: {=IF(O84,INDEX($AP$2:$AP$21,S84,1),"")} | U84: =IF(P84<>"",ABS(P84),"") | W84: =IFERROR(AA84-V84,"") | X84: =IF(W84<>"",IF(ABS(W84)/AA84>0.1,"Gny",""),"") | Y84: =IF(W84<>"",ABS(W84)/AA84,"") | Z84: =_xlfn.NUMBERVALUE(Z83)+IF(V84,1,0) -> 17 | AA84: {=IF(V84,INDEX($AK$2:$AK$20,Z84,1),"")} | AB84: =IF(W84<>"",ABS(W84),"")
A85: ALUM | B85: =_xlfn.IFNA(INDEX(bf!B:B,MATCH(A85,bf!A:A,0),1),0) -> 0 | C85: =INDEX('اسعار الاسهم'!A:L,MATCH(A85,'اسعار الاسهم'!K:K,0),2) -> 24.7 | G85: =B85/C85 -> 0 | J85: =1-(_xlfn.RANK.EQ(G85,G:G,)-1)/(COUNTIF(G:G,">0")) -> 0 | K85: =_xlfn.IFNA(1-(_xlfn.RANK.EQ(H85,H:H,)-1)/(COUNTIF(H:H,">0")),0) -> 0 | L85: =_xlfn.IFNA(1-(_xlfn.RANK.EQ(I85,I:I,)-1)/(COUNTIF(I:I,">0")),0) -> 0 | M85: =$AG$2*J85+K85 *$AG$3+L85*$AG$4+$AG$5*E85+$AG$6*F85 -> 0 | N85: =OR(O85<>"",V85<>"") -> FALSE | P85: =IFERROR(T85-O85,"") | Q85: =IF(P85<>"",IF(ABS(P85)/T85>0.1,"Gny",""),"") | R85: =IF(P85<>"",ABS(P85)/T85,"") | S85: =_xlfn.NUMBERVALUE(S84)+IF(O85,1,0) -> 18 | T85: {=IF(O85,INDEX($AP$2:$AP$21,S85,1),"")} | U85: =IF(P85<>"",ABS(P85),"") | W85: =IFERROR(AA85-V85,"") | X85: =IF(W85<>"",IF(ABS(W85)/AA85>0.1,"Gny",""),"") | Y85: =IF(W85<>"",ABS(W85)/AA85,"") | Z85: =_xlfn.NUMBERVALUE(Z84)+IF(V85,1,0) -> 17 | AA85: {=IF(V85,INDEX($AK$2:$AK$20,Z85,1),"")} | AB85: =IF(W85<>"",ABS(W85),"")
A86: AMIA | B86: =_xlfn.IFNA(INDEX(bf!B:B,MATCH(A86,bf!A:A,0),1),0) -> 0 | C86: =INDEX('اسعار الاسهم'!A:L,MATCH(A86,'اسعار الاسهم'!K:K,0),2) -> 8.7 | G86: =B86/C86 -> 0 | J86: =1-(_xlfn.RANK.EQ(G86,G:G,)-1)/(COUNTIF(G:G,">0")) -> 0 | K86: =_xlfn.IFNA(1-(_xlfn.RANK.EQ(H86,H:H,)-1)/(COUNTIF(H:H,">0")),0) -> 0 | L86: =_xlfn.IFNA(1-(_xlfn.RANK.EQ(I86,I:I,)-1)/(COUNTIF(I:I,">0")),0) -> 0 | M86: =$AG$2*J86+K86 *$AG$3+L86*$AG$4+$AG$5*E86+$AG$6*F86 -> 0 | N86: =OR(O86<>"",V86<>"") -> FALSE | P86: =IFERROR(T86-O86,"") | Q86: =IF(P86<>"",IF(ABS(P86)/T86>0.1,"Gny",""),"") | R86: =IF(P86<>"",ABS(P86)/T86,"") | S86: =_xlfn.NUMBERVALUE(S85)+IF(O86,1,0) -> 18 | T86: {=IF(O86,INDEX($AP$2:$AP$21,S86,1),"")} | U86: =IF(P86<>"",ABS(P86),"") | W86: =IFERROR(AA86-V86,"") | X86: =IF(W86<>"",IF(ABS(W86)/AA86>0.1,"Gny",""),"") | Y86: =IF(W86<>"",ABS(W86)/AA86,"") | Z86: =_xlfn.NUMBERVALUE(Z85)+IF(V86,1,0) -> 17 | AA86: {=IF(V86,INDEX($AK$2:$AK$20,Z86,1),"")} | AB86: =IF(W86<>"",ABS(W86),"")
A87: AMOC | B87: =_xlfn.IFNA(INDEX(bf!B:B,MATCH(A87,bf!A:A,0),1),0) -> 0 | C87: =INDEX('اسعار الاسهم'!A:L,MATCH(A87,'اسعار الاسهم'!K:K,0),2) -> 8.35 | G87: =B87/C87 -> 0 | J87: =1-(_xlfn.RANK.EQ(G87,G:G,)-1)/(COUNTIF(G:G,">0")) -> 0 | K87: =_xlfn.IFNA(1-(_xlfn.RANK.EQ(H87,H:H,)-1)/(COUNTIF(H:H,">0")),0) -> 0 | L87: =_xlfn.IFNA(1-(_xlfn.RANK.EQ(I87,I:I,)-1)/(COUNTIF(I:I,">0")),0) -> 0 | M87: =$AG$2*J87+K87 *$AG$3+L87*$AG$4+$AG$5*E87+$AG$6*F87 -> 0 | N87: =OR(O87<>"",V87<>"") -> FALSE | P87: =IFERROR(T87-O87,"") | Q87: =IF(P87<>"",IF(ABS(P87)/T87>0.1,"Gny",""),"") | R87: =IF(P87<>"",ABS(P87)/T87,"") | S87: =_xlfn.NUMBERVALUE(S86)+IF(O87,1,0) -> 18 | T87: {=IF(O87,INDEX($AP$2:$AP$21,S87,1),"")} | U87: =IF(P87<>"",ABS(P87),"") | W87: =IFERROR(AA87-V87,"") | X87: =IF(W87<>"",IF(ABS(W87)/AA87>0.1,"Gny",""),"") | Y87: =IF(W87<>"",ABS(W87)/AA87,"") | Z87: =_xlfn.NUMBERVALUE(Z86)+IF(V87,1,0) -> 17 | AA87: {=IF(V87,INDEX($AK$2:$AK$20,Z87,1),"")} | AB87: =IF(W87<>"",ABS(W87),"")
A88: AREH | B88: =_xlfn.IFNA(INDEX(bf!B:B,MATCH(A88,bf!A:A,0),1),0) -> 0 | C88: =INDEX('اسعار الاسهم'!A:L,MATCH(A88,'اسعار الاسهم'!K:K,0),2) -> 1.3 | G88: =B88/C88 -> 0 | J88: =1-(_xlfn.RANK.EQ(G88,G:G,)-1)/(COUNTIF(G:G,">0")) -> 0 | K88: =_xlfn.IFNA(1-(_xlfn.RANK.EQ(H88,H:H,)-1)/(COUNTIF(H:H,">0")),0) -> 0 | L88: =_xlfn.IFNA(1-(_xlfn.RANK.EQ(I88,I:I,)-1)/(COUNTIF(I:I,">0")),0) -> 0 | M88: =$AG$2*J88+K88 *$AG$3+L88*$AG$4+$AG$5*E88+$AG$6*F88 -> 0 | N88: =OR(O88<>"",V88<>"") -> FALSE | P88: =IFERROR(T88-O88,"") | Q88: =IF(P88<>"",IF(ABS(P88)/T88>0.1,"Gny",""),"") | R88: =IF(P88<>"",ABS(P88)/T88,"") | S88: =_xlfn.NUMBERVALUE(S87)+IF(O88,1,0) -> 18 | T88: {=IF(O88,INDEX($AP$2:$AP$21,S88,1),"")} | U88: =IF(P88<>"",ABS(P88),"") | W88: =IFERROR(AA88-V88,"") | X88: =IF(W88<>"",IF(ABS(W88)/AA88>0.1,"Gny",""),"") | Y88: =IF(W88<>"",ABS(W88)/AA88,"") | Z88: =_xlfn.NUMBERVALUE(Z87)+IF(V88,1,0) -> 17 | AA88: {=IF(V88,INDEX($AK$2:$AK$20,Z88,1),"")} | AB88: =IF(W88<>"",ABS(W88),"")
A89: ARVA | B89: =_xlfn.IFNA(INDEX(bf!B:B,MATCH(A89,bf!A:A,0),1),0) -> 0 | C89: =INDEX('اسعار الاسهم'!A:L,MATCH(A89,'اسعار الاسهم'!K:K,0),2) -> 8.37 | G89: =B89/C89 -> 0 | J89: =1-(_xlfn.RANK.EQ(G89,G:G,)-1)/(COUNTIF(G:G,">0")) -> 0 | K89: =_xlfn.IFNA(1-(_xlfn.RANK.EQ(H89,H:H,)-1)/(COUNTIF(H:H,">0")),0) -> 0 | L89: =_xlfn.IFNA(1-(_xlfn.RANK.EQ(I89,I:I,)-1)/(COUNTIF(I:I,">0")),0) -> 0 | M89: =$AG$2*J89+K89 *$AG$3+L89*$AG$4+$AG$5*E89+$AG$6*F89 -> 0 | N89: =OR(O89<>"",V89<>"") -> FALSE | P89: =IFERROR(T89-O89,"") | Q89: =IF(P89<>"",IF(ABS(P89)/T89>0.1,"Gny",""),"") | R89: =IF(P89<>"",ABS(P89)/T89,"") | S89: =_xlfn.NUMBERVALUE(S88)+IF(O89,1,0) -> 18 | T89: {=IF(O89,INDEX($AP$2:$AP$21,S89,1),"")} | U89: =IF(P89<>"",ABS(P89),"") | W89: =IFERROR(AA89-V89,"") | X89: =IF(W89<>"",IF(ABS(W89)/AA89>0.1,"Gny",""),"") | Y89: =IF(W89<>"",ABS(W89)/AA89,"") | Z89: =_xlfn.NUMBERVALUE(Z88)+IF(V89,1,0) -> 17 | AA89: {=IF(V89,INDEX($AK$2:$AK$20,Z89,1),"")} | AB89: =IF(W89<>"",ABS(W89),"")
A90: ASCM | B90: =_xlfn.IFNA(INDEX(bf!B:B,MATCH(A90,bf!A:A,0),1),0) -> 0 | C90: =INDEX('اسعار الاسهم'!A:L,MATCH(A90,'اسعار الاسهم'!K:K,0),2) -> 47.7 | G90: =B90/C90 -> 0 | J90: =1-(_xlfn.RANK.EQ(G90,G:G,)-1)/(COUNTIF(G:G,">0")) -> 0 | K90: =_xlfn.IFNA(1-(_xlfn.RANK.EQ(H90,H:H,)-1)/(COUNTIF(H:H,">0")),0) -> 0 | L90: =_xlfn.IFNA(1-(_xlfn.RANK.EQ(I90,I:I,)-1)/(COUNTIF(I:I,">0")),0) -> 0 | M90: =$AG$2*J90+K90 *$AG$3+L90*$AG$4+$AG$5*E90+$AG$6*F90 -> 0 | N90: =OR(O90<>"",V90<>"") -> FALSE | P90: =IFERROR(T90-O90,"") | Q90: =IF(P90<>"",IF(ABS(P90)/T90>0.1,"Gny",""),"") | R90: =IF(P90<>"",ABS(P90)/T90,"") | S90: =_xlfn.NUMBERVALUE(S89)+IF(O90,1,0) -> 18 | T90: {=IF(O90,INDEX($AP$2:$AP$21,S90,1),"")} | U90: =IF(P90<>"",ABS(P90),"") | W90: =IFERROR(AA90-V90,"") | X90: =IF(W90<>"",IF(ABS(W90)/AA90>0.1,"Gny",""),"") | Y90: =IF(W90<>"",ABS(W90)/AA90,"") | Z90: =_xlfn.NUMBERVALUE(Z89)+IF(V90,1,0) -> 17 | AA90: {=IF(V90,INDEX($AK$2:$AK$20,Z90,1),"")} | AB90: =IF(W90<>"",ABS(W90),"")
A91: ASPI | B91: =_xlfn.IFNA(INDEX(bf!B:B,MATCH(A91,bf!A:A,0),1),0) -> 0 | C91: =INDEX('اسعار الاسهم'!A:L,MATCH(A91,'اسعار الاسهم'!K:K,0),2) -> 0.3 | G91: =B91/C91 -> 0 | J91: =1-(_xlfn.RANK.EQ(G91,G:G,)-1)/(COUNTIF(G:G,">0")) -> 0 | K91: =_xlfn.IFNA(1-(_xlfn.RANK.EQ(H91,H:H,)-1)/(COUNTIF(H:H,">0")),0) -> 0 | L91: =_xlfn.IFNA(1-(_xlfn.RANK.EQ(I91,I:I,)-1)/(COUNTIF(I:I,">0")),0) -> 0 | M91: =$AG$2*J91+K91 *$AG$3+L91*$AG$4+$AG$5*E91+$AG$6*F91 -> 0 | N91: =OR(O91<>"",V91<>"") -> FALSE | P91: =IFERROR(T91-O91,"") | Q91: =IF(P91<>"",IF(ABS(P91)/T91>0.1,"Gny",""),"") | R91: =IF(P91<>"",ABS(P91)/T91,"") | S91: =_xlfn.NUMBERVALUE(S90)+IF(O91,1,0) -> 18 | T91: {=IF(O91,INDEX($AP$2:$AP$21,S91,1),"")} | U91: =IF(P91<>"",ABS(P91),"") | W91: =IFERROR(AA91-V91,"") | X91: =IF(W91<>"",IF(ABS(W91)/AA91>0.1,"Gny",""),"") | Y91: =IF(W91<>"",ABS(W91)/AA91,"") | Z91: =_xlfn.NUMBERVALUE(Z90)+IF(V91,1,0) -> 17 | AA91: {=IF(V91,INDEX($AK$2:$AK$20,Z91,1),"")} | AB91: =IF(W91<>"",ABS(W91),"")
A92: BTFH | B92: =_xlfn.IFNA(INDEX(bf!B:B,MATCH(A92,bf!A:A,0),1),0) -> 0 | C92: =INDEX('اسعار الاسهم'!A:L,MATCH(A92,'اسعار الاسهم'!K:K,0),2) -> 3.08 | G92: =B92/C92 -> 0 | J92: =1-(_xlfn.RANK.EQ(G92,G:G,)-1)/(COUNTIF(G:G,">0")) -> 0 | K92: =_xlfn.IFNA(1-(_xlfn.RANK.EQ(H92,H:H,)-1)/(COUNTIF(H:H,">0")),0) -> 0 | L92: =_xlfn.IFNA(1-(_xlfn.RANK.EQ(I92,I:I,)-1)/(COUNTIF(I:I,">0")),0) -> 0 | M92: =$AG$2*J92+K92 *$AG$3+L92*$AG$4+$AG$5*E92+$AG$6*F92 -> 0 | N92: =OR(O92<>"",V92<>"") -> FALSE | P92: =IFERROR(T92-O92,"") | Q92: =IF(P92<>"",IF(ABS(P92)/T92>0.1,"Gny",""),"") | R92: =IF(P92<>"",ABS(P92)/T92,"") | S92: =_xlfn.NUMBERVALUE(S91)+IF(O92,1,0) -> 18 | T92: {=IF(O92,INDEX($AP$2:$AP$21,S92,1),"")} | U92: =IF(P92<>"",ABS(P92),"") | W92: =IFERROR(AA92-V92,"") | X92: =IF(W92<>"",IF(ABS(W92)/AA92>0.1,"Gny",""),"") | Y92: =IF(W92<>"",ABS(W92)/AA92,"") | Z92: =_xlfn.NUMBERVALUE(Z91)+IF(V92,1,0) -> 17 | AA92: {=IF(V92,INDEX($AK$2:$AK$20,Z92,1),"")} | AB92: =IF(W92<>"",ABS(W92),"")
A93: CANA | B93: =_xlfn.IFNA(INDEX(bf!B:B,MATCH(A93,bf!A:A,0),1),0) -> 0 | C93: =INDEX('اسعار الاسهم'!A:L,MATCH(A93,'اسعار الاسهم'!K:K,0),2) -> 34.5 | G93: =B93/C93 -> 0 | J93: =1-(_xlfn.RANK.EQ(G93,G:G,)-1)/(COUNTIF(G:G,">0")) -> 0 | K93: =_xlfn.IFNA(1-(_xlfn.RANK.EQ(H93,H:H,)-1)/(COUNTIF(H:H,">0")),0) -> 0 | L93: =_xlfn.IFNA(1-(_xlfn.RANK.EQ(I93,I:I,)-1)/(COUNTIF(I:I,">0")),0) -> 0 | M93: =$AG$2*J93+K93 *$AG$3+L93*$AG$4+$AG$5*E93+$AG$6*F93 -> 0 | N93: =OR(O93<>"",V93<>"") -> FALSE | P93: =IFERROR(T93-O93,"") | Q93: =IF(P93<>"",IF(ABS(P93)/T93>0.1,"Gny",""),"") | R93: =IF(P93<>"",ABS(P93)/T93,"") | S93: =_xlfn.NUMBERVALUE(S92)+IF(O93,1,0) -> 18 | T93: {=IF(O93,INDEX($AP$2:$AP$21,S93,1),"")} | U93: =IF(P93<>"",ABS(P93),"") | W93: =IFERROR(AA93-V93,"") | X93: =IF(W93<>"",IF(ABS(W93)/AA93>0.1,"Gny",""),"") | Y93: =IF(W93<>"",ABS(W93)/AA93,"") | Z93: =_xlfn.NUMBERVALUE(Z92)+IF(V93,1,0) -> 17 | AA93: {=IF(V93,INDEX($AK$2:$AK$20,Z93,1),"")} | AB93: =IF(W93<>"",ABS(W93),"")
... A110: ELKA | B110: =_xlfn.IFNA(INDEX(bf!B:B,MATCH(A110,bf!A:A,0),1),0) -> 0 | C110: =INDEX('اسعار الاسهم'!A:L,MATCH(A110,'اسعار الاسهم'!K:K,0),2) -> 1.14 | G110: =B110/C110 -> 0 | J110: =1-(_xlfn.RANK.EQ(G110,G:G,)-1)/(COUNTIF(G:G,">0")) -> 0 | K110: =_xlfn.IFNA(1-(_xlfn.RANK.EQ(H110,H:H,)-1)/(COUNTIF(H:H,">0")),0) -> 0 | L110: =_xlfn.IFNA(1-(_xlfn.RANK.EQ(I110,I:I,)-1)/(COUNTIF(I:I,">0")),0) -> 0 | M110: =$AG$2*J110+K110 *$AG$3+L110*$AG$4+$AG$5*E110+$AG$6*F110 -> 0 | N110: =OR(O110<>"",V110<>"") -> FALSE | P110: =IFERROR(T110-O110,"") | Q110: =IF(P110<>"",IF(ABS(P110)/T110>0.1,"Gny",""),"") | R110: =IF(P110<>"",ABS(P110)/T110,"") | S110: =_xlfn.NUMBERVALUE(S109)+IF(O110,1,0) -> 18 | T110: {=IF(O110,INDEX($AP$2:$AP$21,S110,1),"")} | U110: =IF(P110<>"",ABS(P110),"") | W110: =IFERROR(AA110-V110,"") | X110: =IF(W110<>"",IF(ABS(W110)/AA110>0.1,"Gny",""),"") | Y110: =IF(W110<>"",ABS(W110)/AA110,"") | Z110: =_xlfn.NUMBERVALUE(Z109)+IF(V110,1,0) -> 17 | AA110: {=IF(V110,INDEX($AK$2:$AK$20,Z110,1),"")} | AB110: =IF(W110<>"",ABS(W110),"")
A111: EPCO | B111: =_xlfn.IFNA(INDEX(bf!B:B,MATCH(A111,bf!A:A,0),1),0) -> 0 | C111: =INDEX('اسعار الاسهم'!A:L,MATCH(A111,'اسعار الاسهم'!K:K,0),2) -> 8.94 | G111: =B111/C111 -> 0 | J111: =1-(_xlfn.RANK.EQ(G111,G:G,)-1)/(COUNTIF(G:G,">0")) -> 0 | K111: =_xlfn.IFNA(1-(_xlfn.RANK.EQ(H111,H:H,)-1)/(COUNTIF(H:H,">0")),0) -> 0 | L111: =_xlfn.IFNA(1-(_xlfn.RANK.EQ(I111,I:I,)-1)/(COUNTIF(I:I,">0")),0) -> 0 | M111: =$AG$2*J111+K111 *$AG$3+L111*$AG$4+$AG$5*E111+$AG$6*F111 -> 0 | N111: =OR(O111<>"",V111<>"") -> FALSE | P111: =IFERROR(T111-O111,"") | Q111: =IF(P111<>"",IF(ABS(P111)/T111>0.1,"Gny",""),"") | R111: =IF(P111<>"",ABS(P111)/T111,"") | S111: =_xlfn.NUMBERVALUE(S110)+IF(O111,1,0) -> 18 | T111: {=IF(O111,INDEX($AP$2:$AP$21,S111,1),"")} | U111: =IF(P111<>"",ABS(P111),"") | W111: =IFERROR(AA111-V111,"") | X111: =IF(W111<>"",IF(ABS(W111)/AA111>0.1,"Gny",""),"") | Y111: =IF(W111<>"",ABS(W111)/AA111,"") | Z111: =_xlfn.NUMBERVALUE(Z110)+IF(V111,1,0) -> 17 | AA111: {=IF(V111,INDEX($AK$2:$AK$20,Z111,1),"")} | AB111: =IF(W111<>"",ABS(W111),"") | AD111: 1
A112: ESRS | B112: =_xlfn.IFNA(INDEX(bf!B:B,MATCH(A112,bf!A:A,0),1),0) -> 0 | C112: =INDEX('اسعار الاسهم'!A:L,MATCH(A112,'اسعار الاسهم'!K:K,0),2) -> 141 | G112: =B112/C112 -> 0 | J112: =1-(_xlfn.RANK.EQ(G112,G:G,)-1)/(COUNTIF(G:G,">0")) -> 0 | K112: =_xlfn.IFNA(1-(_xlfn.RANK.EQ(H112,H:H,)-1)/(COUNTIF(H:H,">0")),0) -> 0 | L112: =_xlfn.IFNA(1-(_xlfn.RANK.EQ(I112,I:I,)-1)/(COUNTIF(I:I,">0")),0) -> 0 | M112: =$AG$2*J112+K112 *$AG$3+L112*$AG$4+$AG$5*E112+$AG$6*F112 -> 0 | N112: =OR(O112<>"",V112<>"") -> FALSE | P112: =IFERROR(T112-O112,"") | Q112: =IF(P112<>"",IF(ABS(P112)/T112>0.1,"Gny",""),"") | R112: =IF(P112<>"",ABS(P112)/T112,"") | S112: =_xlfn.NUMBERVALUE(S111)+IF(O112,1,0) -> 18 | T112: {=IF(O112,INDEX($AP$2:$AP$21,S112,1),"")} | U112: =IF(P112<>"",ABS(P112),"") | W112: =IFERROR(AA112-V112,"") | X112: =IF(W112<>"",IF(ABS(W112)/AA112>0.1,"Gny",""),"") | Y112: =IF(W112<>"",ABS(W112)/AA112,"") | Z112: =_xlfn.NUMBERVALUE(Z111)+IF(V112,1,0) -> 17 | AA112: {=IF(V112,INDEX($AK$2:$AK$20,Z112,1),"")} | AB112: =IF(W112<>"",ABS(W112),"")
A113: FAIT | B113: =_xlfn.IFNA(INDEX(bf!B:B,MATCH(A113,bf!A:A,0),1),0) -> 0 | C113: =INDEX('اسعار الاسهم'!A:L,MATCH(A113,'اسعار الاسهم'!K:K,0),2) -> 37.4 | G113: =B113/C113 -> 0 | J113: =1-(_xlfn.RANK.EQ(G113,G:G,)-1)/(COUNTIF(G:G,">0")) -> 0 | K113: =_xlfn.IFNA(1-(_xlfn.RANK.EQ(H113,H:H,)-1)/(COUNTIF(H:H,">0")),0) -> 0 | L113: =_xlfn.IFNA(1-(_xlfn.RANK.EQ(I113,I:I,)-1)/(COUNTIF(I:I,">0")),0) -> 0 | M113: =$AG$2*J113+K113 *$AG$3+L113*$AG$4+$AG$5*E113+$AG$6*F113 -> 0 | N113: =OR(O113<>"",V113<>"") -> FALSE | P113: =IFERROR(T113-O113,"") | Q113: =IF(P113<>"",IF(ABS(P113)/T113>0.1,"Gny",""),"") | R113: =IF(P113<>"",ABS(P113)/T113,"") | S113: =_xlfn.NUMBERVALUE(S112)+IF(O113,1,0) -> 18 | T113: {=IF(O113,INDEX($AP$2:$AP$21,S113,1),"")} | U113: =IF(P113<>"",ABS(P113),"") | W113: =IFERROR(AA113-V113,"") | X113: =IF(W113<>"",IF(ABS(W113)/AA113>0.1,"Gny",""),"") | Y113: =IF(W113<>"",ABS(W113)/AA113,"") | Z113: =_xlfn.NUMBERVALUE(Z112)+IF(V113,1,0) -> 17 | AA113: {=IF(V113,INDEX($AK$2:$AK$20,Z113,1),"")} | AB113: =IF(W113<>"",ABS(W113),"")
A114: GGCC | B114: =_xlfn.IFNA(INDEX(bf!B:B,MATCH(A114,bf!A:A,0),1),0) -> 0 | C114: =INDEX('اسعار الاسهم'!A:L,MATCH(A114,'اسعار الاسهم'!K:K,0),2) -> 0.39 | G114: =B114/C114 -> 0 | J114: =1-(_xlfn.RANK.EQ(G114,G:G,)-1)/(COUNTIF(G:G,">0")) -> 0 | K114: =_xlfn.IFNA(1-(_xlfn.RANK.EQ(H114,H:H,)-1)/(COUNTIF(H:H,">0")),0) -> 0 | L114: =_xlfn.IFNA(1-(_xlfn.RANK.EQ(I114,I:I,)-1)/(COUNTIF(I:I,">0")),0) -> 0 | M114: =$AG$2*J114+K114 *$AG$3+L114*$AG$4+$AG$5*E114+$AG$6*F114 -> 0 | N114: =OR(O114<>"",V114<>"") -> FALSE | P114: =IFERROR(T114-O114,"") | Q114: =IF(P114<>"",IF(ABS(P114)/T114>0.1,"Gny",""),"") | R114: =IF(P114<>"",ABS(P114)/T114,"") | S114: =_xlfn.NUMBERVALUE(S112)+IF(O114,1,0) -> 18 | T114: {=IF(O114,INDEX($AP$2:$AP$21,S114,1),"")} | U114: =IF(P114<>"",ABS(P114),"") | W114: =IFERROR(AA114-V114,"") | X114: =IF(W114<>"",IF(ABS(W114)/AA114>0.1,"Gny",""),"") | Y114: =IF(W114<>"",ABS(W114)/AA114,"") | Z114: =_xlfn.NUMBERVALUE(Z113)+IF(V114,1,0) -> 17 | AA114: {=IF(V114,INDEX($AK$2:$AK$20,Z114,1),"")} | AB114: =IF(W114<>"",ABS(W114),"")
A115: GGRN | B115: =_xlfn.IFNA(INDEX(bf!B:B,MATCH(A115,bf!A:A,0),1),0) -> 0 | C115: =INDEX('اسعار الاسهم'!A:L,MATCH(A115,'اسعار الاسهم'!K:K,0),2) -> 1.42 | G115: =B115/C115 -> 0 | J115: =1-(_xlfn.RANK.EQ(G115,G:G,)-1)/(COUNTIF(G:G,">0")) -> 0 | K115: =_xlfn.IFNA(1-(_xlfn.RANK.EQ(H115,H:H,)-1)/(COUNTIF(H:H,">0")),0) -> 0 | L115: =_xlfn.IFNA(1-(_xlfn.RANK.EQ(I115,I:I,)-1)/(COUNTIF(I:I,">0")),0) -> 0 | M115: =$AG$2*J115+K115 *$AG$3+L115*$AG$4+$AG$5*E115+$AG$6*F115 -> 0 | N115: =OR(O115<>"",V115<>"") -> FALSE | P115: =IFERROR(T115-O115,"") | Q115: =IF(P115<>"",IF(ABS(P115)/T115>0.1,"Gny",""),"") | R115: =IF(P115<>"",ABS(P115)/T115,"") | S115: =_xlfn.NUMBERVALUE(S113)+IF(O115,1,0) -> 18 | T115: {=IF(O115,INDEX($AP$2:$AP$21,S115,1),"")} | U115: =IF(P115<>"",ABS(P115),"") | W115: =IFERROR(AA115-V115,"") | X115: =IF(W115<>"",IF(ABS(W115)/AA115>0.1,"Gny",""),"") | Y115: =IF(W115<>"",ABS(W115)/AA115,"") | Z115: =_xlfn.NUMBERVALUE(Z113)+IF(V115,1,0) -> 17 | AA115: {=IF(V115,INDEX($AK$2:$AK$20,Z115,1),"")} | AB115: =IF(W115<>"",ABS(W115),"")
A116: HBCO | B116: =_xlfn.IFNA(INDEX(bf!B:B,MATCH(A116,bf!A:A,0),1),0) -> 0 | C116: =INDEX('اسعار الاسهم'!A:L,MATCH(A116,'اسعار الاسهم'!K:K,0),2) -> 7.92 | G116: =B116/C116 -> 0 | J116: =1-(_xlfn.RANK.EQ(G116,G:G,)-1)/(COUNTIF(G:G,">0")) -> 0 | K116: =_xlfn.IFNA(1-(_xlfn.RANK.EQ(H116,H:H,)-1)/(COUNTIF(H:H,">0")),0) -> 0 | L116: =_xlfn.IFNA(1-(_xlfn.RANK.EQ(I116,I:I,)-1)/(COUNTIF(I:I,">0")),0) -> 0 | M116: =$AG$2*J116+K116 *$AG$3+L116*$AG$4+$AG$5*E116+$AG$6*F116 -> 0 | N116: =OR(O116<>"",V116<>"") -> TRUE | O116: 3.24 | P116: =IFERROR(T116-O116,"") -> -0.28 | Q116: =IF(P116<>"",IF(ABS(P116)/T116>0.1,"Gny",""),"") | R116: =IF(P116<>"",ABS(P116)/T116,"") -> 0.094594595 | S116: =_xlfn.NUMBERVALUE(S115)+IF(O116,1,0) -> 19 | T116: {=IF(O116,INDEX($AP$2:$AP$21,S116,1),"")} -> 2.96 | U116: =IF(P116<>"",ABS(P116),"") -> 0.28 | V116: 45.2 | W116: =IFERROR(AA116-V116,"") -> -0.2 | X116: =IF(W116<>"",IF(ABS(W116)/AA116>0.1,"Gny",""),"") | Y116: =IF(W116<>"",ABS(W116)/AA116,"") -> 0.0044444444 | Z116: =_xlfn.NUMBERVALUE(Z115)+IF(V116,1,0) -> 18 | AA116: {=IF(V116,INDEX($AK$2:$AK$20,Z116,1),"")} -> 45 | AB116: =IF(W116<>"",ABS(W116),"") -> 0.2
...

Sheet ra2eb egabia
A1: sahm | B1: egaby | C1: current | D1: ba2y | F1: rank | G1: sahm | H1: 45764 | I1: توزيعات | J1: today | K1: performance
A2: ebsc | B2: 1.29 | C2: =INDEX('اسعار الاسهم'!A:B,MATCH(A2,'اسعار الاسهم'!K:K,0),2) -> 1.66 | D2: =1-C2/B2 -> -0.28682171 | F2: 5 | G2: hdbk | H2: 50.79 | I2: =5+8 -> 13 | J2: =I2+INDEX('اسعار الاسهم'!A:B,MATCH(G2,'اسعار الاسهم'!K:K,0),2) -> 156.45 | K2: =J2/H2-1 -> 2.0803308
A3: swdy | B3: 79.25 | C3: =INDEX('اسعار الاسهم'!A:B,MATCH(A3,'اسعار الاسهم'!K:K,0),2) -> 87.9 | D3: =1-C3/B3 -> -0.10914826 | F3: 1 | G3: adib | H3: =41.46/2/1.25 -> 16.584 | J3: =I3+INDEX('اسعار الاسهم'!A:B,MATCH(G3,'اسعار الاسهم'!K:K,0),2) -> 46.1 | K3: =J3/H3-1 -> 1.7797877
A4: zmid | B4: 3.35 | C4: =INDEX('اسعار الاسهم'!A:B,MATCH(A4,'اسعار الاسهم'!K:K,0),2) -> 5.86 | D4: =1-C4/B4 -> -0.74925373 | F4: 2 | G4: qnbe | H4: 28.31 | I4: =2+1.5 -> 3.5 | J4: =I4+INDEX('اسعار الاسهم'!A:B,MATCH(G4,'اسعار الاسهم'!K:K,0),2) -> 56.89 | K4: =J4/H4-1 -> 1.0095373
A5: comi | B5: 80.31 | C5: =INDEX('اسعار الاسهم'!A:B,MATCH(A5,'اسعار الاسهم'!K:K,0),2) -> 132.35 | D5: =1-C5/B5 -> -0.64798904 | F5: 4 | G5: efid | H5: =27.3/2 -> 13.65 | I5: =1.142/2 -> 0.571 | J5: =I5+INDEX('اسعار الاسهم'!A:B,MATCH(G5,'اسعار الاسهم'!K:K,0),2) -> 28.491 | K5: =J5/H5-1 -> 1.0872527
A6: mich | B6: 28.13 | C6: =INDEX('اسعار الاسهم'!A:B,MATCH(A6,'اسعار الاسهم'!K:K,0),2) -> 35.5 | D6: =1-C6/B6 -> -0.26199787 | F6: 3 | G6: engc | H6: 23.35 | I6: 1.25 | J6: =I6+INDEX('اسعار الاسهم'!A:B,MATCH(G6,'اسعار الاسهم'!K:K,0),2) -> 34.01 | K6: =J6/H6-1 -> 0.45653105
A7: afdi | B7: 28.82 | C7: =INDEX('اسعار الاسهم'!A:B,MATCH(A7,'اسعار الاسهم'!K:K,0),2) -> 41.67 | D7: =1-C7/B7 -> -0.44587092 | F7: 6 | G7: olfi | H7: 16.72 | I7: 1.75 | J7: =I7+INDEX('اسعار الاسهم'!A:B,MATCH(G7,'اسعار الاسهم'!K:K,0),2) -> 22.9 | K7: =J7/H7-1 -> 0.36961722
A8: arab | B8: 0.39 | C8: =INDEX('اسعار الاسهم'!A:B,MATCH(A8,'اسعار الاسهم'!K:K,0),2) -> 0.2 | D8: =1-C8/B8 -> 0.48717949 | F8: 7 | G8: orhd | H8: 22.94 | I8: 0.384346 | J8: =I8+INDEX('اسعار الاسهم'!A:B,MATCH(G8,'اسعار الاسهم'!K:K,0),2) -> 34.934346 | K8: =J8/H8-1 -> 0.52285728
A9: fwry | B9: 8.57 | C9: =INDEX('اسعار الاسهم'!A:B,MATCH(A9,'اسعار الاسهم'!K:K,0),2) -> 19.32 | D9: =1-C9/B9 -> -1.2543757 | F9: 8 | G9: VLMRA | H9: =29.18/1.05046 -> 27.778307 | I9: =0.035*50/1.05046+0.045*50 -> 3.9159368 | J9: =I9+INDEX('اسعار الاسهم'!A:B,MATCH(G9,'اسعار الاسهم'!K:K,0),2) -> 34.315937 | K9: =J9/H9-1 -> 0.23535021
A10: efih | B10: 18.02 | C10: =INDEX('اسعار الاسهم'!A:B,MATCH(A10,'اسعار الاسهم'!K:K,0),2) -> 21.76 | D10: =1-C10/B10 -> -0.20754717
A11: tmgh | B11: 54.74 | C11: =INDEX('اسعار الاسهم'!A:B,MATCH(A11,'اسعار الاسهم'!K:K,0),2) -> 99.48 | D11: =1-C11/B11 -> -0.81731823
A12: phgc | B12: 1.2 | C12: =INDEX('اسعار الاسهم'!A:B,MATCH(A12,'اسعار الاسهم'!K:K,0),2) -> 0.09 | D12: =1-C12/B12 -> 0.925
A13: GGRN | B13: 1.89 | C13: =INDEX('اسعار الاسهم'!A:B,MATCH(A13,'اسعار الاسهم'!K:K,0),2) -> 1.42 | D13: =1-C13/B13 -> 0.24867725
C14: =INDEX('اسعار الاسهم'!A:B,MATCH(A14,'اسعار الاسهم'!K:K,0),2) -> #N/A | D14: =1-C14/B14 -> #N/A
C15: =INDEX('اسعار الاسهم'!A:B,MATCH(A15,'اسعار الاسهم'!K:K,0),2) -> #N/A | D15: =1-C15/B15 -> #N/A
C16: =INDEX('اسعار الاسهم'!A:B,MATCH(A16,'اسعار الاسهم'!K:K,0),2) -> #N/A | D16: =1-C16/B16 -> #N/A
C17: =INDEX('اسعار الاسهم'!A:B,MATCH(A17,'اسعار الاسهم'!K:K,0),2) -> #N/A | D17: =1-C17/B17 -> #N/A

Sheet ra2eb 2
B1: curr | C1: next
A2: hrho | B2: 500 | C2: {=IF(B2<>"",INDEX(H:H,MATCH(B2,H:H)+1),"")} -> 900 | H2: 500
A3: atqa | B3: 500 | C3: {=IF(B3<>"",INDEX(H:H,MATCH(B3,H:H)+1),"")} -> 900 | H3: 900
A4: zmid | B4: 500 | C4: {=IF(B4<>"",INDEX(H:H,MATCH(B4,H:H)+1),"")} -> 900 | H4: 1600
A5: ismq | B5: 500 | C5: {=IF(B5<>"",INDEX(H:H,MATCH(B5,H:H)+1),"")} -> 900 | H5: 2800
A6: ocdi | B6: 500 | C6: {=IF(B6<>"",INDEX(H:H,MATCH(B6,H:H)+1),"")} -> 900 | E6: safety | H6: 4800
A7: amer | B7: 500 | C7: {=IF(B7<>"",INDEX(H:H,MATCH(B7,H:H)+1),"")} -> 900 | E7: =SUM(C2:C28)/4 -> 1575 | H7: 8000
A8: heli | B8: 500 | C8: {=IF(B8<>"",INDEX(H:H,MATCH(B8,H:H)+1),"")} -> 900 | H8: 12800
C9: {=IF(B9<>"",INDEX(H:H,MATCH(B9,H:H)+1),"")} | H9: 25600
C10: {=IF(B10<>"",INDEX(H:H,MATCH(B10,H:H)+1),"")} | H10: 25600
C11: {=IF(B11<>"",INDEX(H:H,MATCH(B11,H:H)+1),"")}
C12: {=IF(B12<>"",INDEX(H:H,MATCH(B12,H:H)+1),"")}
C13: {=IF(B13<>"",INDEX(H:H,MATCH(B13,H:H)+1),"")}
C14: {=IF(B14<>"",INDEX(H:H,MATCH(B14,H:H)+1),"")}
C15: {=IF(B15<>"",INDEX(H:H,MATCH(B15,H:H)+1),"")}
C16: {=IF(B16<>"",INDEX(H:H,MATCH(B16,H:H)+1),"")}
C17: {=IF(B17<>"",INDEX(H:H,MATCH(B17,H:H)+1),"")}
C18: {=IF(B18<>"",INDEX(H:H,MATCH(B18,H:H)+1),"")}

Sheet evaluate ostoul
A1: num | B1: sahm | C1: before end of | D1: buy | E1: target | F1: loss | G1: current | H1: result | I1: up | J1: down | K1: range | L1: ratio | M1: near | N1: count active | O1: done scenario | P1: done num | Q1: result
A2: 362 | B2: tmgh | C2: 45652 | D2: 56.75 | E2: 61.6 | F2: 55.5 | G2: =INDEX('اسعار الاسهم'!A:B,MATCH(B2,'اسعار الاسهم'!K:K,0),2) -> 99.48 | H2: =IF(O2="", G2/D2-1,"") -> 0.75295154 | I2: =IF(O2="", E2/G2-1,"") -> -0.38078006 | J2: =IF(O2="", 1-F2/G2,"") -> 0.44209891 | K2: =E2/F2-1 -> 0.10990991 | L2: =IF( P2="",I2/J2,"") -> -0.86130059 | M2: =IF(O2="",IF(I2<J2,"up","down"),"") -> up | N2: =COUNTIFS(B:B,B2,O:O,"") -> 5 | Q2: =IF(NOT( P2=""),IF(O2=1,E2/D2-1,F2/D2-1),"") | S2: =AVERAGE(Q:Q) -> 0.00065718838 | T2: =MAX(P:P) -> 204
A3: 363 | B3: snfc | C3: 45652 | D3: 5.58 | E3: 6.15 | F3: 5.25 | G3: =INDEX('اسعار الاسهم'!A:B,MATCH(B3,'اسعار الاسهم'!K:K,0),2) -> 12.29 | H3: =IF(O3="", G3/D3-1,"") -> 1.202509 | I3: =IF(O3="", E3/G3-1,"") -> -0.49959317 | J3: =IF(O3="", 1-F3/G3,"") -> 0.57282343 | K3: =E3/F3-1 -> 0.17142857 | L3: =IF( P3="",I3/J3,"") -> -0.87215909 | M3: =IF(O3="",IF(I3<J3,"up","down"),"") -> up | N3: =COUNTIFS(B:B,B3,O:O,"") -> 2 | Q3: =IF(NOT( P3=""),IF(O3=1,E3/D3-1,F3/D3-1),"")
A4: 364 | B4: clho | C4: 45652 | D4: 7.94 | E4: 9.35 | F4: 7.55 | G4: =INDEX('اسعار الاسهم'!A:B,MATCH(B4,'اسعار الاسهم'!K:K,0),2) -> 15.19 | H4: =IF(O4="", G4/D4-1,"") -> 0.91309824 | I4: =IF(O4="", E4/G4-1,"") -> -0.38446346 | J4: =IF(O4="", 1-F4/G4,"") -> 0.50296248 | K4: =E4/F4-1 -> 0.2384106 | L4: =IF( P4="",I4/J4,"") -> -0.76439791 | M4: =IF(O4="",IF(I4<J4,"up","down"),"") -> up | N4: =COUNTIFS(B:B,B4,O:O,"") -> 2 | Q4: =IF(NOT( P4=""),IF(O4=1,E4/D4-1,F4/D4-1),"")
A5: 365 | B5: phdc | C5: 45652 | D5: 6.26 | E5: 6.9 | F5: 5.9 | G5: =INDEX('اسعار الاسهم'!A:B,MATCH(B5,'اسعار الاسهم'!K:K,0),2) -> 13.61 | H5: =IF(O5="", G5/D5-1,"") -> 1.1741214 | I5: =IF(O5="", E5/G5-1,"") -> -0.49301984 | J5: =IF(O5="", 1-F5/G5,"") -> 0.56649522 | K5: =E5/F5-1 -> 0.16949153 | L5: =IF( P5="",I5/J5,"") -> -0.87029831 | M5: =IF(O5="",IF(I5<J5,"up","down"),"") -> up | N5: =COUNTIFS(B:B,B5,O:O,"") -> 4 | Q5: =IF(NOT( P5=""),IF(O5=1,E5/D5-1,F5/D5-1),"")
A6: 366 | B6: kabo | C6: 45652 | D6: 3.82 | E6: 4.15 | F6: 3.5 | G6: =INDEX('اسعار الاسهم'!A:B,MATCH(B6,'اسعار الاسهم'!K:K,0),2) -> 6.11 | H6: =IF(O6="", G6/D6-1,"") -> 0.59947644 | I6: =IF(O6="", E6/G6-1,"") -> -0.3207856 | J6: =IF(O6="", 1-F6/G6,"") -> 0.42716858 | K6: =E6/F6-1 -> 0.18571429 | L6: =IF( P6="",I6/J6,"") -> -0.75095785 | M6: =IF(O6="",IF(I6<J6,"up","down"),"") -> up | N6: =COUNTIFS(B:B,B6,O:O,"") -> 1 | Q6: =IF(NOT( P6=""),IF(O6=1,E6/D6-1,F6/D6-1),"")
A7: 263 | B7: raya | C7: 45638 | D7: 3.52 | E7: 4 | F7: 3.15 | G7: =INDEX('اسعار الاسهم'!A:B,MATCH(B7,'اسعار الاسهم'!K:K,0),2) -> 7.15 | H7: =IF(O7="", G7/D7-1,"") | I7: =IF(O7="", E7/G7-1,"") | J7: =IF(O7="", 1-F7/G7,"") | K7: =E7/F7-1 -> 0.26984127 | L7: =IF( P7="",I7/J7,"") | M7: =IF(O7="",IF(I7<J7,"up","down"),"") | N7: =COUNTIFS(B:B,B7,O:O,"") -> 3 | O7: 0 | P7: 202 | Q7: =IF(NOT( P7=""),IF(O7=1,E7/D7-1,F7/D7-1),"") -> -0.10511364
A8: 367 | B8: comi | C8: 45652 | D8: 81.6 | E8: 84 | F8: 80 | G8: =INDEX('اسعار الاسهم'!A:B,MATCH(B8,'اسعار الاسهم'!K:K,0),2) -> 132.35 | H8: =IF(O8="", G8/D8-1,"") -> 0.62193627 | I8: =IF(O8="", E8/G8-1,"") -> -0.36531923 | J8: =IF(O8="", 1-F8/G8,"") -> 0.39554212 | K8: =E8/F8-1 -> 0.05 | L8: =IF( P8="",I8/J8,"") -> -0.92359121 | M8: =IF(O8="",IF(I8<J8,"up","down"),"") -> up | N8: =COUNTIFS(B:B,B8,O:O,"") -> 5 | Q8: =IF(NOT( P8=""),IF(O8=1,E8/D8-1,F8/D8-1),"")
A9: 305 | B9: raya | C9: 45644 | D9: 3.43 | E9: 4.07 | F9: 3.12 | G9: =INDEX('اسعار الاسهم'!A:B,MATCH(B9,'اسعار الاسهم'!K:K,0),2) -> 7.15 | H9: =IF(O9="", G9/D9-1,"") | I9: =IF(O9="", E9/G9-1,"") | J9: =IF(O9="", 1-F9/G9,"") | K9: =E9/F9-1 -> 0.30448718 | L9: =IF( P9="",I9/J9,"") | M9: =IF(O9="",IF(I9<J9,"up","down"),"") | N9: =COUNTIFS(B:B,B9,O:O,"") -> 3 | O9: 0 | P9: 204 | Q9: =IF(NOT( P9=""),IF(O9=1,E9/D9-1,F9/D9-1),"") -> -0.090379009
A10: 368 | B10: oras | C10: 45652 | D10: 281.63 | E10: 300 | F10: 275 | G10: =INDEX('اسعار الاسهم'!A:B,MATCH(B10,'اسعار الاسهم'!K:K,0),2) -> 708.01 | H10: =IF(O10="", G10/D10-1,"") -> 1.5139722 | I10: =IF(O10="", E10/G10-1,"") -> -0.57627717 | J10: =IF(O10="", 1-F10/G10,"") -> 0.61158741 | K10: =E10/F10-1 -> 0.090909091 | L10: =IF( P10="",I10/J10,"") -> -0.94226461 | M10: =IF(O10="",IF(I10<J10,"up","down"),"") -> up | N10: =COUNTIFS(B:B,B10,O:O,"") -> 1 | Q10: =IF(NOT( P10=""),IF(O10=1,E10/D10-1,F10/D10-1),"")
A11: 369 | B11: olfi | C11: 45652 | D11: 17.62 | E11: 20.5 | F11: 16.8 | G11: =INDEX('اسعار الاسهم'!A:B,MATCH(B11,'اسعار الاسهم'!K:K,0),2) -> 21.15 | H11: =IF(O11="", G11/D11-1,"") -> 0.20034052 | I11: =IF(O11="", E11/G11-1,"") -> -0.030732861 | J11: =IF(O11="", 1-F11/G11,"") -> 0.20567376 | K11: =E11/F11-1 -> 0.2202381 | L11: =IF( P11="",I11/J11,"") -> -0.14942529 | M11: =IF(O11="",IF(I11<J11,"up","down"),"") -> up | N11: =COUNTIFS(B:B,B11,O:O,"") -> 2 | Q11: =IF(NOT( P11=""),IF(O11=1,E11/D11-1,F11/D11-1),"")
A12: 352 | B12: svce | C12: 45651 | D12: 3.31 | E12: 3.65 | F12: 3.1 | G12: =INDEX('اسعار الاسهم'!A:B,MATCH(B12,'اسعار الاسهم'!K:K,0),2) -> 9.3 | H12: =IF(O12="", G12/D12-1,"") -> 1.8096677 | I12: =IF(O12="", E12/G12-1,"") -> -0.60752688 | J12: =IF(O12="", 1-F12/G12,"") -> 0.66666667 | K12: =E12/F12-1 -> 0.17741935 | L12: =IF( P12="",I12/J12,"") -> -0.91129032 | M12: =IF(O12="",IF(I12<J12,"up","down"),"") -> up | N12: =COUNTIFS(B:B,B12,O:O,"") -> 3 | Q12: =IF(NOT( P12=""),IF(O12=1,E12/D12-1,F12/D12-1),"")
A13: 353 | B13: etrs | C13: 45651 | D13: 5.75 | E13: 6.65 | F13: 5.25 | G13: =INDEX('اسعار الاسهم'!A:B,MATCH(B13,'اسعار الاسهم'!K:K,0),2) -> 7.59 | H13: =IF(O13="", G13/D13-1,"") -> 0.32 | I13: =IF(O13="", E13/G13-1,"") -> -0.12384717 | J13: =IF(O13="", 1-F13/G13,"") -> 0.3083004 | K13: =E13/F13-1 -> 0.26666667 | L13: =IF( P13="",I13/J13,"") -> -0.4017094 | M13: =IF(O13="",IF(I13<J13,"up","down"),"") -> up | N13: =COUNTIFS(B:B,B13,O:O,"") -> 3 | Q13: =IF(NOT( P13=""),IF(O13=1,E13/D13-1,F13/D13-1),"")
A14: 354 | B14: masr | C14: 45651 | D14: 3.86 | E14: 4.2 | F14: 3.8 | G14: =INDEX('اسعار الاسهم'!A:B,MATCH(B14,'اسعار الاسهم'!K:K,0),2) -> 6.79 | H14: =IF(O14="", G14/D14-1,"") -> 0.75906736 | I14: =IF(O14="", E14/G14-1,"") -> -0.3814433 | J14: =IF(O14="", 1-F14/G14,"") -> 0.44035346 | K14: =E14/F14-1 -> 0.10526316 | L14: =IF( P14="",I14/J14,"") -> -0.86622074 | M14: =IF(O14="",IF(I14<J14,"up","down"),"") -> up | N14: =COUNTIFS(B:B,B14,O:O,"") -> 4 | Q14: =IF(NOT( P14=""),IF(O14=1,E14/D14-1,F14/D14-1),"")
A15: 355 | B15: svce | C15: 45651 | D15: 3.31 | E15: 3.6 | F15: 3.07 | G15: =INDEX('اسعار الاسهم'!A:B,MATCH(B15,'اسعار الاسهم'!K:K,0),2) -> 9.3 | H15: =IF(O15="", G15/D15-1,"") -> 1.8096677 | I15: =IF(O15="", E15/G15-1,"") -> -0.61290323 | J15: =IF(O15="", 1-F15/G15,"") -> 0.66989247 | K15: =E15/F15-1 -> 0.17263844 | L15: =IF( P15="",I15/J15,"") -> -0.91492777 | M15: =IF(O15="",IF(I15<J15,"up","down"),"") -> up | N15: =COUNTIFS(B:B,B15,O:O,"") -> 3 | Q15: =IF(NOT( P15=""),IF(O15=1,E15/D15-1,F15/D15-1),"")
A16: 356 | B16: etrs | C16: 45651 | D16: 5.75 | E16: 6.1 | F16: 5.3 | G16: =INDEX('اسعار الاسهم'!A:B,MATCH(B16,'اسعار الاسهم'!K:K,0),2) -> 7.59 | H16: =IF(O16="", G16/D16-1,"") -> 0.32 | I16: =IF(O16="", E16/G16-1,"") -> -0.19631094 | J16: =IF(O16="", 1-F16/G16,"") -> 0.30171278 | K16: =E16/F16-1 -> 0.1509434 | L16: =IF( P16="",I16/J16,"") -> -0.65065502 | M16: =IF(O16="",IF(I16<J16,"up","down"),"") -> up | N16: =COUNTIFS(B:B,B16,O:O,"") -> 3 | Q16: =IF(NOT( P16=""),IF(O16=1,E16/D16-1,F16/D16-1),"")
A17: 357 | B17: eppk | C17: 45651 | D17: 10 | E17: 11.5 | F17: 8.7 | G17: =INDEX('اسعار الاسهم'!A:B,MATCH(B17,'اسعار الاسهم'!K:K,0),2) -> 12.63 | H17: =IF(O17="", G17/D17-1,"") -> 0.263 | I17: =IF(O17="", E17/G17-1,"") -> -0.089469517 | J17: =IF(O17="", 1-F17/G17,"") -> 0.3111639 | K17: =E17/F17-1 -> 0.32183908 | L17: =IF( P17="",I17/J17,"") -> -0.28753181 | M17: =IF(O17="",IF(I17<J17,"up","down"),"") -> up | N17: =COUNTIFS(B:B,B17,O:O,"") -> 1 | Q17: =IF(NOT( P17=""),IF(O17=1,E17/D17-1,F17/D17-1),"")
A18: 358 | B18: masr | C18: 45651 | D18: 3.9 | E18: 4.18 | F18: 3.8 | G18: =INDEX('اسعار الاسهم'!A:B,MATCH(B18,'اسعار الاسهم'!K:K,0),2) -> 6.79 | H18: =IF(O18="", G18/D18-1,"") -> 0.74102564 | I18: =IF(O18="", E18/G18-1,"") -> -0.38438881 | J18: =IF(O18="", 1-F18/G18,"") -> 0.44035346 | K18: =E18/F18-1 -> 0.1 | L18: =IF( P18="",I18/J18,"") -> -0.8729097 | M18: =IF(O18="",IF(I18<J18,"up","down"),"") -> up | N18: =COUNTIFS(B:B,B18,O:O,"") -> 4 | Q18: =IF(NOT( P18=""),IF(O18=1,E18/D18-1,F18/D18-1),"")
A19: 359 | B19: rrei | C19: 45651 | D19: 1.7 | E19: 2.02 | F19: 1.59 | G19: =INDEX('اسعار الاسهم'!A:B,MATCH(B19,'اسعار الاسهم'!K:K,0),2) -> 3.38 | H19: =IF(O19="", G19/D19-1,"") -> 0.98823529 | I19: =IF(O19="", E19/G19-1,"") -> -0.40236686 | J19: =IF(O19="", 1-F19/G19,"") -> 0.5295858 | K19: =E19/F19-1 -> 0.27044025 | L19: =IF( P19="",I19/J19,"") -> -0.75977654 | M19: =IF(O19="",IF(I19<J19,"up","down"),"") -> up | N19: =COUNTIFS(B:B,B19,O:O,"") -> 2 | Q19: =IF(NOT( P19=""),IF(O19=1,E19/D19-1,F19/D19-1),"")
A20: 360 | B20: amia | C20: 45651 | D20: 2.55 | E20: 2.75 | F20: 2.42 | G20: =INDEX('اسعار الاسهم'!A:B,MATCH(B20,'اسعار الاسهم'!K:K,0),2) -> 8.7 | H20: =IF(O20="", G20/D20-1,"") -> 2.4117647 | I20: =IF(O20="", E20/G20-1,"") -> -0.68390805 | J20: =IF(O20="", 1-F20/G20,"") -> 0.72183908 | K20: =E20/F20-1 -> 0.13636364 | L20: =IF( P20="",I20/J20,"") -> -0.94745223 | M20: =IF(O20="",IF(I20<J20,"up","down"),"") -> up | N20: =COUNTIFS(B:B,B20,O:O,"") -> 1 | Q20: =IF(NOT( P20=""),IF(O20=1,E20/D20-1,F20/D20-1),"")
A21: 361 | B21: alcn | C21: 45651 | D21: 21.7 | E21: 24.5 | F21: 21.1 | G21: =INDEX('اسعار الاسهم'!A:B,MATCH(B21,'اسعار الاسهم'!K:K,0),2) -> 28.85 | H21: =IF(O21="", G21/D21-1,"") -> 0.32949309 | I21: =IF(O21="", E21/G21-1,"") -> -0.1507799 | J21: =IF(O21="", 1-F21/G21,"") -> 0.26863085 | K21: =E21/F21-1 -> 0.16113744 | L21: =IF( P21="",I21/J21,"") -> -0.56129032 | M21: =IF(O21="",IF(I21<J21,"up","down"),"") -> up | N21: =COUNTIFS(B:B,B21,O:O,"") -> 3 | Q21: =IF(NOT( P21=""),IF(O21=1,E21/D21-1,F21/D21-1),"")
... A56: 312 | B56: orwe | C56: 45645 | D56: 26.79 | E56: 31.25 | F56: 25.3 | G56: =INDEX('اسعار الاسهم'!A:B,MATCH(B56,'اسعار الاسهم'!K:K,0),2) -> 21.84 | H56: =IF(O56="", G56/D56-1,"") -> -0.18477044 | I56: =IF(O56="", E56/G56-1,"") -> 0.43086081 | J56: =IF(O56="", 1-F56/G56,"") -> -0.15842491 | K56: =E56/F56-1 -> 0.23517787 | L56: =IF( P56="",I56/J56,"") -> -2.7196532 | M56: =IF(O56="",IF(I56<J56,"up","down"),"") -> down | N56: =COUNTIFS(B:B,B56,O:O,"") -> 4 | Q56: =IF(NOT( P56=""),IF(O56=1,E56/D56-1,F56/D56-1),"")
A57: 314 | B57: efih | C57: 45645 | D57: 20.4 | E57: 23.8 | F57: 19.65 | G57: =INDEX('اسعار الاسهم'!A:B,MATCH(B57,'اسعار الاسهم'!K:K,0),2) -> 21.76 | H57: =IF(O57="", G57/D57-1,"") -> 0.066666667 | I57: =IF(O57="", E57/G57-1,"") -> 0.09375 | J57: =IF(O57="", 1-F57/G57,"") -> 0.096966912 | K57: =E57/F57-1 -> 0.21119593 | L57: =IF( P57="",I57/J57,"") | M57: =IF(O57="",IF(I57<J57,"up","down"),"") -> up | N57: =COUNTIFS(B:B,B57,O:O,"") -> 2 | P57: 203 | Q57: =IF(NOT( P57=""),IF(O57=1,E57/D57-1,F57/D57-1),"") -> -0.036764706
A58: 317 | B58: mfpc | C58: 45645 | D58: 39.65 | E58: 43.35 | F58: 39 | G58: =INDEX('اسعار الاسهم'!A:B,MATCH(B58,'اسعار الاسهم'!K:K,0),2) -> 43.48 | H58: =IF(O58="", G58/D58-1,"") -> 0.096595208 | I58: =IF(O58="", E58/G58-1,"") -> -0.0029898804 | J58: =IF(O58="", 1-F58/G58,"") -> 0.10303588 | K58: =E58/F58-1 -> 0.11153846 | L58: =IF( P58="",I58/J58,"") -> -0.029017857 | M58: =IF(O58="",IF(I58<J58,"up","down"),"") -> up | N58: =COUNTIFS(B:B,B58,O:O,"") -> 1 | Q58: =IF(NOT( P58=""),IF(O58=1,E58/D58-1,F58/D58-1),"")
A59: 317 | B59: eiud | C59: 45645 | D59: 0.253 | E59: 0.275 | F59: 0.24 | G59: =INDEX('اسعار الاسهم'!A:B,MATCH(B59,'اسعار الاسهم'!K:K,0),2) -> #N/A | H59: =IF(O59="", G59/D59-1,"") -> #N/A | I59: =IF(O59="", E59/G59-1,"") -> #N/A | J59: =IF(O59="", 1-F59/G59,"") -> #N/A | K59: =E59/F59-1 -> 0.14583333 | L59: =IF( P59="",I59/J59,"") -> #N/A | M59: =IF(O59="",IF(I59<J59,"up","down"),"") -> #N/A | N59: =COUNTIFS(B:B,B59,O:O,"") -> 3 | Q59: =IF(NOT( P59=""),IF(O59=1,E59/D59-1,F59/D59-1),"")
A60: 303 | B60: tmgh | C60: 45644 | D60: 57.5 | E60: 63.5 | F60: 51.2 | G60: =INDEX('اسعار الاسهم'!A:B,MATCH(B60,'اسعار الاسهم'!K:K,0),2) -> 99.48 | H60: =IF(O60="", G60/D60-1,"") -> 0.73008696 | I60: =IF(O60="", E60/G60-1,"") -> -0.36168074 | J60: =IF(O60="", 1-F60/G60,"") -> 0.48532368 | K60: =E60/F60-1 -> 0.24023438 | L60: =IF( P60="",I60/J60,"") -> -0.74523612 | M60: =IF(O60="",IF(I60<J60,"up","down"),"") -> up | N60: =COUNTIFS(B:B,B60,O:O,"") -> 5 | Q60: =IF(NOT( P60=""),IF(O60=1,E60/D60-1,F60/D60-1),"")
A61: 304 | B61: gbco | C61: 45644 | D61: 17.49 | E61: 24 | F61: 15.55 | G61: =INDEX('اسعار الاسهم'!A:B,MATCH(B61,'اسعار الاسهم'!K:K,0),2) -> 25.67 | H61: =IF(O61="", G61/D61-1,"") -> 0.46769583 | I61: =IF(O61="", E61/G61-1,"") -> -0.065056486 | J61: =IF(O61="", 1-F61/G61,"") -> 0.39423451 | K61: =E61/F61-1 -> 0.54340836 | L61: =IF( P61="",I61/J61,"") -> -0.16501976 | M61: =IF(O61="",IF(I61<J61,"up","down"),"") -> up | N61: =COUNTIFS(B:B,B61,O:O,"") -> 3 | Q61: =IF(NOT( P61=""),IF(O61=1,E61/D61-1,F61/D61-1),"")
A62: 306 | B62: oih | C62: 45644 | D62: 0.586 | E62: 0.747 | F62: 0.55 | G62: =INDEX('اسعار الاسهم'!A:B,MATCH(B62,'اسعار الاسهم'!K:K,0),2) -> 1.46 | H62: =IF(O62="", G62/D62-1,"") -> 1.4914676 | I62: =IF(O62="", E62/G62-1,"") -> -0.48835616 | J62: =IF(O62="", 1-F62/G62,"") -> 0.62328767 | K62: =E62/F62-1 -> 0.35818182 | L62: =IF( P62="",I62/J62,"") -> -0.78351648 | M62: =IF(O62="",IF(I62<J62,"up","down"),"") -> up | N62: =COUNTIFS(B:B,B62,O:O,"") -> 2 | Q62: =IF(NOT( P62=""),IF(O62=1,E62/D62-1,F62/D62-1),"")
A63: 307 | B63: orwe | C63: 45644 | D63: 26.48 | E63: 28.85 | F63: 25.3 | G63: =INDEX('اسعار الاسهم'!A:B,MATCH(B63,'اسعار الاسهم'!K:K,0),2) -> 21.84 | H63: =IF(O63="", G63/D63-1,"") -> -0.17522659 | I63: =IF(O63="", E63/G63-1,"") -> 0.3209707 | J63: =IF(O63="", 1-F63/G63,"") -> -0.15842491 | K63: =E63/F63-1 -> 0.14031621 | L63: =IF( P63="",I63/J63,"") -> -2.0260116 | M63: =IF(O63="",IF(I63<J63,"up","down"),"") -> down | N63: =COUNTIFS(B:B,B63,O:O,"") -> 4 | Q63: =IF(NOT( P63=""),IF(O63=1,E63/D63-1,F63/D63-1),"")
A64: 308 | B64: odin | C64: 45644 | D64: 1.98 | E64: 2.2 | F64: 1.8 | G64: =INDEX('اسعار الاسهم'!A:B,MATCH(B64,'اسعار الاسهم'!K:K,0),2) -> 1.92 | H64: =IF(O64="", G64/D64-1,"") -> -0.03030303 | I64: =IF(O64="", E64/G64-1,"") -> 0.14583333 | J64: =IF(O64="", 1-F64/G64,"") -> 0.0625 | K64: =E64/F64-1 -> 0.22222222 | L64: =IF( P64="",I64/J64,"") -> 2.3333333 | M64: =IF(O64="",IF(I64<J64,"up","down"),"") -> down | N64: =COUNTIFS(B:B,B64,O:O,"") -> 1 | Q64: =IF(NOT( P64=""),IF(O64=1,E64/D64-1,F64/D64-1),"")
A65: 309 | B65: orwe | C65: 45644 | D65: 26.48 | E65: 28 | F65: 25.3 | G65: =INDEX('اسعار الاسهم'!A:B,MATCH(B65,'اسعار الاسهم'!K:K,0),2) -> 21.84 | H65: =IF(O65="", G65/D65-1,"") -> -0.17522659 | I65: =IF(O65="", E65/G65-1,"") -> 0.28205128 | J65: =IF(O65="", 1-F65/G65,"") -> -0.15842491 | K65: =E65/F65-1 -> 0.10671937 | L65: =IF( P65="",I65/J65,"") -> -1.7803468 | M65: =IF(O65="",IF(I65<J65,"up","down"),"") -> down | N65: =COUNTIFS(B:B,B65,O:O,"") -> 4 | Q65: =IF(NOT( P65=""),IF(O65=1,E65/D65-1,F65/D65-1),"")
A66: 310 | B66: mepa | C66: 45644 | D66: 1.41 | E66: 1.7 | F66: 1.28 | G66: =INDEX('اسعار الاسهم'!A:B,MATCH(B66,'اسعار الاسهم'!K:K,0),2) -> 1.66 | H66: =IF(O66="", G66/D66-1,"") -> 0.17730496 | I66: =IF(O66="", E66/G66-1,"") -> 0.024096386 | J66: =IF(O66="", 1-F66/G66,"") -> 0.22891566 | K66: =E66/F66-1 -> 0.328125 | L66: =IF( P66="",I66/J66,"") -> 0.10526316 | M66: =IF(O66="",IF(I66<J66,"up","down"),"") -> up | N66: =COUNTIFS(B:B,B66,O:O,"") -> 1 | Q66: =IF(NOT( P66=""),IF(O66=1,E66/D66-1,F66/D66-1),"")
A67: 293 | B67: afdi | C67: 45643 | D67: 34.14 | E67: 36.8 | F67: 30 | G67: =INDEX('اسعار الاسهم'!A:B,MATCH(B67,'اسعار الاسهم'!K:K,0),2) -> 41.67 | H67: =IF(O67="", G67/D67-1,"") -> 0.22056239 | I67: =IF(O67="", E67/G67-1,"") -> -0.11687065 | J67: =IF(O67="", 1-F67/G67,"") -> 0.2800576 | K67: =E67/F67-1 -> 0.22666667 | L67: =IF( P67="",I67/J67,"") -> -0.41730934 | M67: =IF(O67="",IF(I67<J67,"up","down"),"") -> up | N67: =COUNTIFS(B:B,B67,O:O,"") -> 2 | Q67: =IF(NOT( P67=""),IF(O67=1,E67/D67-1,F67/D67-1),"")
A68: 294 | B68: emfd | C68: 45643 | D68: 8.03 | E68: 8.75 | F68: 7.5 | G68: =INDEX('اسعار الاسهم'!A:B,MATCH(B68,'اسعار الاسهم'!K:K,0),2) -> 10.11 | H68: =IF(O68="", G68/D68-1,"") -> 0.25902864 | I68: =IF(O68="", E68/G68-1,"") -> -0.13452028 | J68: =IF(O68="", 1-F68/G68,"") -> 0.25816024 | K68: =E68/F68-1 -> 0.16666667 | L68: =IF( P68="",I68/J68,"") -> -0.5210728 | M68: =IF(O68="",IF(I68<J68,"up","down"),"") -> up | N68: =COUNTIFS(B:B,B68,O:O,"") -> 3 | Q68: =IF(NOT( P68=""),IF(O68=1,E68/D68-1,F68/D68-1),"")
A69: 295 | B69: gbco | C69: 45643 | D69: 15.89 | E69: 18 | F69: 14.8 | G69: =INDEX('اسعار الاسهم'!A:B,MATCH(B69,'اسعار الاسهم'!K:K,0),2) -> 25.67 | H69: =IF(O69="", G69/D69-1,"") -> 0.61548143 | I69: =IF(O69="", E69/G69-1,"") -> -0.29879236 | J69: =IF(O69="", 1-F69/G69,"") -> 0.4234515 | K69: =E69/F69-1 -> 0.21621622 | L69: =IF( P69="",I69/J69,"") -> -0.70561178 | M69: =IF(O69="",IF(I69<J69,"up","down"),"") -> up | N69: =COUNTIFS(B:B,B69,O:O,"") -> 3 | Q69: =IF(NOT( P69=""),IF(O69=1,E69/D69-1,F69/D69-1),"")
... A117: 207 | B117: ismq | C117: 45630 | D117: 4.45 | E117: 5 | F117: 4.1 | G117: =INDEX('اسعار الاسهم'!A:B,MATCH(B117,'اسعار الاسهم'!K:K,0),2) -> 7.33 | H117: =IF(O117="", G117/D117-1,"") -> 0.64719101 | I117: =IF(O117="", E117/G117-1,"") -> -0.31787176 | J117: =IF(O117="", 1-F117/G117,"") -> 0.44065484 | K117: =E117/F117-1 -> 0.2195122 | L117: =IF( P117="",I117/J117,"") -> -0.72136223 | M117: =IF(O117="",IF(I117<J117,"up","down"),"") -> up | N117: =COUNTIFS(B:B,B117,O:O,"") -> 1 | Q117: =IF(NOT( P117=""),IF(O117=1,E117/D117-1,F117/D117-1),"")
A118: 210 | B118: zmid | C118: 45630 | D118: =7.26*9/17 -> 3.8435294 | E118: =8.9*9/17 -> 4.7117647 | F118: =6.9*9/17 -> 3.6529412 | G118: =INDEX('اسعار الاسهم'!A:B,MATCH(B118,'اسعار الاسهم'!K:K,0),2) -> 5.86 | H118: =IF(O118="", G118/D118-1,"") -> 0.52464034 | I118: =IF(O118="", E118/G118-1,"") -> -0.19594459 | J118: =IF(O118="", 1-F118/G118,"") -> 0.3766312 | K118: =E118/F118-1 -> 0.28985507 | L118: =IF( P118="",I118/J118,"") -> -0.52025586 | M118: =IF(O118="",IF(I118<J118,"up","down"),"") -> up | N118: =COUNTIFS(B:B,B118,O:O,"") -> 3 | Q118: =IF(NOT( P118=""),IF(O118=1,E118/D118-1,F118/D118-1),"")
A119: 211 | B119: binv | C119: 45630 | D119: 25.3 | E119: 28 | F119: 24.15 | G119: =INDEX('اسعار الاسهم'!A:B,MATCH(B119,'اسعار الاسهم'!K:K,0),2) -> 41.43 | H119: =IF(O119="", G119/D119-1,"") -> 0.63754941 | I119: =IF(O119="", E119/G119-1,"") -> -0.32416124 | J119: =IF(O119="", 1-F119/G119,"") -> 0.41708907 | K119: =E119/F119-1 -> 0.15942029 | L119: =IF( P119="",I119/J119,"") -> -0.77719907 | M119: =IF(O119="",IF(I119<J119,"up","down"),"") -> up | N119: =COUNTIFS(B:B,B119,O:O,"") -> 3 | Q119: =IF(NOT( P119=""),IF(O119=1,E119/D119-1,F119/D119-1),"")
A120: 197 | B120: masr | C120: 45629 | D120: 4.08 | E120: 4.6 | F120: 3.9 | G120: =INDEX('اسعار الاسهم'!A:B,MATCH(B120,'اسعار الاسهم'!K:K,0),2) -> 6.79 | H120: =IF(O120="", G120/D120-1,"") -> 0.66421569 | I120: =IF(O120="", E120/G120-1,"") -> -0.32253314 | J120: =IF(O120="", 1-F120/G120,"") -> 0.42562592 | K120: =E120/F120-1 -> 0.17948718 | L120: =IF( P120="",I120/J120,"") -> -0.75778547 | M120: =IF(O120="",IF(I120<J120,"up","down"),"") -> up | N120: =COUNTIFS(B:B,B120,O:O,"") -> 4 | Q120: =IF(NOT( P120=""),IF(O120=1,E120/D120-1,F120/D120-1),"")
A121: 198 | B121: acgc | C121: 45629 | D121: 8.32 | E121: 9 | F121: 7.9 | G121: =INDEX('اسعار الاسهم'!A:B,MATCH(B121,'اسعار الاسهم'!K:K,0),2) -> 10.1 | H121: =IF(O121="", G121/D121-1,"") -> 0.21394231 | I121: =IF(O121="", E121/G121-1,"") -> -0.10891089 | J121: =IF(O121="", 1-F121/G121,"") -> 0.21782178 | K121: =E121/F121-1 -> 0.13924051 | L121: =IF( P121="",I121/J121,"") -> -0.5 | M121: =IF(O121="",IF(I121<J121,"up","down"),"") -> up | N121: =COUNTIFS(B:B,B121,O:O,"") -> 4 | Q121: =IF(NOT( P121=""),IF(O121=1,E121/D121-1,F121/D121-1),"")
A122: 199 | B122: acgc | C122: 45629 | D122: 8.32 | E122: 9.25 | F122: 7.65 | G122: =INDEX('اسعار الاسهم'!A:B,MATCH(B122,'اسعار الاسهم'!K:K,0),2) -> 10.1 | H122: =IF(O122="", G122/D122-1,"") -> 0.21394231 | I122: =IF(O122="", E122/G122-1,"") -> -0.084158416 | J122: =IF(O122="", 1-F122/G122,"") -> 0.24257426 | K122: =E122/F122-1 -> 0.20915033 | L122: =IF( P122="",I122/J122,"") -> -0.34693878 | M122: =IF(O122="",IF(I122<J122,"up","down"),"") -> up | N122: =COUNTIFS(B:B,B122,O:O,"") -> 4 | Q122: =IF(NOT( P122=""),IF(O122=1,E122/D122-1,F122/D122-1),"")
A123: 201 | B123: eeii | C123: 45629 | D123: 1.47 | E123: 1.6 | F123: 1.38 | G123: =INDEX('اسعار الاسهم'!A:B,MATCH(B123,'اسعار الاسهم'!K:K,0),2) -> 2.33 | H123: =IF(O123="", G123/D123-1,"") -> 0.58503401 | I123: =IF(O123="", E123/G123-1,"") -> -0.31330472 | J123: =IF(O123="", 1-F123/G123,"") -> 0.40772532 | K123: =E123/F123-1 -> 0.15942029 | L123: =IF( P123="",I123/J123,"") -> -0.76842105 | M123: =IF(O123="",IF(I123<J123,"up","down"),"") -> up | N123: =COUNTIFS(B:B,B123,O:O,"") -> 4 | Q123: =IF(NOT( P123=""),IF(O123=1,E123/D123-1,F123/D123-1),"")
A124: 184 | B124: phdc | C124: 45628 | D124: 5.91 | E124: 6.9 | F124: 5.6 | G124: =INDEX('اسعار الاسهم'!A:B,MATCH(B124,'اسعار الاسهم'!K:K,0),2) -> 13.61 | H124: =IF(O124="", G124/D124-1,"") -> 1.3028765 | I124: =IF(O124="", E124/G124-1,"") -> -0.49301984 | J124: =IF(O124="", 1-F124/G124,"") -> 0.58853784 | K124: =E124/F124-1 -> 0.23214286 | L124: =IF( P124="",I124/J124,"") -> -0.83770287 | M124: =IF(O124="",IF(I124<J124,"up","down"),"") -> up | N124: =COUNTIFS(B:B,B124,O:O,"") -> 4 | Q124: =IF(NOT( P124=""),IF(O124=1,E124/D124-1,F124/D124-1),"")
A125: 76 | B125: prcl | C125: 45610 | D125: 11.39 | E125: 12.8 | F125: 10.4 | G125: =INDEX('اسعار الاسهم'!A:B,MATCH(B125,'اسعار الاسهم'!K:K,0),2) -> 22.1 | H125: =IF(O125="", G125/D125-1,"") | I125: =IF(O125="", E125/G125-1,"") | J125: =IF(O125="", 1-F125/G125,"") | K125: =E125/F125-1 -> 0.23076923 | L125: =IF( P125="",I125/J125,"") | M125: =IF(O125="",IF(I125<J125,"up","down"),"") | N125: =COUNTIFS(B:B,B125,O:O,"") -> 1 | O125: 0 | P125: 199 | Q125: =IF(NOT( P125=""),IF(O125=1,E125/D125-1,F125/D125-1),"") -> -0.086918349
A126: 119 | B126: efid | C126: 45616 | D126: 29.77 | E126: 34 | F126: 27.5 | G126: =INDEX('اسعار الاسهم'!A:B,MATCH(B126,'اسعار الاسهم'!K:K,0),2) -> 27.92 | H126: =IF(O126="", G126/D126-1,"") | I126: =IF(O126="", E126/G126-1,"") | J126: =IF(O126="", 1-F126/G126,"") | K126: =E126/F126-1 -> 0.23636364 | L126: =IF( P126="",I126/J126,"") | M126: =IF(O126="",IF(I126<J126,"up","down"),"") | N126: =COUNTIFS(B:B,B126,O:O,"") -> 0 | O126: 0 | P126: 198 | Q126: =IF(NOT( P126=""),IF(O126=1,E126/D126-1,F126/D126-1),"") -> -0.07625126
A127: 233 | B127: btfh | C127: 45634 | D127: 2.94 | E127: 3.45 | F127: 2.8 | G127: =INDEX('اسعار الاسهم'!A:B,MATCH(B127,'اسعار الاسهم'!K:K,0),2) -> 3.08 | H127: =IF(O127="", G127/D127-1,"") | I127: =IF(O127="", E127/G127-1,"") | J127: =IF(O127="", 1-F127/G127,"") | K127: =E127/F127-1 -> 0.23214286 | L127: =IF( P127="",I127/J127,"") | M127: =IF(O127="",IF(I127<J127,"up","down"),"") | N127: =COUNTIFS(B:B,B127,O:O,"") -> 0 | O127: 0 | P127: 182 | Q127: =IF(NOT( P127=""),IF(O127=1,E127/D127-1,F127/D127-1),"") -> -0.047619048
A128: 282 | B128: clho | C128: 45642 | D128: 8.25 | E128: 8.85 | F128: 7.92 | G128: =INDEX('اسعار الاسهم'!A:B,MATCH(B128,'اسعار الاسهم'!K:K,0),2) -> 15.19 | H128: =IF(O128="", G128/D128-1,"") | I128: =IF(O128="", E128/G128-1,"") | J128: =IF(O128="", 1-F128/G128,"") | K128: =E128/F128-1 -> 0.11742424 | L128: =IF( P128="",I128/J128,"") | M128: =IF(O128="",IF(I128<J128,"up","down"),"") | N128: =COUNTIFS(B:B,B128,O:O,"") -> 2 | O128: 0 | P128: 180 | Q128: =IF(NOT( P128=""),IF(O128=1,E128/D128-1,F128/D128-1),"") -> -0.04
A129: 33 | B129: cieb | C129: 45603 | D129: 21.35 | E129: 24.5 | F129: 20.2 | G129: =INDEX('اسعار الاسهم'!A:B,MATCH(B129,'اسعار الاسهم'!K:K,0),2) -> 23.41 | H129: =IF(O129="", G129/D129-1,"") | I129: =IF(O129="", E129/G129-1,"") | J129: =IF(O129="", 1-F129/G129,"") | K129: =E129/F129-1 -> 0.21287129 | L129: =IF( P129="",I129/J129,"") | M129: =IF(O129="",IF(I129<J129,"up","down"),"") | N129: =COUNTIFS(B:B,B129,O:O,"") -> 0 | O129: 0 | P129: 179 | Q129: =IF(NOT( P129=""),IF(O129=1,E129/D129-1,F129/D129-1),"") -> -0.053864169
A130: 177 | B130: ggcc | C130: 45627 | D130: 0.465 | E130: 0.54 | F130: 0.435 | G130: =INDEX('اسعار الاسهم'!A:B,MATCH(B130,'اسعار الاسهم'!K:K,0),2) -> 0.39 | H130: =IF(O130="", G130/D130-1,"") | I130: =IF(O130="", E130/G130-1,"") | J130: =IF(O130="", 1-F130/G130,"") | K130: =E130/F130-1 -> 0.24137931 | L130: =IF( P130="",I130/J130,"") | M130: =IF(O130="",IF(I130<J130,"up","down"),"") | N130: =COUNTIFS(B:B,B130,O:O,"") -> 1 | O130: 0 | P130: 178 | Q130: =IF(NOT( P130=""),IF(O130=1,E130/D130-1,F130/D130-1),"") -> -0.064516129
A131: 302 | B131: ascm | C131: 45643 | D131: 37.3 | E131: 42.5 | F131: 36.35 | G131: =INDEX('اسعار الاسهم'!A:B,MATCH(B131,'اسعار الاسهم'!K:K,0),2) -> 47.7 | H131: =IF(O131="", G131/D131-1,"") | I131: =IF(O131="", E131/G131-1,"") | J131: =IF(O131="", 1-F131/G131,"") | K131: =E131/F131-1 -> 0.16918845 | L131: =IF( P131="",I131/J131,"") | M131: =IF(O131="",IF(I131<J131,"up","down"),"") | N131: =COUNTIFS(B:B,B131,O:O,"") -> 0 | O131: 0 | P131: 177 | Q131: =IF(NOT( P131=""),IF(O131=1,E131/D131-1,F131/D131-1),"") -> -0.025469169
A132: 267 | B132: ocdi | C132: 45638 | D132: 65.36 | E132: 70 | F132: 63 | G132: =INDEX('اسعار الاسهم'!A:B,MATCH(B132,'اسعار الاسهم'!K:K,0),2) -> 20.7 | H132: =IF(O132="", G132/D132-1,"") | I132: =IF(O132="", E132/G132-1,"") | J132: =IF(O132="", 1-F132/G132,"") | K132: =E132/F132-1 -> 0.11111111 | L132: =IF( P132="",I132/J132,"") | M132: =IF(O132="",IF(I132<J132,"up","down"),"") | N132: =COUNTIFS(B:B,B132,O:O,"") -> 0 | O132: 0 | P132: 176 | Q132: =IF(NOT( P132=""),IF(O132=1,E132/D132-1,F132/D132-1),"") -> -0.036107711
A133: 292 | B133: copr | C133: 45642 | D133: 0.405 | E133: 0.48 | F133: 0.39 | G133: =INDEX('اسعار الاسهم'!A:B,MATCH(B133,'اسعار الاسهم'!K:K,0),2) -> 0.36 | H133: =IF(O133="", G133/D133-1,"") | I133: =IF(O133="", E133/G133-1,"") | J133: =IF(O133="", 1-F133/G133,"") | K133: =E133/F133-1 -> 0.23076923 | L133: =IF( P133="",I133/J133,"") | M133: =IF(O133="",IF(I133<J133,"up","down"),"") | N133: =COUNTIFS(B:B,B133,O:O,"") -> 0 | O133: 0 | P133: 197 | Q133: =IF(NOT( P133=""),IF(O133=1,E133/D133-1,F133/D133-1),"") -> -0.037037037
A134: 216 | B134: olfi | C134: 45631 | D134: 18.9 | E134: 21.8 | F134: 17.8 | G134: =INDEX('اسعار الاسهم'!A:B,MATCH(B134,'اسعار الاسهم'!K:K,0),2) -> 21.15 | H134: =IF(O134="", G134/D134-1,"") | I134: =IF(O134="", E134/G134-1,"") | J134: =IF(O134="", 1-F134/G134,"") | K134: =E134/F134-1 -> 0.2247191 | L134: =IF( P134="",I134/J134,"") | M134: =IF(O134="",IF(I134<J134,"up","down"),"") | N134: =COUNTIFS(B:B,B134,O:O,"") -> 2 | O134: 0 | P134: 175 | Q134: =IF(NOT( P134=""),IF(O134=1,E134/D134-1,F134/D134-1),"") -> -0.058201058
A135: 146 | B135: mprc | C135: 45621 | D135: 24.82 | E135: 27 | F135: 23.8 | G135: =INDEX('اسعار الاسهم'!A:B,MATCH(B135,'اسعار الاسهم'!K:K,0),2) -> 31.55 | H135: =IF(O135="", G135/D135-1,"") | I135: =IF(O135="", E135/G135-1,"") | J135: =IF(O135="", 1-F135/G135,"") | K135: =E135/F135-1 -> 0.13445378 | L135: =IF( P135="",I135/J135,"") | M135: =IF(O135="",IF(I135<J135,"up","down"),"") | N135: =COUNTIFS(B:B,B135,O:O,"") -> 2 | O135: 0 | P135: 174 | Q135: =IF(NOT( P135=""),IF(O135=1,E135/D135-1,F135/D135-1),"") -> -0.04109589
A136: 264 | B136: mprc | C136: 45638 | D136: 24.95 | E136: 26.65 | F136: 23.85 | G136: =INDEX('اسعار الاسهم'!A:B,MATCH(B136,'اسعار الاسهم'!K:K,0),2) -> 31.55 | H136: =IF(O136="", G136/D136-1,"") | I136: =IF(O136="", E136/G136-1,"") | J136: =IF(O136="", 1-F136/G136,"") | K136: =E136/F136-1 -> 0.11740042 | L136: =IF( P136="",I136/J136,"") | M136: =IF(O136="",IF(I136<J136,"up","down"),"") | N136: =COUNTIFS(B:B,B136,O:O,"") -> 2 | O136: 0 | P136: 173 | Q136: =IF(NOT( P136=""),IF(O136=1,E136/D136-1,F136/D136-1),"") -> -0.044088176
... A225: 172 | B225: cira | C225: 45624 | D225: 14.2 | E225: 14.9 | F225: 13.9 | G225: =INDEX('اسعار الاسهم'!A:B,MATCH(B225,'اسعار الاسهم'!K:K,0),2) -> 27.63 | H225: =IF(O225="", G225/D225-1,"") | I225: =IF(O225="", E225/G225-1,"") | J225: =IF(O225="", 1-F225/G225,"") | K225: =E225/F225-1 -> 0.071942446 | L225: =IF( P225="",I225/J225,"") | M225: =IF(O225="",IF(I225<J225,"up","down"),"") | N225: =COUNTIFS(B:B,B225,O:O,"") -> 0 | O225: 0 | P225: 110 | Q225: =IF(NOT( P225=""),IF(O225=1,E225/D225-1,F225/D225-1),"") -> -0.021126761
A226: 29 | B226: orwe | C226: 45603 | D226: 29.89 | E226: 34 | F226: 28.7 | G226: =INDEX('اسعار الاسهم'!A:B,MATCH(B226,'اسعار الاسهم'!K:K,0),2) -> 21.84 | H226: =IF(O226="", G226/D226-1,"") | I226: =IF(O226="", E226/G226-1,"") | J226: =IF(O226="", 1-F226/G226,"") | K226: =E226/F226-1 -> 0.18466899 | L226: =IF( P226="",I226/J226,"") | M226: =IF(O226="",IF(I226<J226,"up","down"),"") | N226: =COUNTIFS(B:B,B226,O:O,"") -> 4 | O226: 0 | P226: =P225+1 -> 111 | Q226: =IF(NOT( P226=""),IF(O226=1,E226/D226-1,F226/D226-1),"") -> -0.039812646
A227: 98 | B227: engc | C227: 45614 | D227: 22.94 | E227: 26 | F227: 21.5 | G227: =INDEX('اسعار الاسهم'!A:B,MATCH(B227,'اسعار الاسهم'!K:K,0),2) -> 32.76 | H227: =IF(O227="", G227/D227-1,"") | I227: =IF(O227="", E227/G227-1,"") | J227: =IF(O227="", 1-F227/G227,"") | K227: =E227/F227-1 -> 0.20930233 | L227: =IF( P227="",I227/J227,"") | M227: =IF(O227="",IF(I227<J227,"up","down"),"") | N227: =COUNTIFS(B:B,B227,O:O,"") -> 2 | O227: 1 | P227: 59 | Q227: =IF(NOT( P227=""),IF(O227=1,E227/D227-1,F227/D227-1),"") -> 0.13339146
A228: 97 | B228: adpc | C228: 45614 | D228: 2.91 | E228: 3.6 | F228: 2.7 | G228: =INDEX('اسعار الاسهم'!A:B,MATCH(B228,'اسعار الاسهم'!K:K,0),2) -> 3.95 | H228: =IF(O228="", G228/D228-1,"") | I228: =IF(O228="", E228/G228-1,"") | J228: =IF(O228="", 1-F228/G228,"") | K228: =E228/F228-1 -> 0.33333333 | L228: =IF( P228="",I228/J228,"") | M228: =IF(O228="",IF(I228<J228,"up","down"),"") | N228: =COUNTIFS(B:B,B228,O:O,"") -> 2 | O228: 1 | P228: 79 | Q228: =IF(NOT( P228=""),IF(O228=1,E228/D228-1,F228/D228-1),"") -> 0.2371134
A229: 185 | B229: rmda | C229: 45628 | D229: 3.58 | E229: 4.05 | F229: 3.26 | G229: =INDEX('اسعار الاسهم'!A:B,MATCH(B229,'اسعار الاسهم'!K:K,0),2) -> 5.06 | H229: =IF(O229="", G229/D229-1,"") -> 0.41340782 | I229: =IF(O229="", E229/G229-1,"") -> -0.19960474 | J229: =IF(O229="", 1-F229/G229,"") -> 0.35573123 | K229: =E229/F229-1 -> 0.24233129 | L229: =IF( P229="",I229/J229,"") -> -0.56111111 | M229: =IF(O229="",IF(I229<J229,"up","down"),"") -> up | N229: =COUNTIFS(B:B,B229,O:O,"") -> 4 | Q229: =IF(NOT( P229=""),IF(O229=1,E229/D229-1,F229/D229-1),"")
A230: 186 | B230: raya | C230: 45628 | D230: 3.17 | E230: 3.7 | F230: 2.9 | G230: =INDEX('اسعار الاسهم'!A:B,MATCH(B230,'اسعار الاسهم'!K:K,0),2) -> 7.15 | H230: =IF(O230="", G230/D230-1,"") -> 1.2555205 | I230: =IF(O230="", E230/G230-1,"") -> -0.48251748 | J230: =IF(O230="", 1-F230/G230,"") -> 0.59440559 | K230: =E230/F230-1 -> 0.27586207 | L230: =IF( P230="",I230/J230,"") -> -0.81176471 | M230: =IF(O230="",IF(I230<J230,"up","down"),"") -> up | N230: =COUNTIFS(B:B,B230,O:O,"") -> 3 | Q230: =IF(NOT( P230=""),IF(O230=1,E230/D230-1,F230/D230-1),"")
A231: 140 | B231: cieb | C231: 45620 | D231: 22 | E231: 25.3 | F231: 21 | G231: =INDEX('اسعار الاسهم'!A:B,MATCH(B231,'اسعار الاسهم'!K:K,0),2) -> 23.41 | H231: =IF(O231="", G231/D231-1,"") | I231: =IF(O231="", E231/G231-1,"") | J231: =IF(O231="", 1-F231/G231,"") | K231: =E231/F231-1 -> 0.2047619 | L231: =IF( P231="",I231/J231,"") | M231: =IF(O231="",IF(I231<J231,"up","down"),"") | N231: =COUNTIFS(B:B,B231,O:O,"") -> 0 | O231: 0 | P231: 96 | Q231: =IF(NOT( P231=""),IF(O231=1,E231/D231-1,F231/D231-1),"") -> -0.045454545
A232: 66 | B232: saud | C232: 45609 | D232: 13.94 | E232: 15.4 | F232: 13.1 | G232: =INDEX('اسعار الاسهم'!A:B,MATCH(B232,'اسعار الاسهم'!K:K,0),2) -> 22.19 | H232: =IF(O232="", G232/D232-1,"") | I232: =IF(O232="", E232/G232-1,"") | J232: =IF(O232="", 1-F232/G232,"") | K232: =E232/F232-1 -> 0.17557252 | L232: =IF( P232="",I232/J232,"") | M232: =IF(O232="",IF(I232<J232,"up","down"),"") | N232: =COUNTIFS(B:B,B232,O:O,"") -> 0 | O232: 0 | P232: 95 | Q232: =IF(NOT( P232=""),IF(O232=1,E232/D232-1,F232/D232-1),"") -> -0.06025825
A233: 36 | B233: skpc | C233: 45606 | D233: 21.13 | E233: 23.6 | F233: 20.2 | G233: =INDEX('اسعار الاسهم'!A:B,MATCH(B233,'اسعار الاسهم'!K:K,0),2) -> 17.01 | H233: =IF(O233="", G233/D233-1,"") | I233: =IF(O233="", E233/G233-1,"") | J233: =IF(O233="", 1-F233/G233,"") | K233: =E233/F233-1 -> 0.16831683 | L233: =IF( P233="",I233/J233,"") | M233: =IF(O233="",IF(I233<J233,"up","down"),"") | N233: =COUNTIFS(B:B,B233,O:O,"") -> 0 | O233: 0 | P233: 94 | Q233: =IF(NOT( P233=""),IF(O233=1,E233/D233-1,F233/D233-1),"") -> -0.044013251
A234: 89 | B234: egal | C234: 45613 | D234: 107.95 | E234: 113 | F234: 102 | G234: =INDEX('اسعار الاسهم'!A:B,MATCH(B234,'اسعار الاسهم'!K:K,0),2) -> 331.99 | H234: =IF(O234="", G234/D234-1,"") | I234: =IF(O234="", E234/G234-1,"") | J234: =IF(O234="", 1-F234/G234,"") | K234: =E234/F234-1 -> 0.10784314 | L234: =IF( P234="",I234/J234,"") | M234: =IF(O234="",IF(I234<J234,"up","down"),"") | N234: =COUNTIFS(B:B,B234,O:O,"") -> 4 | O234: 1 | P234: 56 | Q234: =IF(NOT( P234=""),IF(O234=1,E234/D234-1,F234/D234-1),"") -> 0.046780917
A235: 118 | B235: oih | C235: 45616 | D235: 0.47 | E235: 0.55 | F235: 0.435 | G235: =INDEX('اسعار الاسهم'!A:B,MATCH(B235,'اسعار الاسهم'!K:K,0),2) -> 1.46 | H235: =IF(O235="", G235/D235-1,"") | I235: =IF(O235="", E235/G235-1,"") | J235: =IF(O235="", 1-F235/G235,"") | K235: =E235/F235-1 -> 0.26436782 | L235: =IF( P235="",I235/J235,"") | M235: =IF(O235="",IF(I235<J235,"up","down"),"") | N235: =COUNTIFS(B:B,B235,O:O,"") -> 2 | O235: 0 | P235: 93 | Q235: =IF(NOT( P235=""),IF(O235=1,E235/D235-1,F235/D235-1),"") -> -0.074468085
A236: 25 | B236: prdc | C236: 45602 | D236: 3.48 | E236: 3.75 | F236: 3.3 | G236: =INDEX('اسعار الاسهم'!A:B,MATCH(B236,'اسعار الاسهم'!K:K,0),2) -> 5.45 | H236: =IF(O236="", G236/D236-1,"") | I236: =IF(O236="", E236/G236-1,"") | J236: =IF(O236="", 1-F236/G236,"") | K236: =E236/F236-1 -> 0.13636364 | L236: =IF( P236="",I236/J236,"") | M236: =IF(O236="",IF(I236<J236,"up","down"),"") | N236: =COUNTIFS(B:B,B236,O:O,"") -> 0 | O236: 0 | P236: 92 | Q236: =IF(NOT( P236=""),IF(O236=1,E236/D236-1,F236/D236-1),"") -> -0.051724138
A237: 85 | B237: etrs | C237: 45613 | D237: 4.95 | E237: 5.8 | F237: 4.7 | G237: =INDEX('اسعار الاسهم'!A:B,MATCH(B237,'اسعار الاسهم'!K:K,0),2) -> 7.59 | H237: =IF(O237="", G237/D237-1,"") | I237: =IF(O237="", E237/G237-1,"") | J237: =IF(O237="", 1-F237/G237,"") | K237: =E237/F237-1 -> 0.23404255 | L237: =IF( P237="",I237/J237,"") | M237: =IF(O237="",IF(I237<J237,"up","down"),"") | N237: =COUNTIFS(B:B,B237,O:O,"") -> 3 | O237: 1 | P237: 86 | Q237: =IF(NOT( P237=""),IF(O237=1,E237/D237-1,F237/D237-1),"") -> 0.17171717
A238: 38 | B238: swdy | C238: 45606 | D238: 92.5 | E238: 103 | F238: 88 | G238: =INDEX('اسعار الاسهم'!A:B,MATCH(B238,'اسعار الاسهم'!K:K,0),2) -> 87.9 | H238: =IF(O238="", G238/D238-1,"") | I238: =IF(O238="", E238/G238-1,"") | J238: =IF(O238="", 1-F238/G238,"") | K238: =E238/F238-1 -> 0.17045455 | L238: =IF( P238="",I238/J238,"") | M238: =IF(O238="",IF(I238<J238,"up","down"),"") | N238: =COUNTIFS(B:B,B238,O:O,"") -> 0 | O238: 0 | P238: 91 | Q238: =IF(NOT( P238=""),IF(O238=1,E238/D238-1,F238/D238-1),"") -> -0.048648649
A239: 81 | B239: lcsw | C239: 45610 | D239: 25.9 | E239: 31 | F239: 23.2 | G239: =INDEX('اسعار الاسهم'!A:B,MATCH(B239,'اسعار الاسهم'!K:K,0),2) -> 26.64 | H239: =IF(O239="", G239/D239-1,"") | I239: =IF(O239="", E239/G239-1,"") | J239: =IF(O239="", 1-F239/G239,"") | K239: =E239/F239-1 -> 0.3362069 | L239: =IF( P239="",I239/J239,"") | M239: =IF(O239="",IF(I239<J239,"up","down"),"") | N239: =COUNTIFS(B:B,B239,O:O,"") -> 1 | O239: 1 | P239: 108 | Q239: =IF(NOT( P239=""),IF(O239=1,E239/D239-1,F239/D239-1),"") -> 0.1969112
A240: 80 | B240: engc | C240: 45610 | D240: 22.79 | E240: 26.5 | F240: 21.5 | G240: =INDEX('اسعار الاسهم'!A:B,MATCH(B240,'اسعار الاسهم'!K:K,0),2) -> 32.76 | H240: =IF(O240="", G240/D240-1,"") | I240: =IF(O240="", E240/G240-1,"") | J240: =IF(O240="", 1-F240/G240,"") | K240: =E240/F240-1 -> 0.23255814 | L240: =IF( P240="",I240/J240,"") | M240: =IF(O240="",IF(I240<J240,"up","down"),"") | N240: =COUNTIFS(B:B,B240,O:O,"") -> 2 | O240: 1 | P240: 88 | Q240: =IF(NOT( P240=""),IF(O240=1,E240/D240-1,F240/D240-1),"") -> 0.1627907
A241: 46 | B241: spmd | C241: 45607 | D241: 0.375 | E241: 0.45 | F241: 0.355 | G241: =INDEX('اسعار الاسهم'!A:B,MATCH(B241,'اسعار الاسهم'!K:K,0),2) -> 0.39 | H241: =IF(O241="", G241/D241-1,"") | I241: =IF(O241="", E241/G241-1,"") | J241: =IF(O241="", 1-F241/G241,"") | K241: =E241/F241-1 -> 0.26760563 | L241: =IF( P241="",I241/J241,"") | M241: =IF(O241="",IF(I241<J241,"up","down"),"") | N241: =COUNTIFS(B:B,B241,O:O,"") -> 1 | O241: 0 | P241: 90 | Q241: =IF(NOT( P241=""),IF(O241=1,E241/D241-1,F241/D241-1),"") -> -0.053333333
A242: 92 | B242: gdwa | C242: 45613 | D242: 5.42 | E242: 6.4 | F242: 5 | G242: =INDEX('اسعار الاسهم'!A:B,MATCH(B242,'اسعار الاسهم'!K:K,0),2) -> 0.78 | H242: =IF(O242="", G242/D242-1,"") | I242: =IF(O242="", E242/G242-1,"") | J242: =IF(O242="", 1-F242/G242,"") | K242: =E242/F242-1 -> 0.28 | L242: =IF( P242="",I242/J242,"") | M242: =IF(O242="",IF(I242<J242,"up","down"),"") | N242: =COUNTIFS(B:B,B242,O:O,"") -> 0 | O242: 0 | P242: 89 | Q242: =IF(NOT( P242=""),IF(O242=1,E242/D242-1,F242/D242-1),"") -> -0.077490775
... A267: 27 | B267: arab | C267: 45602 | D267: 0.351 | E267: 0.395 | F267: 0.33 | G267: =INDEX('اسعار الاسهم'!A:B,MATCH(B267,'اسعار الاسهم'!K:K,0),2) -> 0.2 | H267: =IF(O267="", G267/D267-1,"") | I267: =IF(O267="", E267/G267-1,"") | J267: =IF(O267="", 1-F267/G267,"") | K267: =E267/F267-1 -> 0.1969697 | L267: =IF( P267="",I267/J267,"") | M267: =IF(O267="",IF(I267<J267,"up","down"),"") | N267: =COUNTIFS(B:B,B267,O:O,"") -> 1 | O267: 0 | P267: 40 | Q267: =IF(NOT( P267=""),IF(O267=1,E267/D267-1,F267/D267-1),"") -> -0.05982906
A268: 178 | B268: emfd | C268: 45627 | D268: 7.8 | E268: 8.5 | F268: 7.3 | G268: =INDEX('اسعار الاسهم'!A:B,MATCH(B268,'اسعار الاسهم'!K:K,0),2) -> 10.11 | H268: =IF(O268="", G268/D268-1,"") -> 0.29615385 | I268: =IF(O268="", E268/G268-1,"") -> -0.15924827 | J268: =IF(O268="", 1-F268/G268,"") -> 0.27794263 | K268: =E268/F268-1 -> 0.16438356 | L268: =IF( P268="",I268/J268,"") -> -0.57295374 | M268: =IF(O268="",IF(I268<J268,"up","down"),"") -> up | N268: =COUNTIFS(B:B,B268,O:O,"") -> 3 | Q268: =IF(NOT( P268=""),IF(O268=1,E268/D268-1,F268/D268-1),"")
A269: 93 | B269: esrs | C269: 45614 | D269: 117.01 | E269: 135 | F269: 112 | G269: =INDEX('اسعار الاسهم'!A:B,MATCH(B269,'اسعار الاسهم'!K:K,0),2) -> 141 | H269: =IF(O269="", G269/D269-1,"") | I269: =IF(O269="", E269/G269-1,"") | J269: =IF(O269="", 1-F269/G269,"") | K269: =E269/F269-1 -> 0.20535714 | L269: =IF( P269="",I269/J269,"") | M269: =IF(O269="",IF(I269<J269,"up","down"),"") | N269: =COUNTIFS(B:B,B269,O:O,"") -> 2 | O269: 0 | P269: 38 | Q269: =IF(NOT( P269=""),IF(O269=1,E269/D269-1,F269/D269-1),"") -> -0.042816853
A270: 47 | B270: taqa | C270: 45607 | D270: 14.1 | E270: 16 | F270: 13.15 | G270: =INDEX('اسعار الاسهم'!A:B,MATCH(B270,'اسعار الاسهم'!K:K,0),2) -> 13.19 | H270: =IF(O270="", G270/D270-1,"") | I270: =IF(O270="", E270/G270-1,"") | J270: =IF(O270="", 1-F270/G270,"") | K270: =E270/F270-1 -> 0.21673004 | L270: =IF( P270="",I270/J270,"") | M270: =IF(O270="",IF(I270<J270,"up","down"),"") | N270: =COUNTIFS(B:B,B270,O:O,"") -> 0 | O270: 0 | P270: 36 | Q270: =IF(NOT( P270=""),IF(O270=1,E270/D270-1,F270/D270-1),"") -> -0.067375887
A271: 124 | B271: ggcc | C271: 45617 | D271: 0.46 | E271: 0.55 | F271: 0.445 | G271: =INDEX('اسعار الاسهم'!A:B,MATCH(B271,'اسعار الاسهم'!K:K,0),2) -> 0.39 | H271: =IF(O271="", G271/D271-1,"") | I271: =IF(O271="", E271/G271-1,"") | J271: =IF(O271="", 1-F271/G271,"") | K271: =E271/F271-1 -> 0.23595506 | L271: =IF( P271="",I271/J271,"") | M271: =IF(O271="",IF(I271<J271,"up","down"),"") | N271: =COUNTIFS(B:B,B271,O:O,"") -> 1 | O271: 0 | P271: 34 | Q271: =IF(NOT( P271=""),IF(O271=1,E271/D271-1,F271/D271-1),"") -> -0.032608696
A272: 39 | B272: tmgh | C272: 45606 | D272: 60.71 | E272: 70 | F272: 58.5 | G272: =INDEX('اسعار الاسهم'!A:B,MATCH(B272,'اسعار الاسهم'!K:K,0),2) -> 99.48 | H272: =IF(O272="", G272/D272-1,"") | I272: =IF(O272="", E272/G272-1,"") | J272: =IF(O272="", 1-F272/G272,"") | K272: =E272/F272-1 -> 0.1965812 | L272: =IF( P272="",I272/J272,"") | M272: =IF(O272="",IF(I272<J272,"up","down"),"") | N272: =COUNTIFS(B:B,B272,O:O,"") -> 5 | O272: 0 | P272: 33 | Q272: =IF(NOT( P272=""),IF(O272=1,E272/D272-1,F272/D272-1),"") -> -0.03640257
A273: 3 | B273: rmda | C273: 45599 | D273: 3.59 | E273: 4.6 | F273: 3.3 | G273: =INDEX('اسعار الاسهم'!A:B,MATCH(B273,'اسعار الاسهم'!K:K,0),2) -> 5.06 | H273: =IF(O273="", G273/D273-1,"") | I273: =IF(O273="", E273/G273-1,"") | J273: =IF(O273="", 1-F273/G273,"") | K273: =E273/F273-1 -> 0.39393939 | L273: =IF( P273="",I273/J273,"") | M273: =IF(O273="",IF(I273<J273,"up","down"),"") | N273: =COUNTIFS(B:B,B273,O:O,"") -> 4 | O273: 0 | P273: 32 | Q273: =IF(NOT( P273=""),IF(O273=1,E273/D273-1,F273/D273-1),"") -> -0.080779944
A274: 79 | B274: comi | C274: 45610 | D274: 82.5 | E274: 89.5 | F274: 80 | G274: =INDEX('اسعار الاسهم'!A:B,MATCH(B274,'اسعار الاسهم'!K:K,0),2) -> 132.35 | H274: =IF(O274="", G274/D274-1,"") | I274: =IF(O274="", E274/G274-1,"") | J274: =IF(O274="", 1-F274/G274,"") | K274: =E274/F274-1 -> 0.11875 | L274: =IF( P274="",I274/J274,"") | M274: =IF(O274="",IF(I274<J274,"up","down"),"") | N274: =COUNTIFS(B:B,B274,O:O,"") -> 5 | O274: 0 | P274: 30 | Q274: =IF(NOT( P274=""),IF(O274=1,E274/D274-1,F274/D274-1),"") -> -0.03030303
A275: 34 | B275: hrho | C275: 45603 | D275: 22.77 | E275: 26.25 | F275: 21.5 | G275: =INDEX('اسعار الاسهم'!A:B,MATCH(B275,'اسعار الاسهم'!K:K,0),2) -> 26.32 | H275: =IF(O275="", G275/D275-1,"") | I275: =IF(O275="", E275/G275-1,"") | J275: =IF(O275="", 1-F275/G275,"") | K275: =E275/F275-1 -> 0.22093023 | L275: =IF( P275="",I275/J275,"") | M275: =IF(O275="",IF(I275<J275,"up","down"),"") | N275: =COUNTIFS(B:B,B275,O:O,"") -> 2 | O275: 0 | P275: 28 | Q275: =IF(NOT( P275=""),IF(O275=1,E275/D275-1,F275/D275-1),"") -> -0.055775143
A276: 55 | B276: btfh | C276: 45608 | D276: 3.06 | E276: 3.5 | F276: 2.9 | G276: =INDEX('اسعار الاسهم'!A:B,MATCH(B276,'اسعار الاسهم'!K:K,0),2) -> 3.08 | H276: =IF(O276="", G276/D276-1,"") | I276: =IF(O276="", E276/G276-1,"") | J276: =IF(O276="", 1-F276/G276,"") | K276: =E276/F276-1 -> 0.20689655 | L276: =IF( P276="",I276/J276,"") | M276: =IF(O276="",IF(I276<J276,"up","down"),"") | N276: =COUNTIFS(B:B,B276,O:O,"") -> 0 | O276: 0 | P276: 27 | Q276: =IF(NOT( P276=""),IF(O276=1,E276/D276-1,F276/D276-1),"") -> -0.052287582
A277: 30 | B277: fwry | C277: 45603 | D277: 8.16 | E277: 8.8 | F277: 7.6 | G277: =INDEX('اسعار الاسهم'!A:B,MATCH(B277,'اسعار الاسهم'!K:K,0),2) -> 19.32 | H277: =IF(O277="", G277/D277-1,"") | I277: =IF(O277="", E277/G277-1,"") | J277: =IF(O277="", 1-F277/G277,"") | K277: =E277/F277-1 -> 0.15789474 | L277: =IF( P277="",I277/J277,"") | M277: =IF(O277="",IF(I277<J277,"up","down"),"") | N277: =COUNTIFS(B:B,B277,O:O,"") -> 2 | O277: 1 | P277: 102 | Q277: =IF(NOT( P277=""),IF(O277=1,E277/D277-1,F277/D277-1),"") -> 0.078431373
A278: 88 | B278: comi | C278: 45613 | D278: 82.62 | E278: 87 | F278: 80.5 | G278: =INDEX('اسعار الاسهم'!A:B,MATCH(B278,'اسعار الاسهم'!K:K,0),2) -> 132.35 | H278: =IF(O278="", G278/D278-1,"") | I278: =IF(O278="", E278/G278-1,"") | J278: =IF(O278="", 1-F278/G278,"") | K278: =E278/F278-1 -> 0.080745342 | L278: =IF( P278="",I278/J278,"") | M278: =IF(O278="",IF(I278<J278,"up","down"),"") | N278: =COUNTIFS(B:B,B278,O:O,"") -> 5 | O278: 0 | P278: 24 | Q278: =IF(NOT( P278=""),IF(O278=1,E278/D278-1,F278/D278-1),"") -> -0.025659647
A279: 103 | B279: orwe | C279: 45614 | D279: 26.9 | E279: 28.1 | F279: 26.4 | G279: =INDEX('اسعار الاسهم'!A:B,MATCH(B279,'اسعار الاسهم'!K:K,0),2) -> 21.84 | H279: =IF(O279="", G279/D279-1,"") | I279: =IF(O279="", E279/G279-1,"") | J279: =IF(O279="", 1-F279/G279,"") | K279: =E279/F279-1 -> 0.064393939 | L279: =IF( P279="",I279/J279,"") | M279: =IF(O279="",IF(I279<J279,"up","down"),"") | N279: =COUNTIFS(B:B,B279,O:O,"") -> 4 | O279: 0 | P279: 23 | Q279: =IF(NOT( P279=""),IF(O279=1,E279/D279-1,F279/D279-1),"") -> -0.018587361
A280: 26 | B280: egal | C280: 45602 | D280: 105.29 | E280: 112.2 | F280: 103 | G280: =INDEX('اسعار الاسهم'!A:B,MATCH(B280,'اسعار الاسهم'!K:K,0),2) -> 331.99 | H280: =IF(O280="", G280/D280-1,"") | I280: =IF(O280="", E280/G280-1,"") | J280: =IF(O280="", 1-F280/G280,"") | K280: =E280/F280-1 -> 0.089320388 | L280: =IF( P280="",I280/J280,"") | M280: =IF(O280="",IF(I280<J280,"up","down"),"") | N280: =COUNTIFS(B:B,B280,O:O,"") -> 4 | O280: 1 | P280: 55 | Q280: =IF(NOT( P280=""),IF(O280=1,E280/D280-1,F280/D280-1),"") -> 0.065628265
... A316: 141 | B316: lcsw | C316: 45620 | D316: 26.66 | E316: 32.5 | F316: 23.5 | G316: =INDEX('اسعار الاسهم'!A:B,MATCH(B316,'اسعار الاسهم'!K:K,0),2) -> 26.64 | H316: =IF(O316="", G316/D316-1,"") | I316: =IF(O316="", E316/G316-1,"") | J316: =IF(O316="", 1-F316/G316,"") | K316: =E316/F316-1 -> 0.38297872 | L316: =IF( P316="",I316/J316,"") | M316: =IF(O316="",IF(I316<J316,"up","down"),"") | N316: =COUNTIFS(B:B,B316,O:O,"") -> 1 | O316: 1 | P316: 170 | Q316: =IF(NOT( P316=""),IF(O316=1,E316/D316-1,F316/D316-1),"") -> 0.21905476
A317: 191 | B317: mtie | C317: 45628 | D317: 7.23 | E317: 8.1 | F317: 6.8 | G317: =INDEX('اسعار الاسهم'!A:B,MATCH(B317,'اسعار الاسهم'!K:K,0),2) -> 8.79 | H317: =IF(O317="", G317/D317-1,"") | I317: =IF(O317="", E317/G317-1,"") | J317: =IF(O317="", 1-F317/G317,"") | K317: =E317/F317-1 -> 0.19117647 | L317: =IF( P317="",I317/J317,"") -> #VALUE! | M317: =IF(O317="",IF(I317<J317,"up","down"),"") | N317: =COUNTIFS(B:B,B317,O:O,"") -> 0 | O317: 0 | Q317: =IF(NOT( P317=""),IF(O317=1,E317/D317-1,F317/D317-1),"")
A318: 109 | B318: mtie | C318: 45615 | D318: 7.21 | E318: 8.1 | F318: 6.7 | G318: =INDEX('اسعار الاسهم'!A:B,MATCH(B318,'اسعار الاسهم'!K:K,0),2) -> 8.79 | H318: =IF(O318="", G318/D318-1,"") | I318: =IF(O318="", E318/G318-1,"") | J318: =IF(O318="", 1-F318/G318,"") | K318: =E318/F318-1 -> 0.20895522 | L318: =IF( P318="",I318/J318,"") -> #VALUE! | M318: =IF(O318="",IF(I318<J318,"up","down"),"") | N318: =COUNTIFS(B:B,B318,O:O,"") -> 0 | O318: 0 | Q318: =IF(NOT( P318=""),IF(O318=1,E318/D318-1,F318/D318-1),"")
A319: 179 | B319: rmda | C319: 45627 | D319: 3.46 | E319: 4.05 | F319: 3.2 | G319: =INDEX('اسعار الاسهم'!A:B,MATCH(B319,'اسعار الاسهم'!K:K,0),2) -> 5.06 | H319: =IF(O319="", G319/D319-1,"") -> 0.46242775 | I319: =IF(O319="", E319/G319-1,"") -> -0.19960474 | J319: =IF(O319="", 1-F319/G319,"") -> 0.36758893 | K319: =E319/F319-1 -> 0.265625 | L319: =IF( P319="",I319/J319,"") -> -0.54301075 | M319: =IF(O319="",IF(I319<J319,"up","down"),"") -> up | N319: =COUNTIFS(B:B,B319,O:O,"") -> 4 | Q319: =IF(NOT( P319=""),IF(O319=1,E319/D319-1,F319/D319-1),"")
A320: 182 | B320: masr | C320: 45627 | D320: 3.9 | E320: 4.4 | F320: 3.75 | G320: =INDEX('اسعار الاسهم'!A:B,MATCH(B320,'اسعار الاسهم'!K:K,0),2) -> 6.79 | H320: =IF(O320="", G320/D320-1,"") -> 0.74102564 | I320: =IF(O320="", E320/G320-1,"") -> -0.35198822 | J320: =IF(O320="", 1-F320/G320,"") -> 0.44771723 | K320: =E320/F320-1 -> 0.17333333 | L320: =IF( P320="",I320/J320,"") -> -0.78618421 | M320: =IF(O320="",IF(I320<J320,"up","down"),"") -> up | N320: =COUNTIFS(B:B,B320,O:O,"") -> 4 | Q320: =IF(NOT( P320=""),IF(O320=1,E320/D320-1,F320/D320-1),"")
A321: 170 | B321: orwe | C321: 45624 | D321: 26.15 | E321: 27.8 | F321: 24.8 | G321: =INDEX('اسعار الاسهم'!A:B,MATCH(B321,'اسعار الاسهم'!K:K,0),2) -> 21.84 | H321: =IF(O321="", G321/D321-1,"") -> -0.16481836 | I321: =IF(O321="", E321/G321-1,"") -> 0.27289377 | J321: =IF(O321="", 1-F321/G321,"") -> -0.13553114 | K321: =E321/F321-1 -> 0.12096774 | L321: =IF( P321="",I321/J321,"") -> -2.0135135 | M321: =IF(O321="",IF(I321<J321,"up","down"),"") -> down | N321: =COUNTIFS(B:B,B321,O:O,"") -> 4 | Q321: =IF(NOT( P321=""),IF(O321=1,E321/D321-1,F321/D321-1),"")
A322: 163 | B322: unip | C322: 45623 | D322: 0.595 | E322: 0.74 | F322: 0.53 | G322: =INDEX('اسعار الاسهم'!A:B,MATCH(B322,'اسعار الاسهم'!K:K,0),2) -> 0.28 | H322: =IF(O322="", G322/D322-1,"") -> -0.52941176 | I322: =IF(O322="", E322/G322-1,"") -> 1.6428571 | J322: =IF(O322="", 1-F322/G322,"") -> -0.89285714 | K322: =E322/F322-1 -> 0.39622642 | L322: =IF( P322="",I322/J322,"") -> -1.84 | M322: =IF(O322="",IF(I322<J322,"up","down"),"") -> down | N322: =COUNTIFS(B:B,B322,O:O,"") -> 2 | Q322: =IF(NOT( P322=""),IF(O322=1,E322/D322-1,F322/D322-1),"")
A323: 164 | B323: engc | C323: 45623 | D323: 25.5 | E323: 29.7 | F323: 23.35 | G323: =INDEX('اسعار الاسهم'!A:B,MATCH(B323,'اسعار الاسهم'!K:K,0),2) -> 32.76 | H323: =IF(O323="", G323/D323-1,"") -> 0.28470588 | I323: =IF(O323="", E323/G323-1,"") -> -0.093406593 | J323: =IF(O323="", 1-F323/G323,"") -> 0.28724054 | K323: =E323/F323-1 -> 0.27194861 | L323: =IF( P323="",I323/J323,"") -> -0.32518597 | M323: =IF(O323="",IF(I323<J323,"up","down"),"") -> up | N323: =COUNTIFS(B:B,B323,O:O,"") -> 2 | Q323: =IF(NOT( P323=""),IF(O323=1,E323/D323-1,F323/D323-1),"")
A324: 166 | B324: etel | C324: 45623 | D324: 33.11 | E324: 37 | F324: 31.5 | G324: =INDEX('اسعار الاسهم'!A:B,MATCH(B324,'اسعار الاسهم'!K:K,0),2) -> 95.5 | H324: =IF(O324="", G324/D324-1,"") -> 1.884325 | I324: =IF(O324="", E324/G324-1,"") -> -0.61256545 | J324: =IF(O324="", 1-F324/G324,"") -> 0.67015707 | K324: =E324/F324-1 -> 0.17460317 | L324: =IF( P324="",I324/J324,"") -> -0.9140625 | M324: =IF(O324="",IF(I324<J324,"up","down"),"") -> up | N324: =COUNTIFS(B:B,B324,O:O,"") -> 2 | Q324: =IF(NOT( P324=""),IF(O324=1,E324/D324-1,F324/D324-1),"")
A325: 167 | B325: egal | C325: 45623 | D325: 111.67 | E325: 123 | F325: 103 | G325: =INDEX('اسعار الاسهم'!A:B,MATCH(B325,'اسعار الاسهم'!K:K,0),2) -> 331.99 | H325: =IF(O325="", G325/D325-1,"") -> 1.972956 | I325: =IF(O325="", E325/G325-1,"") -> -0.62950691 | J325: =IF(O325="", 1-F325/G325,"") -> 0.68974969 | K325: =E325/F325-1 -> 0.19417476 | L325: =IF( P325="",I325/J325,"") -> -0.91265994 | M325: =IF(O325="",IF(I325<J325,"up","down"),"") -> up | N325: =COUNTIFS(B:B,B325,O:O,"") -> 4 | Q325: =IF(NOT( P325=""),IF(O325=1,E325/D325-1,F325/D325-1),"")
A326: 168 | B326: unip | C326: 45623 | D326: 0.57 | E326: 0.68 | F326: 0.51 | G326: =INDEX('اسعار الاسهم'!A:B,MATCH(B326,'اسعار الاسهم'!K:K,0),2) -> 0.28 | H326: =IF(O326="", G326/D326-1,"") -> -0.50877193 | I326: =IF(O326="", E326/G326-1,"") -> 1.4285714 | J326: =IF(O326="", 1-F326/G326,"") -> -0.82142857 | K326: =E326/F326-1 -> 0.33333333 | L326: =IF( P326="",I326/J326,"") -> -1.7391304 | M326: =IF(O326="",IF(I326<J326,"up","down"),"") -> down | N326: =COUNTIFS(B:B,B326,O:O,"") -> 2 | Q326: =IF(NOT( P326=""),IF(O326=1,E326/D326-1,F326/D326-1),"")
A327: 150 | B327: ofh | C327: 45622 | D327: 0.375 | E327: 0.45 | F327: 0.345 | G327: =INDEX('اسعار الاسهم'!A:B,MATCH(B327,'اسعار الاسهم'!K:K,0),2) -> 0.61 | H327: =IF(O327="", G327/D327-1,"") -> 0.62666667 | I327: =IF(O327="", E327/G327-1,"") -> -0.26229508 | J327: =IF(O327="", 1-F327/G327,"") -> 0.43442623 | K327: =E327/F327-1 -> 0.30434783 | L327: =IF( P327="",I327/J327,"") -> -0.60377358 | M327: =IF(O327="",IF(I327<J327,"up","down"),"") -> up | N327: =COUNTIFS(B:B,B327,O:O,"") -> 1 | Q327: =IF(NOT( P327=""),IF(O327=1,E327/D327-1,F327/D327-1),"")
A328: 151 | B328: rmda | C328: 45622 | D328: 3.4 | E328: 3.9 | F328: 3.2 | G328: =INDEX('اسعار الاسهم'!A:B,MATCH(B328,'اسعار الاسهم'!K:K,0),2) -> 5.06 | H328: =IF(O328="", G328/D328-1,"") -> 0.48823529 | I328: =IF(O328="", E328/G328-1,"") -> -0.22924901 | J328: =IF(O328="", 1-F328/G328,"") -> 0.36758893 | K328: =E328/F328-1 -> 0.21875 | L328: =IF( P328="",I328/J328,"") -> -0.62365591 | M328: =IF(O328="",IF(I328<J328,"up","down"),"") -> up | N328: =COUNTIFS(B:B,B328,O:O,"") -> 4 | Q328: =IF(NOT( P328=""),IF(O328=1,E328/D328-1,F328/D328-1),"")
...

Sheet evaluate ahmed saad
A1: num | B1: sahm | C1: before end of | D1: buy | E1: target | F1: loss | G1: current | H1: result | I1: up | J1: down | K1: range | L1: ratio | M1: near | N1: count active | O1: count | P1: done scenario | Q1: done date | R1: duration | S1: done num | T1: result | V1: recomendation average | W1: recommendations count | X1: average duration | Y1: year result
A2: 300 | B2: csag | C2: 45729 | D2: 23.6 | E2: 26.5 | F2: 22 | G2: =INDEX('اسعار الاسهم'!A:B,MATCH(B2,'اسعار الاسهم'!K:K,0),2) -> 30.5 | H2: =IF(P2="", G2/D2-1,"") -> 0.29237288 | I2: =IF(P2="", E2/G2-1,"") -> -0.13114754 | J2: =IF(P2="", 1-F2/G2,"") -> 0.27868852 | K2: =E2/F2-1 -> 0.20454545 | L2: =IF( S2="",I2/J2,"") -> -0.47058824 | M2: =IF(P2="",IF(I2<J2,"up","down"),"") -> up | N2: =COUNTIFS(B:B,B2,Q:Q,"") -> 1 | O2: =COUNTIFS(B:B,B2) -> 2 | R2: =IF(Q2, Q2-C2+2,"") | T2: =IF(NOT( S2=""),IF(P2=1,E2/D2-1,F2/D2-1),"") | V2: =AVERAGE(T:T) -> 0.014523676 | W2: =MAX(S:S) -> 238 | X2: =AVERAGE(R:R) -> 21.743697 | Y2: =POWER(1+V2,365/X2) -> 1.2738551
A3: 255 | B3: elsh | C3: 45713 | D3: 6.12 | E3: 6.8 | F3: 5.7 | G3: =INDEX('اسعار الاسهم'!A:B,MATCH(B3,'اسعار الاسهم'!K:K,0),2) -> 8.38 | H3: =IF(P3="", G3/D3-1,"") -> 0.36928105 | I3: =IF(P3="", E3/G3-1,"") -> -0.18854415 | J3: =IF(P3="", 1-F3/G3,"") -> 0.31980907 | K3: =E3/F3-1 -> 0.19298246 | L3: =IF( S3="",I3/J3,"") -> -0.58955224 | M3: =IF(P3="",IF(I3<J3,"up","down"),"") -> up | N3: =COUNTIFS(B:B,B3,Q:Q,"") -> 2 | O3: =COUNTIFS(B:B,B3) -> 3 | R3: =IF(Q3, Q3-C3+2,"") | T3: =IF(NOT( S3=""),IF(P3=1,E3/D3-1,F3/D3-1),"")
A4: 304 | B4: binv | C4: 45732 | D4: 22.8 | E4: 25.4 | F4: 21.3 | G4: =INDEX('اسعار الاسهم'!A:B,MATCH(B4,'اسعار الاسهم'!K:K,0),2) -> 41.43 | H4: =IF(P4="", G4/D4-1,"") -> 0.81710526 | I4: =IF(P4="", E4/G4-1,"") -> -0.38691769 | J4: =IF(P4="", 1-F4/G4,"") -> 0.4858798 | K4: =E4/F4-1 -> 0.19248826 | L4: =IF( S4="",I4/J4,"") -> -0.79632389 | M4: =IF(P4="",IF(I4<J4,"up","down"),"") -> up | N4: =COUNTIFS(B:B,B4,Q:Q,"") -> 1 | O4: =COUNTIFS(B:B,B4) -> 2 | R4: =IF(Q4, Q4-C4+2,"") | T4: =IF(NOT( S4=""),IF(P4=1,E4/D4-1,F4/D4-1),"")
A5: 187 | B5: elsh | C5: 45687 | D5: 6.12 | E5: 6.9 | F5: 5.7 | G5: =INDEX('اسعار الاسهم'!A:B,MATCH(B5,'اسعار الاسهم'!K:K,0),2) -> 8.38 | H5: =IF(P5="", G5/D5-1,"") -> 0.36928105 | I5: =IF(P5="", E5/G5-1,"") -> -0.17661098 | J5: =IF(P5="", 1-F5/G5,"") -> 0.31980907 | K5: =E5/F5-1 -> 0.21052632 | L5: =IF( S5="",I5/J5,"") -> -0.55223881 | M5: =IF(P5="",IF(I5<J5,"up","down"),"") -> up | N5: =COUNTIFS(B:B,B5,Q:Q,"") -> 2 | O5: =COUNTIFS(B:B,B5) -> 3 | R5: =IF(Q5, Q5-C5+2,"") | T5: =IF(NOT( S5=""),IF(P5=1,E5/D5-1,F5/D5-1),"")
A6: 160 | B6: amer | C6: 45678 | D6: 1.16 | E6: 1.33 | F6: 1.07 | G6: =INDEX('اسعار الاسهم'!A:B,MATCH(B6,'اسعار الاسهم'!K:K,0),2) -> 2.57 | H6: =IF(P6="", G6/D6-1,"") -> 1.2155172 | I6: =IF(P6="", E6/G6-1,"") -> -0.48249027 | J6: =IF(P6="", 1-F6/G6,"") -> 0.58365759 | K6: =E6/F6-1 -> 0.24299065 | L6: =IF( S6="",I6/J6,"") -> -0.82666667 | M6: =IF(P6="",IF(I6<J6,"up","down"),"") -> up | N6: =COUNTIFS(B:B,B6,Q:Q,"") -> 2 | O6: =COUNTIFS(B:B,B6) -> 4 | R6: =IF(Q6, Q6-C6+2,"") | T6: =IF(NOT( S6=""),IF(P6=1,E6/D6-1,F6/D6-1),"")
A7: 217 | B7: ofh | C7: 45699 | D7: 0.427 | E7: 0.475 | F7: 0.405 | G7: =INDEX('اسعار الاسهم'!A:B,MATCH(B7,'اسعار الاسهم'!K:K,0),2) -> 0.61 | H7: =IF(P7="", G7/D7-1,"") -> 0.42857143 | I7: =IF(P7="", E7/G7-1,"") -> -0.22131148 | J7: =IF(P7="", 1-F7/G7,"") -> 0.33606557 | K7: =E7/F7-1 -> 0.17283951 | L7: =IF( S7="",I7/J7,"") | M7: =IF(P7="",IF(I7<J7,"up","down"),"") -> up | N7: =COUNTIFS(B:B,B7,Q:Q,"") -> 0 | O7: =COUNTIFS(B:B,B7) -> 1 | Q7: 45699 | R7: =IF(Q7, Q7-C7+2,"") -> 2 | S7: 143 | T7: =IF(NOT( S7=""),IF(P7=1,E7/D7-1,F7/D7-1),"") -> -0.051522248
A8: 254 | B8: amer | C8: 45712 | D8: 1.215 | E8: 1.35 | F8: 1.14 | G8: =INDEX('اسعار الاسهم'!A:B,MATCH(B8,'اسعار الاسهم'!K:K,0),2) -> 2.57 | H8: =IF(P8="", G8/D8-1,"") -> 1.1152263 | I8: =IF(P8="", E8/G8-1,"") -> -0.47470817 | J8: =IF(P8="", 1-F8/G8,"") -> 0.55642023 | K8: =E8/F8-1 -> 0.18421053 | L8: =IF( S8="",I8/J8,"") -> -0.85314685 | M8: =IF(P8="",IF(I8<J8,"up","down"),"") -> up | N8: =COUNTIFS(B:B,B8,Q:Q,"") -> 2 | O8: =COUNTIFS(B:B,B8) -> 4 | R8: =IF(Q8, Q8-C8+2,"") | T8: =IF(NOT( S8=""),IF(P8=1,E8/D8-1,F8/D8-1),"")
A9: 246 | B9: bioc | C9: 45711 | D9: 37.6 | E9: 42 | F9: 35.3 | G9: =INDEX('اسعار الاسهم'!A:B,MATCH(B9,'اسعار الاسهم'!K:K,0),2) -> 70.46 | H9: =IF(P9="", G9/D9-1,"") -> 0.87393617 | I9: =IF(P9="", E9/G9-1,"") -> -0.40391712 | J9: =IF(P9="", 1-F9/G9,"") -> 0.49900653 | K9: =E9/F9-1 -> 0.1898017 | L9: =IF( S9="",I9/J9,"") -> -0.80944255 | M9: =IF(P9="",IF(I9<J9,"up","down"),"") -> up | N9: =COUNTIFS(B:B,B9,Q:Q,"") -> 1 | O9: =COUNTIFS(B:B,B9) -> 2 | R9: =IF(Q9, Q9-C9+2,"") | T9: =IF(NOT( S9=""),IF(P9=1,E9/D9-1,F9/D9-1),"")
A10: 62 | B10: etel | C10: 45636 | D10: 33.6 | E10: 38.5 | F10: 32 | G10: =INDEX('اسعار الاسهم'!A:B,MATCH(B10,'اسعار الاسهم'!K:K,0),2) -> 95.5 | H10: =IF(P10="", G10/D10-1,"") -> 1.8422619 | I10: =IF(P10="", E10/G10-1,"") -> -0.59685864 | J10: =IF(P10="", 1-F10/G10,"") -> 0.66492147 | K10: =E10/F10-1 -> 0.203125 | L10: =IF( S10="",I10/J10,"") -> -0.8976378 | M10: =IF(P10="",IF(I10<J10,"up","down"),"") -> up | N10: =COUNTIFS(B:B,B10,Q:Q,"") -> 1 | O10: =COUNTIFS(B:B,B10) -> 1 | R10: =IF(Q10, Q10-C10+2,"") | T10: =IF(NOT( S10=""),IF(P10=1,E10/D10-1,F10/D10-1),"")
A11: 239 | B11: mcro | C11: 45707 | D11: 2.05 | E11: 2.28 | F11: 1.85 | G11: =INDEX('اسعار الاسهم'!A:B,MATCH(B11,'اسعار الاسهم'!K:K,0),2) -> 1.23 | H11: =IF(P11="", G11/D11-1,"") -> -0.4 | I11: =IF(P11="", E11/G11-1,"") -> 0.85365854 | J11: =IF(P11="", 1-F11/G11,"") -> -0.50406504 | K11: =E11/F11-1 -> 0.23243243 | L11: =IF( S11="",I11/J11,"") -> -1.6935484 | M11: =IF(P11="",IF(I11<J11,"up","down"),"") -> down | N11: =COUNTIFS(B:B,B11,Q:Q,"") -> 2 | O11: =COUNTIFS(B:B,B11) -> 4 | R11: =IF(Q11, Q11-C11+2,"") | T11: =IF(NOT( S11=""),IF(P11=1,E11/D11-1,F11/D11-1),"")
A12: 235 | B12: mtie | C12: 45706 | D12: 7.3 | E12: 8.3 | F12: 6.85 | G12: =INDEX('اسعار الاسهم'!A:B,MATCH(B12,'اسعار الاسهم'!K:K,0),2) -> 8.79 | H12: =IF(P12="", G12/D12-1,"") -> 0.20410959 | I12: =IF(P12="", E12/G12-1,"") -> -0.055745165 | J12: =IF(P12="", 1-F12/G12,"") -> 0.22070535 | K12: =E12/F12-1 -> 0.21167883 | L12: =IF( S12="",I12/J12,"") -> -0.25257732 | M12: =IF(P12="",IF(I12<J12,"up","down"),"") -> up | N12: =COUNTIFS(B:B,B12,Q:Q,"") -> 2 | O12: =COUNTIFS(B:B,B12) -> 3 | R12: =IF(Q12, Q12-C12+2,"") | T12: =IF(NOT( S12=""),IF(P12=1,E12/D12-1,F12/D12-1),"")
A13: 146 | B13: phar | C13: 45676 | D13: 46 | E13: 52 | F13: 43.5 | G13: =INDEX('اسعار الاسهم'!A:B,MATCH(B13,'اسعار الاسهم'!K:K,0),2) -> 84.5 | H13: =IF(P13="", G13/D13-1,"") -> 0.83695652 | I13: =IF(P13="", E13/G13-1,"") -> -0.38461538 | J13: =IF(P13="", 1-F13/G13,"") -> 0.4852071 | K13: =E13/F13-1 -> 0.1954023 | L13: =IF( S13="",I13/J13,"") -> -0.79268293 | M13: =IF(P13="",IF(I13<J13,"up","down"),"") -> up | N13: =COUNTIFS(B:B,B13,Q:Q,"") -> 2 | O13: =COUNTIFS(B:B,B13) -> 4 | R13: =IF(Q13, Q13-C13+2,"") | T13: =IF(NOT( S13=""),IF(P13=1,E13/D13-1,F13/D13-1),"")
A14: 216 | B14: heli | C14: 45699 | D14: 10.6 | E14: 11.9 | F14: 10 | G14: =INDEX('اسعار الاسهم'!A:B,MATCH(B14,'اسعار الاسهم'!K:K,0),2) -> 6.43 | H14: =IF(P14="", G14/D14-1,"") -> -0.39339623 | I14: =IF(P14="", E14/G14-1,"") -> 0.85069984 | J14: =IF(P14="", 1-F14/G14,"") -> -0.55520995 | K14: =E14/F14-1 -> 0.19 | L14: =IF( S14="",I14/J14,"") | M14: =IF(P14="",IF(I14<J14,"up","down"),"") -> down | N14: =COUNTIFS(B:B,B14,Q:Q,"") -> 0 | O14: =COUNTIFS(B:B,B14) -> 2 | Q14: 45700 | R14: =IF(Q14, Q14-C14+2,"") -> 3 | S14: 155 | T14: =IF(NOT( S14=""),IF(P14=1,E14/D14-1,F14/D14-1),"") -> -0.056603774
A15: 288 | B15: mtie | C15: 45726 | D15: 7.5 | E15: 8.4 | F15: 7 | G15: =INDEX('اسعار الاسهم'!A:B,MATCH(B15,'اسعار الاسهم'!K:K,0),2) -> 8.79 | H15: =IF(P15="", G15/D15-1,"") -> 0.172 | I15: =IF(P15="", E15/G15-1,"") -> -0.044368601 | J15: =IF(P15="", 1-F15/G15,"") -> 0.2036405 | K15: =E15/F15-1 -> 0.2 | L15: =IF( S15="",I15/J15,"") -> -0.21787709 | M15: =IF(P15="",IF(I15<J15,"up","down"),"") -> up | N15: =COUNTIFS(B:B,B15,Q:Q,"") -> 2 | O15: =COUNTIFS(B:B,B15) -> 3 | R15: =IF(Q15, Q15-C15+2,"") | T15: =IF(NOT( S15=""),IF(P15=1,E15/D15-1,F15/D15-1),"")
A16: 280 | B16: mcro | C16: 45725 | D16: 2.1 | E16: 2.35 | F16: 1.94 | G16: =INDEX('اسعار الاسهم'!A:B,MATCH(B16,'اسعار الاسهم'!K:K,0),2) -> 1.23 | H16: =IF(P16="", G16/D16-1,"") -> -0.41428571 | I16: =IF(P16="", E16/G16-1,"") -> 0.91056911 | J16: =IF(P16="", 1-F16/G16,"") -> -0.57723577 | K16: =E16/F16-1 -> 0.21134021 | L16: =IF( S16="",I16/J16,"") -> -1.5774648 | M16: =IF(P16="",IF(I16<J16,"up","down"),"") -> down | N16: =COUNTIFS(B:B,B16,Q:Q,"") -> 2 | O16: =COUNTIFS(B:B,B16) -> 4 | R16: =IF(Q16, Q16-C16+2,"") | T16: =IF(NOT( S16=""),IF(P16=1,E16/D16-1,F16/D16-1),"")
A17: 287 | B17: sipc | C17: 45726 | D17: 1.23 | E17: 1.35 | F17: 1.12 | G17: =INDEX('اسعار الاسهم'!A:B,MATCH(B17,'اسعار الاسهم'!K:K,0),2) -> 3.43 | H17: =IF(P17="", G17/D17-1,"") -> 1.7886179 | I17: =IF(P17="", E17/G17-1,"") -> -0.60641399 | J17: =IF(P17="", 1-F17/G17,"") -> 0.67346939 | K17: =E17/F17-1 -> 0.20535714 | L17: =IF( S17="",I17/J17,"") -> -0.9004329 | M17: =IF(P17="",IF(I17<J17,"up","down"),"") -> up | N17: =COUNTIFS(B:B,B17,Q:Q,"") -> 1 | O17: =COUNTIFS(B:B,B17) -> 4 | R17: =IF(Q17, Q17-C17+2,"") | T17: =IF(NOT( S17=""),IF(P17=1,E17/D17-1,F17/D17-1),"")
A18: 58 | B18: binv | C18: 45635 | D18: 25.25 | E18: 29 | F18: 23.9 | G18: =INDEX('اسعار الاسهم'!A:B,MATCH(B18,'اسعار الاسهم'!K:K,0),2) -> 41.43 | H18: =IF(P18="", G18/D18-1,"") -> 0.64079208 | I18: =IF(P18="", E18/G18-1,"") -> -0.30002414 | J18: =IF(P18="", 1-F18/G18,"") -> 0.42312334 | K18: =E18/F18-1 -> 0.21338912 | L18: =IF( S18="",I18/J18,"") | M18: =IF(P18="",IF(I18<J18,"up","down"),"") -> up | N18: =COUNTIFS(B:B,B18,Q:Q,"") -> 1 | O18: =COUNTIFS(B:B,B18) -> 2 | Q18: 45690 | R18: =IF(Q18, Q18-C18+2,"") -> 57 | S18: 126 | T18: =IF(NOT( S18=""),IF(P18=1,E18/D18-1,F18/D18-1),"") -> -0.053465347
A19: 266 | B19: phar | C19: 45718 | D19: 47.6 | E19: 53 | F19: 44.5 | G19: =INDEX('اسعار الاسهم'!A:B,MATCH(B19,'اسعار الاسهم'!K:K,0),2) -> 84.5 | H19: =IF(P19="", G19/D19-1,"") -> 0.77521008 | I19: =IF(P19="", E19/G19-1,"") -> -0.37278107 | J19: =IF(P19="", 1-F19/G19,"") -> 0.47337278 | K19: =E19/F19-1 -> 0.19101124 | L19: =IF( S19="",I19/J19,"") -> -0.7875 | M19: =IF(P19="",IF(I19<J19,"up","down"),"") -> up | N19: =COUNTIFS(B:B,B19,Q:Q,"") -> 2 | O19: =COUNTIFS(B:B,B19) -> 4 | R19: =IF(Q19, Q19-C19+2,"") | T19: =IF(NOT( S19=""),IF(P19=1,E19/D19-1,F19/D19-1),"")
A20: 222 | B20: adib | C20: 45701 | D20: 39 | E20: 44.9 | F20: 37 | G20: =INDEX('اسعار الاسهم'!A:B,MATCH(B20,'اسعار الاسهم'!K:K,0),2) -> 46.1 | H20: =IF(P20="", G20/D20-1,"") -> 0.18205128 | I20: =IF(P20="", E20/G20-1,"") -> -0.026030369 | J20: =IF(P20="", 1-F20/G20,"") -> 0.19739696 | K20: =E20/F20-1 -> 0.21351351 | L20: =IF( S20="",I20/J20,"") -> -0.13186813 | M20: =IF(P20="",IF(I20<J20,"up","down"),"") -> up | N20: =COUNTIFS(B:B,B20,Q:Q,"") -> 2 | O20: =COUNTIFS(B:B,B20) -> 8 | R20: =IF(Q20, Q20-C20+2,"") | T20: =IF(NOT( S20=""),IF(P20=1,E20/D20-1,F20/D20-1),"")
A21: 186 | B21: expa | C21: 45687 | D21: 17.1 | E21: 20 | F21: 16.1 | G21: =INDEX('اسعار الاسهم'!A:B,MATCH(B21,'اسعار الاسهم'!K:K,0),2) -> 18.73 | H21: =IF(P21="", G21/D21-1,"") -> 0.095321637 | I21: =IF(P21="", E21/G21-1,"") -> 0.067805659 | J21: =IF(P21="", 1-F21/G21,"") -> 0.14041644 | K21: =E21/F21-1 -> 0.24223602 | L21: =IF( S21="",I21/J21,"") -> 0.48288973 | M21: =IF(P21="",IF(I21<J21,"up","down"),"") -> up | N21: =COUNTIFS(B:B,B21,Q:Q,"") -> 1 | O21: =COUNTIFS(B:B,B21) -> 3 | R21: =IF(Q21, Q21-C21+2,"") | T21: =IF(NOT( S21=""),IF(P21=1,E21/D21-1,F21/D21-1),"")
A22: 283 | B22: afmc | C22: 45725 | D22: 25 | E22: 28 | F22: 23.27 | G22: =INDEX('اسعار الاسهم'!A:B,MATCH(B22,'اسعار الاسهم'!K:K,0),2) -> 70.95 | H22: =IF(P22="", G22/D22-1,"") -> 1.838 | I22: =IF(P22="", E22/G22-1,"") -> -0.60535588 | J22: =IF(P22="", 1-F22/G22,"") -> 0.67202255 | K22: =E22/F22-1 -> 0.20326601 | L22: =IF( S22="",I22/J22,"") -> -0.90079698 | M22: =IF(P22="",IF(I22<J22,"up","down"),"") -> up | N22: =COUNTIFS(B:B,B22,Q:Q,"") -> 1 | O22: =COUNTIFS(B:B,B22) -> 4 | R22: =IF(Q22, Q22-C22+2,"") | T22: =IF(NOT( S22=""),IF(P22=1,E22/D22-1,F22/D22-1),"")
A23: 208 | B23: sugr | C23: 45697 | D23: 49 | E23: 55 | F23: 47 | G23: =INDEX('اسعار الاسهم'!A:B,MATCH(B23,'اسعار الاسهم'!K:K,0),2) -> 48.78 | H23: =IF(P23="", G23/D23-1,"") -> -0.0044897959 | I23: =IF(P23="", E23/G23-1,"") -> 0.12751128 | J23: =IF(P23="", 1-F23/G23,"") -> 0.036490365 | K23: =E23/F23-1 -> 0.17021277 | L23: =IF( S23="",I23/J23,"") -> 3.494382 | M23: =IF(P23="",IF(I23<J23,"up","down"),"") -> down | N23: =COUNTIFS(B:B,B23,Q:Q,"") -> 4 | O23: =COUNTIFS(B:B,B23) -> 4 | R23: =IF(Q23, Q23-C23+2,"") | T23: =IF(NOT( S23=""),IF(P23=1,E23/D23-1,F23/D23-1),"")
A24: 305 | B24: zmid | C24: 45733 | D24: 3.38 | E24: 3.75 | F24: 3.17 | G24: =INDEX('اسعار الاسهم'!A:B,MATCH(B24,'اسعار الاسهم'!K:K,0),2) -> 5.86 | H24: =IF(P24="", G24/D24-1,"") -> 0.73372781 | I24: =IF(P24="", E24/G24-1,"") -> -0.36006826 | J24: =IF(P24="", 1-F24/G24,"") -> 0.45904437 | K24: =E24/F24-1 -> 0.1829653 | L24: =IF( S24="",I24/J24,"") -> -0.78438662 | M24: =IF(P24="",IF(I24<J24,"up","down"),"") -> up | N24: =COUNTIFS(B:B,B24,Q:Q,"") -> 2 | O24: =COUNTIFS(B:B,B24) -> 2 | R24: =IF(Q24, Q24-C24+2,"") | T24: =IF(NOT( S24=""),IF(P24=1,E24/D24-1,F24/D24-1),"")
A25: 264 | B25: prcl | C25: 45715 | D25: 10.56 | E25: 11.9 | F25: 10 | G25: =INDEX('اسعار الاسهم'!A:B,MATCH(B25,'اسعار الاسهم'!K:K,0),2) -> 22.1 | H25: =IF(P25="", G25/D25-1,"") -> 1.092803 | I25: =IF(P25="", E25/G25-1,"") -> -0.46153846 | J25: =IF(P25="", 1-F25/G25,"") -> 0.54751131 | K25: =E25/F25-1 -> 0.19 | L25: =IF( S25="",I25/J25,"") -> -0.84297521 | M25: =IF(P25="",IF(I25<J25,"up","down"),"") -> up | N25: =COUNTIFS(B:B,B25,Q:Q,"") -> 2 | O25: =COUNTIFS(B:B,B25) -> 3 | R25: =IF(Q25, Q25-C25+2,"") | T25: =IF(NOT( S25=""),IF(P25=1,E25/D25-1,F25/D25-1),"")
A26: 245 | B26: kzpc | C26: 45708 | D26: 11 | E26: 12.4 | F26: 10.2 | G26: =INDEX('اسعار الاسهم'!A:B,MATCH(B26,'اسعار الاسهم'!K:K,0),2) -> 10.33 | H26: =IF(P26="", G26/D26-1,"") -> -0.060909091 | I26: =IF(P26="", E26/G26-1,"") -> 0.20038722 | J26: =IF(P26="", 1-F26/G26,"") -> 0.012584705 | K26: =E26/F26-1 -> 0.21568627 | L26: =IF( S26="",I26/J26,"") -> 15.923077 | M26: =IF(P26="",IF(I26<J26,"up","down"),"") -> down | N26: =COUNTIFS(B:B,B26,Q:Q,"") -> 2 | O26: =COUNTIFS(B:B,B26) -> 2 | R26: =IF(Q26, Q26-C26+2,"") | T26: =IF(NOT( S26=""),IF(P26=1,E26/D26-1,F26/D26-1),"")
A27: 282 | B27: kzpc | C27: 45725 | D27: 11.1 | E27: 12.4 | F27: 10.45 | G27: =INDEX('اسعار الاسهم'!A:B,MATCH(B27,'اسعار الاسهم'!K:K,0),2) -> 10.33 | H27: =IF(P27="", G27/D27-1,"") -> -0.069369369 | I27: =IF(P27="", E27/G27-1,"") -> 0.20038722 | J27: =IF(P27="", 1-F27/G27,"") -> -0.011616651 | K27: =E27/F27-1 -> 0.18660287 | L27: =IF( S27="",I27/J27,"") -> -17.25 | M27: =IF(P27="",IF(I27<J27,"up","down"),"") -> down | N27: =COUNTIFS(B:B,B27,Q:Q,"") -> 2 | O27: =COUNTIFS(B:B,B27) -> 2 | R27: =IF(Q27, Q27-C27+2,"") | T27: =IF(NOT( S27=""),IF(P27=1,E27/D27-1,F27/D27-1),"")
A28: 182 | B28: prcl | C28: 45686 | D28: 10.68 | E28: 11.95 | F28: 9.9 | G28: =INDEX('اسعار الاسهم'!A:B,MATCH(B28,'اسعار الاسهم'!K:K,0),2) -> 22.1 | H28: =IF(P28="", G28/D28-1,"") -> 1.0692884 | I28: =IF(P28="", E28/G28-1,"") -> -0.45927602 | J28: =IF(P28="", 1-F28/G28,"") -> 0.5520362 | K28: =E28/F28-1 -> 0.20707071 | L28: =IF( S28="",I28/J28,"") -> -0.83196721 | M28: =IF(P28="",IF(I28<J28,"up","down"),"") -> up | N28: =COUNTIFS(B:B,B28,Q:Q,"") -> 2 | O28: =COUNTIFS(B:B,B28) -> 3 | R28: =IF(Q28, Q28-C28+2,"") | T28: =IF(NOT( S28=""),IF(P28=1,E28/D28-1,F28/D28-1),"")
A29: 145 | B29: sugr | C29: 45673 | D29: 49 | E29: 55.3 | F29: 46 | G29: =INDEX('اسعار الاسهم'!A:B,MATCH(B29,'اسعار الاسهم'!K:K,0),2) -> 48.78 | H29: =IF(P29="", G29/D29-1,"") -> -0.0044897959 | I29: =IF(P29="", E29/G29-1,"") -> 0.13366134 | J29: =IF(P29="", 1-F29/G29,"") -> 0.05699057 | K29: =E29/F29-1 -> 0.20217391 | L29: =IF( S29="",I29/J29,"") -> 2.3453237 | M29: =IF(P29="",IF(I29<J29,"up","down"),"") -> down | N29: =COUNTIFS(B:B,B29,Q:Q,"") -> 4 | O29: =COUNTIFS(B:B,B29) -> 4 | R29: =IF(Q29, Q29-C29+2,"") | T29: =IF(NOT( S29=""),IF(P29=1,E29/D29-1,F29/D29-1),"")
A30: 188 | B30: sugr | C30: 45687 | D30: 49.3 | E30: 55.3 | F30: 47 | G30: =INDEX('اسعار الاسهم'!A:B,MATCH(B30,'اسعار الاسهم'!K:K,0),2) -> 48.78 | H30: =IF(P30="", G30/D30-1,"") -> -0.010547667 | I30: =IF(P30="", E30/G30-1,"") -> 0.13366134 | J30: =IF(P30="", 1-F30/G30,"") -> 0.036490365 | K30: =E30/F30-1 -> 0.17659574 | L30: =IF( S30="",I30/J30,"") -> 3.6629213 | M30: =IF(P30="",IF(I30<J30,"up","down"),"") -> down | N30: =COUNTIFS(B:B,B30,Q:Q,"") -> 4 | O30: =COUNTIFS(B:B,B30) -> 4 | R30: =IF(Q30, Q30-C30+2,"") | T30: =IF(NOT( S30=""),IF(P30=1,E30/D30-1,F30/D30-1),"")
... A52: 152 | B52: taqa | C52: 45677 | D52: 12.2 | E52: 14 | F52: 11.55 | G52: =INDEX('اسعار الاسهم'!A:B,MATCH(B52,'اسعار الاسهم'!K:K,0),2) -> 13.19 | H52: =IF(P52="", G52/D52-1,"") -> 0.081147541 | I52: =IF(P52="", E52/G52-1,"") -> 0.061410159 | J52: =IF(P52="", 1-F52/G52,"") -> 0.12433662 | K52: =E52/F52-1 -> 0.21212121 | L52: =IF( S52="",I52/J52,"") -> 0.49390244 | M52: =IF(P52="",IF(I52<J52,"up","down"),"") -> up | N52: =COUNTIFS(B:B,B52,Q:Q,"") -> 4 | O52: =COUNTIFS(B:B,B52) -> 4 | R52: =IF(Q52, Q52-C52+2,"") | T52: =IF(NOT( S52=""),IF(P52=1,E52/D52-1,F52/D52-1),"")
A53: 195 | B53: taqa | C53: 45691 | D53: 12.35 | E53: 14 | F53: 11.6 | G53: =INDEX('اسعار الاسهم'!A:B,MATCH(B53,'اسعار الاسهم'!K:K,0),2) -> 13.19 | H53: =IF(P53="", G53/D53-1,"") -> 0.068016194 | I53: =IF(P53="", E53/G53-1,"") -> 0.061410159 | K53: =E53/F53-1 -> 0.20689655 | L53: =IF( S53="",I53/J53,"") -> #DIV/0! | M53: =IF(P53="",IF(I53<J53,"up","down"),"") -> down | N53: =COUNTIFS(B:B,B53,Q:Q,"") -> 4 | O53: =COUNTIFS(B:B,B53) -> 4 | R53: =IF(Q53, Q53-C53+2,"") | T53: =IF(NOT( S53=""),IF(P53=1,E53/D53-1,F53/D53-1),"")
A54: 223 | B54: taqa | C54: 45701 | D54: 12.32 | E54: 14 | F54: 11.6 | G54: =INDEX('اسعار الاسهم'!A:B,MATCH(B54,'اسعار الاسهم'!K:K,0),2) -> 13.19 | H54: =IF(P54="", G54/D54-1,"") -> 0.070616883 | I54: =IF(P54="", E54/G54-1,"") -> 0.061410159 | J54: =IF(P54="", 1-F54/G54,"") -> 0.12054587 | K54: =E54/F54-1 -> 0.20689655 | L54: =IF( S54="",I54/J54,"") -> 0.50943396 | M54: =IF(P54="",IF(I54<J54,"up","down"),"") -> up | N54: =COUNTIFS(B:B,B54,Q:Q,"") -> 4 | O54: =COUNTIFS(B:B,B54) -> 4 | R54: =IF(Q54, Q54-C54+2,"") | T54: =IF(NOT( S54=""),IF(P54=1,E54/D54-1,F54/D54-1),"")
A55: 230 | B55: oras | C55: 45705 | D55: 268 | E55: 300 | F55: 259 | G55: =INDEX('اسعار الاسهم'!A:B,MATCH(B55,'اسعار الاسهم'!K:K,0),2) -> 708.01 | H55: =IF(P55="", G55/D55-1,"") -> 1.6418284 | I55: =IF(P55="", E55/G55-1,"") -> -0.57627717 | J55: =IF(P55="", 1-F55/G55,"") -> 0.63418596 | K55: =E55/F55-1 -> 0.15830116 | L55: =IF( S55="",I55/J55,"") -> -0.908688 | M55: =IF(P55="",IF(I55<J55,"up","down"),"") -> up | N55: =COUNTIFS(B:B,B55,Q:Q,"") -> 4 | O55: =COUNTIFS(B:B,B55) -> 5 | R55: =IF(Q55, Q55-C55+2,"") | T55: =IF(NOT( S55=""),IF(P55=1,E55/D55-1,F55/D55-1),"")
A56: 296 | B56: spin | C56: 45728 | D56: 9.3 | E56: 10.7 | F56: 8.7 | G56: =INDEX('اسعار الاسهم'!A:B,MATCH(B56,'اسعار الاسهم'!K:K,0),2) -> 14.35 | H56: =IF(P56="", G56/D56-1,"") -> 0.54301075 | I56: =IF(P56="", E56/G56-1,"") -> -0.2543554 | J56: =IF(P56="", 1-F56/G56,"") -> 0.39372822 | K56: =E56/F56-1 -> 0.22988506 | L56: =IF( S56="",I56/J56,"") -> -0.6460177 | M56: =IF(P56="",IF(I56<J56,"up","down"),"") -> up | N56: =COUNTIFS(B:B,B56,Q:Q,"") -> 1 | O56: =COUNTIFS(B:B,B56) -> 4 | R56: =IF(Q56, Q56-C56+2,"") | T56: =IF(NOT( S56=""),IF(P56=1,E56/D56-1,F56/D56-1),"")
A57: 219 | B57: qnbe | C57: 45701 | D57: 30.5 | E57: 34.2 | F57: 28.5 | G57: =INDEX('اسعار الاسهم'!A:B,MATCH(B57,'اسعار الاسهم'!K:K,0),2) -> 53.39 | H57: =IF(P57="", G57/D57-1,"") -> 0.7504918 | I57: =IF(P57="", E57/G57-1,"") -> -0.3594306 | J57: =IF(P57="", 1-F57/G57,"") -> 0.46619217 | K57: =E57/F57-1 -> 0.2 | L57: =IF( S57="",I57/J57,"") -> -0.77099237 | M57: =IF(P57="",IF(I57<J57,"up","down"),"") -> up | N57: =COUNTIFS(B:B,B57,Q:Q,"") -> 1 | O57: =COUNTIFS(B:B,B57) -> 4 | R57: =IF(Q57, Q57-C57+2,"") | T57: =IF(NOT( S57=""),IF(P57=1,E57/D57-1,F57/D57-1),"")
A58: 281 | B58: elec | C58: 45725 | D58: 2.78 | E58: 3.15 | F58: 2.6 | G58: =INDEX('اسعار الاسهم'!A:B,MATCH(B58,'اسعار الاسهم'!K:K,0),2) -> 2.1 | H58: =IF(P58="", G58/D58-1,"") -> -0.24460432 | I58: =IF(P58="", E58/G58-1,"") -> 0.5 | J58: =IF(P58="", 1-F58/G58,"") -> -0.23809524 | K58: =E58/F58-1 -> 0.21153846 | L58: =IF( S58="",I58/J58,"") -> -2.1 | M58: =IF(P58="",IF(I58<J58,"up","down"),"") -> down | N58: =COUNTIFS(B:B,B58,Q:Q,"") -> 1 | O58: =COUNTIFS(B:B,B58) -> 1 | R58: =IF(Q58, Q58-C58+2,"") | T58: =IF(NOT( S58=""),IF(P58=1,E58/D58-1,F58/D58-1),"")
A59: 210 | B59: aih | C59: 45697 | D59: 0.542 | E59: 0.62 | F59: 0.51 | G59: =INDEX('اسعار الاسهم'!A:B,MATCH(B59,'اسعار الاسهم'!K:K,0),2) -> 0.34 | H59: =IF(P59="", G59/D59-1,"") -> -0.37269373 | I59: =IF(P59="", E59/G59-1,"") -> 0.82352941 | J59: =IF(P59="", 1-F59/G59,"") -> -0.5 | K59: =E59/F59-1 -> 0.21568627 | L59: =IF( S59="",I59/J59,"") | M59: =IF(P59="",IF(I59<J59,"up","down"),"") -> down | N59: =COUNTIFS(B:B,B59,Q:Q,"") -> 0 | O59: =COUNTIFS(B:B,B59) -> 3 | Q59: 45720 | R59: =IF(Q59, Q59-C59+2,"") -> 25 | S59: 173 | T59: =IF(NOT( S59=""),IF(P59=1,E59/D59-1,F59/D59-1),"") -> -0.05904059
A60: 303 | B60: egas | C60: 45732 | D60: 40.3 | E60: 45 | F60: 37.5 | G60: =INDEX('اسعار الاسهم'!A:B,MATCH(B60,'اسعار الاسهم'!K:K,0),2) -> 49 | H60: =IF(P60="", G60/D60-1,"") -> 0.21588089 | I60: =IF(P60="", E60/G60-1,"") -> -0.081632653 | J60: =IF(P60="", 1-F60/G60,"") -> 0.23469388 | K60: =E60/F60-1 -> 0.2 | L60: =IF( S60="",I60/J60,"") -> -0.34782609 | M60: =IF(P60="",IF(I60<J60,"up","down"),"") -> up | N60: =COUNTIFS(B:B,B60,Q:Q,"") -> 2 | O60: =COUNTIFS(B:B,B60) -> 7 | R60: =IF(Q60, Q60-C60+2,"") | T60: =IF(NOT( S60=""),IF(P60=1,E60/D60-1,F60/D60-1),"")
A61: 247 | B61: alum | C61: 45711 | D61: 13.94 | E61: 15.5 | F61: 13 | G61: =INDEX('اسعار الاسهم'!A:B,MATCH(B61,'اسعار الاسهم'!K:K,0),2) -> 24.7 | H61: =IF(P61="", G61/D61-1,"") -> 0.77187948 | I61: =IF(P61="", E61/G61-1,"") -> -0.37246964 | J61: =IF(P61="", 1-F61/G61,"") -> 0.47368421 | K61: =E61/F61-1 -> 0.19230769 | L61: =IF( S61="",I61/J61,"") -> -0.78632479 | M61: =IF(P61="",IF(I61<J61,"up","down"),"") -> up | N61: =COUNTIFS(B:B,B61,Q:Q,"") -> 3 | O61: =COUNTIFS(B:B,B61) -> 4 | R61: =IF(Q61, Q61-C61+2,"") | T61: =IF(NOT( S61=""),IF(P61=1,E61/D61-1,F61/D61-1),"")
A62: 170 | B62: krdi | C62: 45680 | D62: 0.582 | E62: 0.695 | F62: 0.55 | G62: =INDEX('اسعار الاسهم'!A:B,MATCH(B62,'اسعار الاسهم'!K:K,0),2) -> 0.34 | H62: =IF(P62="", G62/D62-1,"") -> -0.41580756 | I62: =IF(P62="", E62/G62-1,"") -> 1.0441176 | J62: =IF(P62="", 1-F62/G62,"") -> -0.61764706 | K62: =E62/F62-1 -> 0.26363636 | L62: =IF( S62="",I62/J62,"") -> -1.6904762 | M62: =IF(P62="",IF(I62<J62,"up","down"),"") -> down | N62: =COUNTIFS(B:B,B62,Q:Q,"") -> 1 | O62: =COUNTIFS(B:B,B62) -> 3 | R62: =IF(Q62, Q62-C62+2,"") | T62: =IF(NOT( S62=""),IF(P62=1,E62/D62-1,F62/D62-1),"")
A63: 117 | B63: aih | C63: 45663 | D63: 0.565 | E63: 0.625 | F63: 0.525 | G63: =INDEX('اسعار الاسهم'!A:B,MATCH(B63,'اسعار الاسهم'!K:K,0),2) -> 0.34 | H63: =IF(P63="", G63/D63-1,"") -> -0.39823009 | I63: =IF(P63="", E63/G63-1,"") -> 0.83823529 | J63: =IF(P63="", 1-F63/G63,"") -> -0.54411765 | K63: =E63/F63-1 -> 0.19047619 | L63: =IF( S63="",I63/J63,"") | M63: =IF(P63="",IF(I63<J63,"up","down"),"") -> down | N63: =COUNTIFS(B:B,B63,Q:Q,"") -> 0 | O63: =COUNTIFS(B:B,B63) -> 3 | Q63: 45669 | R63: =IF(Q63, Q63-C63+2,"") -> 8 | S63: 84 | T63: =IF(NOT( S63=""),IF(P63=1,E63/D63-1,F63/D63-1),"") -> -0.07079646
A64: 290 | B64: eiud | C64: 45727 | D64: 0.283 | E64: 0.319 | F64: 0.264 | G64: =INDEX('اسعار الاسهم'!A:B,MATCH(B64,'اسعار الاسهم'!K:K,0),2) -> #N/A | H64: =IF(P64="", G64/D64-1,"") -> #N/A | I64: =IF(P64="", E64/G64-1,"") -> #N/A | J64: =IF(P64="", 1-F64/G64,"") -> #N/A | K64: =E64/F64-1 -> 0.20833333 | L64: =IF( S64="",I64/J64,"") -> #N/A | M64: =IF(P64="",IF(I64<J64,"up","down"),"") -> #N/A | N64: =COUNTIFS(B:B,B64,Q:Q,"") -> 1 | O64: =COUNTIFS(B:B,B64) -> 4 | R64: =IF(Q64, Q64-C64+2,"") | T64: =IF(NOT( S64=""),IF(P64=1,E64/D64-1,F64/D64-1),"")
A65: 197 | B65: mich | C65: 45692 | D65: 28.2 | E65: 32 | F65: 26.6 | G65: =INDEX('اسعار الاسهم'!A:B,MATCH(B65,'اسعار الاسهم'!K:K,0),2) -> 35.5 | H65: =IF(P65="", G65/D65-1,"") -> 0.25886525 | I65: =IF(P65="", E65/G65-1,"") -> -0.098591549 | J65: =IF(P65="", 1-F65/G65,"") -> 0.25070423 | K65: =E65/F65-1 -> 0.20300752 | L65: =IF( S65="",I65/J65,"") | M65: =IF(P65="",IF(I65<J65,"up","down"),"") -> up | N65: =COUNTIFS(B:B,B65,Q:Q,"") -> 0 | O65: =COUNTIFS(B:B,B65) -> 3 | Q65: 45700 | R65: =IF(Q65, Q65-C65+2,"") -> 10 | S65: 153 | T65: =IF(NOT( S65=""),IF(P65=1,E65/D65-1,F65/D65-1),"") -> -0.056737589
A66: 125 | B66: alum | C66: 45665 | D66: 13.95 | E66: 15.75 | F66: 13 | G66: =INDEX('اسعار الاسهم'!A:B,MATCH(B66,'اسعار الاسهم'!K:K,0),2) -> 24.7 | H66: =IF(P66="", G66/D66-1,"") -> 0.77060932 | I66: =IF(P66="", E66/G66-1,"") -> -0.36234818 | J66: =IF(P66="", 1-F66/G66,"") -> 0.47368421 | K66: =E66/F66-1 -> 0.21153846 | L66: =IF( S66="",I66/J66,"") -> -0.76495726 | M66: =IF(P66="",IF(I66<J66,"up","down"),"") -> up | N66: =COUNTIFS(B:B,B66,Q:Q,"") -> 3 | O66: =COUNTIFS(B:B,B66) -> 4 | R66: =IF(Q66, Q66-C66+2,"") | T66: =IF(NOT( S66=""),IF(P66=1,E66/D66-1,F66/D66-1),"")
A67: 228 | B67: saud | C67: 45704 | D67: 12.05 | E67: 13.5 | F67: 11.5 | G67: =INDEX('اسعار الاسهم'!A:B,MATCH(B67,'اسعار الاسهم'!K:K,0),2) -> 22.19 | H67: =IF(P67="", G67/D67-1,"") -> 0.84149378 | I67: =IF(P67="", E67/G67-1,"") -> -0.39161785 | J67: =IF(P67="", 1-F67/G67,"") -> 0.48174854 | K67: =E67/F67-1 -> 0.17391304 | L67: =IF( S67="",I67/J67,"") -> -0.81290926 | M67: =IF(P67="",IF(I67<J67,"up","down"),"") -> up | N67: =COUNTIFS(B:B,B67,Q:Q,"") -> 2 | O67: =COUNTIFS(B:B,B67) -> 2 | R67: =IF(Q67, Q67-C67+2,"") | T67: =IF(NOT( S67=""),IF(P67=1,E67/D67-1,F67/D67-1),"")
A68: 258 | B68: efid | C68: 45713 | D68: 28.5 | E68: 32 | F68: 26.5 | G68: =INDEX('اسعار الاسهم'!A:B,MATCH(B68,'اسعار الاسهم'!K:K,0),2) -> 27.92 | H68: =IF(P68="", G68/D68-1,"") -> -0.020350877 | I68: =IF(P68="", E68/G68-1,"") -> 0.14613181 | J68: =IF(P68="", 1-F68/G68,"") -> 0.050859599 | K68: =E68/F68-1 -> 0.20754717 | L68: =IF( S68="",I68/J68,"") -> 2.8732394 | M68: =IF(P68="",IF(I68<J68,"up","down"),"") -> down | N68: =COUNTIFS(B:B,B68,Q:Q,"") -> 1 | O68: =COUNTIFS(B:B,B68) -> 1 | R68: =IF(Q68, Q68-C68+2,"") | T68: =IF(NOT( S68=""),IF(P68=1,E68/D68-1,F68/D68-1),"")
A69: 175 | B69: egas | C69: 45684 | D69: 41.25 | E69: 47 | F69: 38 | G69: =INDEX('اسعار الاسهم'!A:B,MATCH(B69,'اسعار الاسهم'!K:K,0),2) -> 49 | H69: =IF(P69="", G69/D69-1,"") -> 0.18787879 | I69: =IF(P69="", E69/G69-1,"") -> -0.040816327 | J69: =IF(P69="", 1-F69/G69,"") -> 0.2244898 | K69: =E69/F69-1 -> 0.23684211 | L69: =IF( S69="",I69/J69,"") -> -0.18181818 | M69: =IF(P69="",IF(I69<J69,"up","down"),"") -> up | N69: =COUNTIFS(B:B,B69,Q:Q,"") -> 2 | O69: =COUNTIFS(B:B,B69) -> 7 | R69: =IF(Q69, Q69-C69+2,"") | T69: =IF(NOT( S69=""),IF(P69=1,E69/D69-1,F69/D69-1),"")
A70: 284 | B70: mfpc | C70: 45726 | D70: 42.1 | E70: 46.9 | F70: 39.5 | G70: =INDEX('اسعار الاسهم'!A:B,MATCH(B70,'اسعار الاسهم'!K:K,0),2) -> 43.48 | H70: =IF(P70="", G70/D70-1,"") -> 0.032779097 | I70: =IF(P70="", E70/G70-1,"") -> 0.078656854 | J70: =IF(P70="", 1-F70/G70,"") -> 0.091536339 | K70: =E70/F70-1 -> 0.18734177 | L70: =IF( S70="",I70/J70,"") -> 0.85929648 | M70: =IF(P70="",IF(I70<J70,"up","down"),"") -> up | N70: =COUNTIFS(B:B,B70,Q:Q,"") -> 1 | O70: =COUNTIFS(B:B,B70) -> 2 | R70: =IF(Q70, Q70-C70+2,"") | T70: =IF(NOT( S70=""),IF(P70=1,E70/D70-1,F70/D70-1),"")
A71: 164 | B71: saud | C71: 45679 | D71: 12.22 | E71: 13.95 | F71: 11.54 | G71: =INDEX('اسعار الاسهم'!A:B,MATCH(B71,'اسعار الاسهم'!K:K,0),2) -> 22.19 | H71: =IF(P71="", G71/D71-1,"") -> 0.81587561 | I71: =IF(P71="", E71/G71-1,"") -> -0.37133844 | J71: =IF(P71="", 1-F71/G71,"") -> 0.47994592 | K71: =E71/F71-1 -> 0.20883882 | L71: =IF( S71="",I71/J71,"") -> -0.77370892 | M71: =IF(P71="",IF(I71<J71,"up","down"),"") -> up | N71: =COUNTIFS(B:B,B71,Q:Q,"") -> 2 | O71: =COUNTIFS(B:B,B71) -> 2 | R71: =IF(Q71, Q71-C71+2,"") | T71: =IF(NOT( S71=""),IF(P71=1,E71/D71-1,F71/D71-1),"")
A72: 85 | B72: ftns | C72: 45644 | D72: 1.6 | E72: 1.94 | F72: 1.46 | G72: =INDEX('اسعار الاسهم'!A:B,MATCH(B72,'اسعار الاسهم'!K:K,0),2) -> 1.15 | H72: =IF(P72="", G72/D72-1,"") -> -0.28125 | I72: =IF(P72="", E72/G72-1,"") -> 0.68695652 | J72: =IF(P72="", 1-F72/G72,"") -> -0.26956522 | K72: =E72/F72-1 -> 0.32876712 | L72: =IF( S72="",I72/J72,"") -> -2.5483871 | M72: =IF(P72="",IF(I72<J72,"up","down"),"") -> down | N72: =COUNTIFS(B:B,B72,Q:Q,"") -> 1 | O72: =COUNTIFS(B:B,B72) -> 4 | R72: =IF(Q72, Q72-C72+2,"") | T72: =IF(NOT( S72=""),IF(P72=1,E72/D72-1,F72/D72-1),"")
A73: 218 | B73: ftns | C73: 45699 | D73: 1.67 | E73: 1.95 | F73: 1.56 | G73: =INDEX('اسعار الاسهم'!A:B,MATCH(B73,'اسعار الاسهم'!K:K,0),2) -> 1.15 | H73: =IF(P73="", G73/D73-1,"") -> -0.31137725 | I73: =IF(P73="", E73/G73-1,"") -> 0.69565217 | J73: =IF(P73="", 1-F73/G73,"") -> -0.35652174 | K73: =E73/F73-1 -> 0.25 | L73: =IF( S73="",I73/J73,"") | M73: =IF(P73="",IF(I73<J73,"up","down"),"") -> down | N73: =COUNTIFS(B:B,B73,Q:Q,"") -> 1 | O73: =COUNTIFS(B:B,B73) -> 4 | Q73: 45712 | R73: =IF(Q73, Q73-C73+2,"") -> 15 | S73: 166 | T73: =IF(NOT( S73=""),IF(P73=1,E73/D73-1,F73/D73-1),"") -> -0.065868263
A74: 196 | B74: spmd | C74: 45692 | D74: 0.405 | E74: 0.46 | F74: 0.375 | G74: =INDEX('اسعار الاسهم'!A:B,MATCH(B74,'اسعار الاسهم'!K:K,0),2) -> 0.39 | H74: =IF(P74="", G74/D74-1,"") -> -0.037037037 | I74: =IF(P74="", E74/G74-1,"") -> 0.17948718 | J74: =IF(P74="", 1-F74/G74,"") -> 0.038461538 | K74: =E74/F74-1 -> 0.22666667 | L74: =IF( S74="",I74/J74,"") -> 4.6666667 | M74: =IF(P74="",IF(I74<J74,"up","down"),"") -> down | N74: =COUNTIFS(B:B,B74,Q:Q,"") -> 1 | O74: =COUNTIFS(B:B,B74) -> 1 | R74: =IF(Q74, Q74-C74+2,"") | T74: =IF(NOT( S74=""),IF(P74=1,E74/D74-1,F74/D74-1),"")
A75: 297 | B75: niph | C75: 45729 | D75: 51.5 | E75: 57.5 | F75: 47 | G75: =INDEX('اسعار الاسهم'!A:B,MATCH(B75,'اسعار الاسهم'!K:K,0),2) -> 156.04 | H75: =IF(P75="", G75/D75-1,"") -> 2.0299029 | I75: =IF(P75="", E75/G75-1,"") -> -0.63150474 | J75: =IF(P75="", 1-F75/G75,"") -> 0.69879518 | K75: =E75/F75-1 -> 0.22340426 | L75: =IF( S75="",I75/J75,"") -> -0.90370506 | M75: =IF(P75="",IF(I75<J75,"up","down"),"") -> up | N75: =COUNTIFS(B:B,B75,Q:Q,"") -> 1 | O75: =COUNTIFS(B:B,B75) -> 1 | R75: =IF(Q75, Q75-C75+2,"") | T75: =IF(NOT( S75=""),IF(P75=1,E75/D75-1,F75/D75-1),"")
A76: 2 | B76: egch | C76: 45610 | D76: 8.43 | E76: 9.5 | F76: 7.95 | G76: =INDEX('اسعار الاسهم'!A:B,MATCH(B76,'اسعار الاسهم'!K:K,0),2) -> 14.13 | H76: =IF(P76="", G76/D76-1,"") | I76: =IF(P76="", E76/G76-1,"") | J76: =IF(P76="", 1-F76/G76,"") | K76: =E76/F76-1 -> 0.19496855 | L76: =IF( S76="",I76/J76,"") | M76: =IF(P76="",IF(I76<J76,"up","down"),"") | N76: =COUNTIFS(B:B,B76,Q:Q,"") -> 0 | O76: =COUNTIFS(B:B,B76) -> 1 | P76: 0 | Q76: 45621 | R76: =IF(Q76, Q76-C76+2,"") -> 13 | S76: 2 | T76: =IF(NOT( S76=""),IF(P76=1,E76/D76-1,F76/D76-1),"") -> -0.056939502
A77: 4 | B77: icid | C77: 45613 | D77: 4 | E77: 4.75 | F77: 3.71 | G77: =INDEX('اسعار الاسهم'!A:B,MATCH(B77,'اسعار الاسهم'!K:K,0),2) -> 4.54 | H77: =IF(P77="", G77/D77-1,"") | I77: =IF(P77="", E77/G77-1,"") | J77: =IF(P77="", 1-F77/G77,"") | K77: =E77/F77-1 -> 0.28032345 | L77: =IF( S77="",I77/J77,"") | M77: =IF(P77="",IF(I77<J77,"up","down"),"") | N77: =COUNTIFS(B:B,B77,Q:Q,"") -> 0 | O77: =COUNTIFS(B:B,B77) -> 3 | P77: 0 | Q77: 45621 | R77: =IF(Q77, Q77-C77+2,"") -> 10 | S77: 1 | T77: =IF(NOT( S77=""),IF(P77=1,E77/D77-1,F77/D77-1),"") -> -0.0725
A78: 12 | B78: lcsw | C78: 45617 | D78: 25.12 | E78: 28.5 | F78: 23.75 | G78: =INDEX('اسعار الاسهم'!A:B,MATCH(B78,'اسعار الاسهم'!K:K,0),2) -> 26.64 | H78: =IF(P78="", G78/D78-1,"") | I78: =IF(P78="", E78/G78-1,"") | J78: =IF(P78="", 1-F78/G78,"") | K78: =E78/F78-1 -> 0.2 | L78: =IF( S78="",I78/J78,"") | M78: =IF(P78="",IF(I78<J78,"up","down"),"") | N78: =COUNTIFS(B:B,B78,Q:Q,"") -> 0 | O78: =COUNTIFS(B:B,B78) -> 3 | P78: 1 | Q78: 45622 | R78: =IF(Q78, Q78-C78+2,"") -> 7 | S78: 5 | T78: =IF(NOT( S78=""),IF(P78=1,E78/D78-1,F78/D78-1),"") -> 0.13455414
A79: 6 | B79: ismq | C79: 45613 | D79: 4.43 | E79: 5.3 | F79: 4.2 | G79: =INDEX('اسعار الاسهم'!A:B,MATCH(B79,'اسعار الاسهم'!K:K,0),2) -> 7.33 | H79: =IF(P79="", G79/D79-1,"") | I79: =IF(P79="", E79/G79-1,"") | J79: =IF(P79="", 1-F79/G79,"") | K79: =E79/F79-1 -> 0.26190476 | L79: =IF( S79="",I79/J79,"") | M79: =IF(P79="",IF(I79<J79,"up","down"),"") | N79: =COUNTIFS(B:B,B79,Q:Q,"") -> 0 | O79: =COUNTIFS(B:B,B79) -> 6 | P79: 0 | Q79: 45622 | R79: =IF(Q79, Q79-C79+2,"") -> 11 | S79: 3 | T79: =IF(NOT( S79=""),IF(P79=1,E79/D79-1,F79/D79-1),"") -> -0.051918736
A80: 9 | B80: orwe | C80: 45614 | D80: 26.85 | E80: 30.5 | F80: 25.5 | G80: =INDEX('اسعار الاسهم'!A:B,MATCH(B80,'اسعار الاسهم'!K:K,0),2) -> 21.84 | H80: =IF(P80="", G80/D80-1,"") | I80: =IF(P80="", E80/G80-1,"") | J80: =IF(P80="", 1-F80/G80,"") | K80: =E80/F80-1 -> 0.19607843 | L80: =IF( S80="",I80/J80,"") | M80: =IF(P80="",IF(I80<J80,"up","down"),"") | N80: =COUNTIFS(B:B,B80,Q:Q,"") -> 0 | O80: =COUNTIFS(B:B,B80) -> 5 | P80: 0 | Q80: 45622 | R80: =IF(Q80, Q80-C80+2,"") -> 10 | S80: 4 | T80: =IF(NOT( S80=""),IF(P80=1,E80/D80-1,F80/D80-1),"") -> -0.05027933
A81: 18 | B81: ismq | C81: 45620 | D81: 4.32 | E81: 4.8 | F81: 4.15 | G81: =INDEX('اسعار الاسهم'!A:B,MATCH(B81,'اسعار الاسهم'!K:K,0),2) -> 7.33 | H81: =IF(P81="", G81/D81-1,"") | I81: =IF(P81="", E81/G81-1,"") | J81: =IF(P81="", 1-F81/G81,"") | K81: =E81/F81-1 -> 0.15662651 | L81: =IF( S81="",I81/J81,"") | M81: =IF(P81="",IF(I81<J81,"up","down"),"") | N81: =COUNTIFS(B:B,B81,Q:Q,"") -> 0 | O81: =COUNTIFS(B:B,B81) -> 6 | P81: 0 | Q81: 45623 | R81: =IF(Q81, Q81-C81+2,"") -> 5 | S81: 6 | T81: =IF(NOT( S81=""),IF(P81=1,E81/D81-1,F81/D81-1),"") -> -0.039351852
A82: 5 | B82: spin | C82: 45613 | D82: 8.55 | E82: 9.6 | F82: 8 | G82: =INDEX('اسعار الاسهم'!A:B,MATCH(B82,'اسعار الاسهم'!K:K,0),2) -> 14.35 | H82: =IF(P82="", G82/D82-1,"") | I82: =IF(P82="", E82/G82-1,"") | J82: =IF(P82="", 1-F82/G82,"") | K82: =E82/F82-1 -> 0.2 | L82: =IF( S82="",I82/J82,"") | M82: =IF(P82="",IF(I82<J82,"up","down"),"") | N82: =COUNTIFS(B:B,B82,Q:Q,"") -> 1 | O82: =COUNTIFS(B:B,B82) -> 4 | P82: 0 | Q82: 45623 | R82: =IF(Q82, Q82-C82+2,"") -> 12 | S82: 9 | T82: =IF(NOT( S82=""),IF(P82=1,E82/D82-1,F82/D82-1),"") -> -0.064327485
A83: 20 | B83: spin | C83: 45621 | D83: 8.65 | E83: 9.95 | F83: 8 | G83: =INDEX('اسعار الاسهم'!A:B,MATCH(B83,'اسعار الاسهم'!K:K,0),2) -> 14.35 | H83: =IF(P83="", G83/D83-1,"") | I83: =IF(P83="", E83/G83-1,"") | J83: =IF(P83="", 1-F83/G83,"") | K83: =E83/F83-1 -> 0.24375 | L83: =IF( S83="",I83/J83,"") | M83: =IF(P83="",IF(I83<J83,"up","down"),"") | N83: =COUNTIFS(B:B,B83,Q:Q,"") -> 1 | O83: =COUNTIFS(B:B,B83) -> 4 | P83: 0 | Q83: 45623 | R83: =IF(Q83, Q83-C83+2,"") -> 4 | S83: 8 | T83: =IF(NOT( S83=""),IF(P83=1,E83/D83-1,F83/D83-1),"") -> -0.075144509
A84: 19 | B84: sdti | C84: 45620 | D84: 19.05 | E84: 22 | F84: 18 | G84: =INDEX('اسعار الاسهم'!A:B,MATCH(B84,'اسعار الاسهم'!K:K,0),2) -> 43.88 | H84: =IF(P84="", G84/D84-1,"") | I84: =IF(P84="", E84/G84-1,"") | J84: =IF(P84="", 1-F84/G84,"") | K84: =E84/F84-1 -> 0.22222222 | L84: =IF( S84="",I84/J84,"") | M84: =IF(P84="",IF(I84<J84,"up","down"),"") | N84: =COUNTIFS(B:B,B84,Q:Q,"") -> 0 | O84: =COUNTIFS(B:B,B84) -> 2 | P84: 0 | Q84: 45623 | R84: =IF(Q84, Q84-C84+2,"") -> 5 | S84: 7 | T84: =IF(NOT( S84=""),IF(P84=1,E84/D84-1,F84/D84-1),"") -> -0.05511811
A85: 7 | B85: icfc | C85: 45613 | D85: 10.75 | E85: 12.5 | F85: 10.25 | G85: =INDEX('اسعار الاسهم'!A:B,MATCH(B85,'اسعار الاسهم'!K:K,0),2) -> 15.8 | H85: =IF(P85="", G85/D85-1,"") | I85: =IF(P85="", E85/G85-1,"") | J85: =IF(P85="", 1-F85/G85,"") | K85: =E85/F85-1 -> 0.2195122 | L85: =IF( S85="",I85/J85,"") | M85: =IF(P85="",IF(I85<J85,"up","down"),"") | N85: =COUNTIFS(B:B,B85,Q:Q,"") -> 0 | O85: =COUNTIFS(B:B,B85) -> 3 | P85: 0 | Q85: 45624 | R85: =IF(Q85, Q85-C85+2,"") -> 13 | S85: 10 | T85: =IF(NOT( S85=""),IF(P85=1,E85/D85-1,F85/D85-1),"") -> -0.046511628
A86: 22 | B86: epco | C86: 45622 | D86: 4.65 | E86: 5.5 | F86: 4.4 | G86: =INDEX('اسعار الاسهم'!A:B,MATCH(B86,'اسعار الاسهم'!K:K,0),2) -> 8.94 | H86: =IF(P86="", G86/D86-1,"") | I86: =IF(P86="", E86/G86-1,"") | J86: =IF(P86="", 1-F86/G86,"") | K86: =E86/F86-1 -> 0.25 | L86: =IF( S86="",I86/J86,"") | M86: =IF(P86="",IF(I86<J86,"up","down"),"") | N86: =COUNTIFS(B:B,B86,Q:Q,"") -> 0 | O86: =COUNTIFS(B:B,B86) -> 1 | P86: 0 | Q86: 45624 | R86: =IF(Q86, Q86-C86+2,"") -> 4 | S86: 11 | T86: =IF(NOT( S86=""),IF(P86=1,E86/D86-1,F86/D86-1),"") -> -0.053763441
